Workbook

Sheet Resumé
A1: BESS ved Ringkøbing Fjernvarme: tidlig investeringsberegning
A2: Udarbejdet 13.10.2026 til Kristian Hautorp. Status: TIL GODKENDELSE. Tidlig skrivebordsberegning uden data fra Ringkøbing Fjernvarme (RFV), uden tilbud og uden afklaring med netselskab og Skattestyrelsen.
A4: Nøgletal | B4: Pessimistisk | C4: Base | D4: Optimistisk
A5: Effekt (MW) | B5: =Pessimistisk!$B$5 -> 10 | C5: =Base!$B$5 -> 10 | D5: =Optimistisk!$B$5 -> 10
A6: Varighed (timer) | B6: =Pessimistisk!$B$6 -> 2 | C6: =Base!$B$6 -> 2 | D6: =Optimistisk!$B$6 -> 2
A7: Samlet investering (EUR) | B7: =Pessimistisk!$B$86 -> 8200000 | C7: =Base!$B$86 -> 6250000 | D7: =Optimistisk!$B$86 -> 5150000
A8: Investering pr. kWh (EUR) | B8: =Pessimistisk!$B$87 -> 410 | C8: =Base!$B$87 -> 312.5 | D8: =Optimistisk!$B$87 -> 257.5
A9: Investering pr. MW (EUR) | B9: =Pessimistisk!$B$88 -> 820000 | C9: =Base!$B$88 -> 625000 | D9: =Optimistisk!$B$88 -> 515000
A10: Markedsindtægt år 1 pr. MW (EUR) | B10: =Pessimistisk!$B$89 -> 62209.301 | C10: =Base!$B$89 -> 102775.34 | D10: =Optimistisk!$B$89 -> 172202.52
A11: EBITDA år 1 (EUR) | B11: =Pessimistisk!$B$90 -> -38032.217 | C11: =Base!$B$90 -> 526633.09 | D11: =Optimistisk!$B$90 -> 1288032
A12: EBITDA år 1 / investering | B12: =Pessimistisk!$B$92 -> -0.0046380752 | C12: =Base!$B$92 -> 0.084261294 | D12: =Optimistisk!$B$92 -> 0.2501033
A13: IRR før skat (ugearet) | B13: =Pessimistisk!$B$82 -> negativ | C13: =Base!$B$82 -> -0.0065111185 | D13: =Optimistisk!$B$82 -> 0.23418177
A14: IRR efter skat (ugearet) | B14: =Pessimistisk!$B$83 -> negativ | C14: =Base!$B$83 -> -0.0065111185 | D14: =Optimistisk!$B$83 -> 0.20329599
A15: NPV efter skat ved 8 % (EUR) | B15: =Pessimistisk!$B$84 -> -9919272.8 | C15: =Base!$B$84 -> -2629940.7 | D15: =Optimistisk!$B$84 -> 4038497.4
A16: Simpel tilbagebetalingstid (år) | B16: =Pessimistisk!$B$85 -> > levetid | C16: =Base!$B$85 -> > levetid | D16: =Optimistisk!$B$85 -> 5
A18: Hvad flytter base-scenariet? (én ændring ad gangen, IRR efter skat)
A19: Statiske tal beregnet 13.10.2026 med scripts/kontroller_model.py (samme logik som arkene). Opdateres ikke automatisk.
A20: Base som beregnet | B20: ca. -1 %
A21: Systemydelser holder dagens niveau (70k EUR/MW i stedet for 30k) | B21: ca. 6 %
A22: Investering 250 EUR/kWh i stedet for ca. 310 | B22: ca. 2 %
A23: Ingen betaling til RFV for netadgang | B23: ca. 1 %
A24: Intraday/ubalance-tillæg 20 % i stedet for 10 % | B24: ca. 1 %
A25: Levetid 20 år i stedet for 15 | B25: ca. 1 %
A26: 4 timer i stedet for 2 timer | B26: ca. -2 %
A27: Fuld elafgift 60,9 øre/kWh på opladning | B27: negativ (casen falder)
A28: Krav for 8 % efter skat: investering | B28: ca. 190 EUR/kWh
A29: Krav for 8 % efter skat: markedsindtægt | B29: ca. +43 %
A31: Sådan læses beregningen
A32: Indtjeningen bygger på en backtest af faktiske DK1-priser fra Energinet (okt. 2025 til okt. 2026), korrigeret for at et rigtigt batteri ikke kender priserne på forhånd. Systemydelser er sat lavere end i dag, fordi priserne allerede er faldet kraftigt, efterhånden som flere batterier er kommet på markedet. Se arket Backtest.
A33: Base-scenariet er bevidst konservativt. Resultatet er meget følsomt over for investering og markedsindtægt; se arket Følsomhed.
A35: Stop-risici (skal afklares før der bruges penge på udvikling)
A36: 1. Elafgift: modellen antager godtgørelse ned til 0,4 øre/kWh på opladning. Hvis den fulde afgift (60,9 øre/kWh fra 2028) rammer batteriet, falder business casen. Kræver bindende svar.
A37: 2. Netadgang: om netselskabet tillader et batteri (evt. ejet af et andet selskab end RFV) bag RFV's tilslutning, og om eksisterende kapacitet kan bruges uden nyt tilslutningsbidrag.
A38: 3. Samtidighed: elkedel og gasmotorer bruger tilslutningen i de samme timer, som batteriet vil bruge. Kræver RFV's 15-min. måledata og tilslutningsaftale.
A39: 4. Investering: base svarer til ca. 300 EUR/kWh all-in for 2h. Skal erstattes af 2-3 indikative tilbud.
A40: 5. Selskabsform: RFV er et forbrugerejet a.m.b.a. under varmeforsyningsloven. Deltagelse skal formentlig ske via et separat selskab. Skal verificeres juridisk.
A42: Bemærk: modellen regner ugearet projektafkast. Gæld hæver kun egenkapitalafkastet, hvis projektafkastet ligger over lånerenten.

Sheet Forudsætninger
A1: Forudsætninger: BESS ved Ringkøbing Fjernvarme (tidlig beregning, til godkendelse)
A2: Udarbejdet 13.10.2026. Gule celler er input og kan ændres; scenarie-arkene regner automatisk. Status: Data = fra kilde, Estimat = min vurdering, Skal verificeres / Ved ikke = skal afklares før beslutning.
A4: Nøgle | B4: Parameter | C4: Enhed | D4: Pessimistisk | E4: Base | F4: Optimistisk | G4: Status | H4: Kilde / begrundelse
A5: Projekt
A6: mw | B6: Batteriets effekt | C6: MW | D6: 10 | E6: 10 | F6: 10 | G6: Ved ikke | H6: Referencestørrelse. Den reelle størrelse afhænger af ledig import- og eksportkapacitet i RFV's tilslutning, som ikke er kendt.
A7: dur | B7: Varighed (1, 2 eller 4 timer) | C7: timer | D7: 2 | E7: 2 | F7: 2 | G7: Estimat | H7: Backtesten findes for 1, 2 og 4 timer (se arket Backtest). 4 timer giver mest indtjening pr. MW nettilslutning, men højere capex.
A8: cod | B8: Første driftsår (COD) | C8: år | D8: 2028 | E8: 2028 | F8: 2028 | G8: Estimat | H8: Antaget: udvikling, netaftale, indkøb og byggeri ca. 15-24 mdr. fra beslutning.
A9: life | B9: Økonomisk levetid | C9: år | D9: 15 | E9: 15 | F9: 15 | G9: Estimat | H9: Ingen restværdi og ingen udvidelse (augmentation) antaget. Maks. 20 år i modellen.
A10: avail | B10: Tilgængelighed inkl. konflikt med RFV's elkedel og gasmotorer | C10: % | D10: 0.85 | E10: 0.92 | F10: 0.97 | G10: Estimat | H10: Batteriet deler tilslutning med elkedel (import) og gasmotorer (eksport), der bruger kapaciteten i de samme timer. Skal afklares med RFV-data.
A11: fade | B11: Kapacitetstab pr. år (påvirker arbitrage) | C11: %/år | D11: 0.025 | E11: 0.02 | F11: 0.015 | G11: Estimat | H11: Typisk for LFP ved ca. 1 cyklus/døgn.
A12: rte | B12: Round-trip-virkningsgrad (AC-AC) | C12: % | D12: 0.86 | E12: 0.86 | F12: 0.86 | G12: Estimat | H12: Samme værdi som i backtesten.
A13: Anlægsomkostninger
A14: ckw | B14: Effektrelateret capex (PCS, trafo, HV/MV, BoP, EPC) | C14: EUR/kW | D14: 250 | E14: 200 | F14: 160 | G14: Estimat | H14: Kalibreret så 2h all-in ligger på 375/300/250 EUR/kWh. Ref.: Modo Energy (16.03.2026) 700k EUR/MW for 2h i Tyskland (scope ikke oplyst); BNEF Cost Survey 2025 Europa turnkey 177 USD/kWh ekskl. EPC og nettilslutning (via Energy-Storage.news, dec. 2025).
A15: ckwh | B15: Energirelateret capex (batteriblokke inkl. montage) | C15: EUR/kWh | D15: 250 | E15: 200 | F15: 170 | G15: Estimat | H15: Se ovenfor. Skal erstattes af tilbud.
A16: dev | B16: Udvikling, rådgivning, netstudier, finansiering | C16: EUR | D16: 400000 | E16: 250000 | F16: 150000 | G16: Estimat | H16: Juridisk, skat (bindende svar), netselskab, teknisk DD.
A17: conn | B17: Tilslutningsbidrag / ombygning af tilslutning | C17: EUR | D17: 300000 | E17: 0 | F17: 0 | G17: Skal verificeres | H17: Elnet.dk/Green Power Denmark: intet tilslutningsbidrag, hvis batteriet bruger eksisterende kapacitet uden at der søges ny. Pessimistisk: netselskabet kræver ombygning eller udvidelse.
A18: Indtægter (2026-priser)
A19: lvl | B19: Arbitrage-niveau ift. backtest seneste 12 mdr. | C19: faktor | D19: 0.836 | E19: 1 | F19: 1.126 | G19: Data | H19: Pess. = kalenderår 2025, Base = okt. 2025 til okt. 2026, Opt. = 2026 år-til-dato (annualiseret). 2h-backtest, se arket Backtest.
A20: cap | B20: Realiseringsgrad ift. perfekt forudsigelse (day-ahead) | C20: % | D20: 0.8 | E20: 0.85 | F20: 0.9 | G20: Estimat | H20: Backtesten antager perfekt kendskab til priserne.
A21: idu | B21: Tillæg fra intraday/ubalance | C21: % | D21: 0 | E21: 0.1 | F21: 0.2 | G21: Estimat | H21: Ikke backtestet. Kan være væsentligt i DK1, men usikkert.
A22: arbtr | B22: Real udvikling i arbitrage-indtjening | C22: %/år | D22: -0.03 | E22: -0.01 | F22: 0.01 | G22: Estimat | H22: Flere batterier presser spreads; mere sol og vind øger dem. Spreads i 2026 er høje sammen med et højt prisniveau.
A23: anc1 | B23: Systemydelser (aFRR + mFRR), netto merindtægt år 1 | C23: EUR/MW/år | D23: 15000 | E23: 30000 | F23: 70000 | G23: Data + estimat | H23: Backtest (2h, seneste 12 mdr.): merindtægt ift. ren arbitrage = 156k ved fulde priser, 70k ved 50 % og 30k ved 25 %. Priserne i Q3 2026 ligger på ca. 50 % af 12-mdr.-gennemsnittet. Base antager yderligere halvering frem til 2028.
A24: anctr | B24: Udvikling i systemydelser | C24: %/år | D24: -0.15 | E24: -0.05 | F24: -0.05 | G24: Estimat | H24: aFRR op i DK1 er faldet fra ca. 70 til ca. 6-10 EUR/MW/h (Q4 2024 til 2026).
A25: ancfl | B25: Gulv for systemydelser | C25: EUR/MW/år | D25: 0 | E25: 10000 | F25: 20000 | G25: Estimat
A26: Nettariffer og afgifter (betales af batteriet)
A27: t_en | B27: Energinet forbrugstarif (net + system) | C27: øre/kWh | D27: 12.5 | E27: 10.5 | F27: 10.5 | G27: Data | H27: Energinet-pressemeddelelse 04.09.2026: 10,5 øre/kWh i 2027 og loft på 12,5 øre/kWh frem til 2030.
A28: t_dso | B28: Netselskabets forbrugstarif (gns. i ladetimer) | C28: øre/kWh | D28: 5 | E28: 3 | F28: 2 | G28: Skal verificeres | H28: Netselskab og tarif for RFV's tilslutning er ikke kendt. Elnet.dk: batterier betaler både forbrugs- og indfødningstarif.
A29: t_afg | B29: Elafgift på opladning efter godtgørelse | C29: øre/kWh | D29: 0.4 | E29: 0.4 | F29: 0.4 | G29: Skal verificeres | H29: KRITISK. Lov nr. 1775 af 29.12.2025: 0,8 øre/kWh i 2026-27, derefter 60,9 øre (2015-niveau). Antaget: momsreg. virksomhed får godtgørelse ned til 0,4 øre. Gælder det ikke for et batteri fra 2028, falder business casen. Kræver bindende svar.
A30: t_enp | B30: Energinet indfødnings- og balancetarif | C30: øre/kWh | D30: 0.92 | E30: 0.92 | F30: 0.92 | G30: Data | H30: Energinet-pressemeddelelse 04.09.2026: 0,5 + 0,42 øre/kWh (2027).
A31: t_dsop | B31: Netselskabets indfødningstarif | C31: øre/kWh | D31: 0.5 | E31: 0.5 | F31: 0.5 | G31: Skal verificeres | H31: Estimat.
A32: fx | B32: Valutakurs | C32: DKK/EUR | D32: 7.46 | E32: 7.46 | F32: 7.46 | G32: Data | H32: Fast kurs (ERM2).
A33: Driftsomkostninger (2026-priser)
A34: om | B34: Drift og vedligehold (LTSA) | C34: % af anlægscapex | D34: 0.02 | E34: 0.015 | F34: 0.012 | G34: Estimat
A35: ins | B35: Forsikring | C35: % af anlægscapex | D35: 0.005 | E35: 0.004 | F35: 0.003 | G35: Estimat
A36: fee | B36: Optimerings-/aggregatorfee | C36: % af markedsindtægt | D36: 0.15 | E36: 0.1 | F36: 0.07 | G36: Estimat | H36: Alternativ: fast fee pr. MW eller gevinstdeling.
A37: rfv | B37: Betaling til RFV for netadgang og areal | C37: EUR/MW/år | D37: 10000 | E37: 6000 | F37: 3000 | G37: Ved ikke | H37: Til forhandling. Kan også erstattes af ejerandel til RFV.
A38: fix | B38: Faste omkostninger (adm., revision, BRP, SCADA, abonnementer) | C38: EUR/år | D38: 60000 | E38: 40000 | F38: 30000 | G38: Estimat
A39: Økonomi og skat
A40: infl | B40: Inflation (indeksering fra 2026-niveau) | C40: %/år | D40: 0.02 | E40: 0.02 | F40: 0.02 | G40: Estimat
A41: tax | B41: Selskabsskat | C41: % | D41: 0.22 | E41: 0.22 | F41: 0.22 | G41: Data | H41: Dansk selskabsskat.
A42: saldo | B42: Skattemæssig afskrivning (saldo) | C42: %/år | D42: 0.25 | E42: 0.25 | F42: 0.25 | G42: Skal verificeres | H42: Antaget almindelige driftsmidler (afskrivningsloven). Underskud fremføres; 60 %-begrænsningen er ikke modelleret.
A43: disc | B43: Diskonteringsrente til NPV (nominel) | C43: % | D43: 0.08 | E43: 0.08 | F43: 0.08 | G43: Estimat | H43: Indikativt afkastkrav for merchant-BESS.

Sheet Backtest
A1: Backtest af batteri i DK1 på Energinet-data (perfekt forudsigelse)
A2: Beregnet 13.10.2026 med scripts/backtest_dk1.py på data fra Energinets Energi Data Service (Elspotprices, DayAheadPrices, AfrrReservesNordic, FcrDK1, mFRRCapacityMarket).
A3: Metode: lineær optimering pr. døgn for 1 MW. Round-trip 86 %, maks. 1,5 cyklus/døgn, SoC 50 % ved døgnstart og -slut. Reserver kræver energi til 60 min (aFRR/mFRR) og 30 min (FCR).
A4: Netomkostning i optimeringen: 18,6 EUR/MWh på opladning og 1,9 EUR/MWh på afladning (svarer til base-tarifferne). Kvartersopløsning fra 1.10.2025, timeopløsning før.
A5: Perfekt forudsigelse overvurderer indtjeningen; det korrigeres med realiseringsgraden i Forudsætninger. Ubegrænset reservevolumen er urealistisk i DK1 (lille marked), se mætningsvarianter.
A7: A. Indtjening pr. MW pr. år, 2h-batteri (EUR, annualiseret)
A8: Periode | B8: Strategi | C8: Arbitrage brutto | D8: Netomkostning | E8: aFRR | F8: FCR | G8: mFRR | H8: Netto | I8: MWh afladet | J8: Dage
A9: Kalenderår 2024 | B9: Kun day-ahead-arbitrage | C9: 55896.431 | D9: -16988.641 | E9: 0 | F9: 0 | G9: 0 | H9: 38907.79 | I9: 722.06342 | J9: 366
A10: Kalenderår 2024 | B10: Day-ahead + alle reserver (ubegrænset volumen) | C10: 18790.452 | D10: -4376.3314 | E10: 176256.11 | F10: 106904.27 | G10: 35416.372 | H10: 332990.87 | I10: 186.00598 | J10: 366
A11: Kalenderår 2025 | B11: Kun day-ahead-arbitrage | C11: 69181.439 | D11: -18189.468 | E11: 0 | F11: 0 | G11: 0 | H11: 50991.971 | I11: 773.10185 | J11: 365
A12: Kalenderår 2025 | B12: Day-ahead + alle reserver (ubegrænset volumen) | C12: 17592.163 | D12: -3897.1289 | E12: 268953.5 | F12: 60227.864 | G12: 57669.762 | H12: 400546.16 | I12: 165.63857 | J12: 365
A13: 13.10.2025 til 12.10.2026 | B13: Kun day-ahead-arbitrage | C13: 82753.375 | D13: -18323.839 | E13: 0 | F13: 0 | G13: 0 | H13: 64429.536 | I13: 778.81296 | J13: 365
A14: 13.10.2025 til 12.10.2026 | B14: Day-ahead + alle reserver (ubegrænset volumen) | C14: 30214.333 | D14: -5765.2906 | E14: 85907.587 | F14: 99818.091 | G14: 76572.664 | H14: 286747.38 | I14: 245.04052 | J14: 365
A15: 2026 år-til-dato | B15: Kun day-ahead-arbitrage | C15: 93165.726 | D15: -19266.565 | E15: 0 | F15: 0 | G15: 0 | H15: 73899.16 | I15: 818.8814 | J15: 285
A16: 2026 år-til-dato | B16: Day-ahead + alle reserver (ubegrænset volumen) | C16: 36245.029 | D16: -6661.6658 | E16: 63004.575 | F16: 119102.9 | G16: 78613.162 | H16: 290304 | I16: 283.13891 | J16: 285
A18: B. Varighed, kun day-ahead, seneste 12 mdr. (bruges af modellen)
A19: Varighed (timer) | B19: Kilde | C19: Arbitrage brutto EUR/MW/år | D19: MWh afladet pr. MW/år | E19: Netto EUR/MW/år
A20: 1 | B20: backtest_varianter.py | C20: 46403 | D20: 425 | E20: 36404
A21: 2 | B21: backtest_dk1.py | C21: 82753.375 | D21: 778.81296 | E21: 64429.536
A22: 4 | B22: backtest_varianter.py | C22: 135158 | D22: 1302 | E22: 104536
A24: C. Mætning af systemydelser: 2h, seneste 12 mdr., aFRR + mFRR (uden FCR), reservepriser skaleret
A25: Reservepris-faktor | B25: Arbitrage brutto | C25: Netomkostning | D25: aFRR | E25: mFRR | F25: Netto | G25: Merindtægt ift. ren arbitrage
A26: 1 | B26: 54252 | C26: -11364 | D26: 95069 | E26: 82536 | F26: 220493 | G26: 156063.46
A27: 0.5 | B27: 64544 | C27: -13162 | D27: 44689 | E27: 37960 | F27: 134031 | G27: 69601.464
A28: 0.25 | B28: 72429 | C28: -14877 | D28: 20003 | E28: 16979 | F28: 94534 | G28: 30104.464
A30: D. DK1 pr. kvartal: prisspænd og reservepriser (gennemsnit). Q4 2026 er kun 1.-13. oktober.
A31: Kvartal | B31: Dagligt spænd top-2h minus bund-2h (EUR/MWh) | C31: Gns. spotpris (EUR/MWh) | D31: aFRR op (EUR/MW/h) | E31: aFRR ned (EUR/MW/h) | F31: FCR DK1 (EUR/MW/h) | G31: mFRR op (EUR/MW/h) | H31: aFRR op behov (MW) | I31: aFRR ned behov (MW) | J31: FCR fra danske enheder (MW) | K31: mFRR op behov (MW)
A32: 2023Q1 | B32: 76.9 | C32: 109.6 | F32: 16.4 | J32: 1.2
A33: 2023Q2 | B33: 86.7 | C33: 87.4 | F33: 9.8 | G33: 0.6 | J33: 0.8
A34: 2023Q3 | B34: 109.8 | C34: 78.4 | F34: 9.7 | G34: 7.4 | J34: 1.8
A35: 2023Q4 | B35: 74 | C35: 72.4 | F35: 15.3 | G35: 1.6 | J35: 3.8
A36: 2024Q1 | B36: 47.7 | C36: 65 | F36: 9.2 | G36: 4.4 | J36: 2.9 | K36: 284
A37: 2024Q2 | B37: 95 | C37: 60.5 | F37: 21.8 | G37: 0.7 | J37: 3.8 | K37: 289.4
A38: 2024Q3 | B38: 122.5 | C38: 68.9 | F38: 21.1 | G38: 12 | J38: 3 | K38: 313.1
A39: 2024Q4 | B39: 105.2 | C39: 88.1 | D39: 70.3 | E39: 13.3 | F39: 12.9 | G39: 6.1 | J39: 2 | K39: 302.8
A40: 2025Q1 | B40: 99.8 | C40: 97.9 | D40: 41.6 | E40: 1.3 | F40: 10.9 | G40: 15 | J40: 2.8 | K40: 317
A41: 2025Q2 | B41: 129.4 | C41: 66 | D41: 46.3 | E41: 1.1 | F41: 22.4 | G41: 4.5 | J41: 8.8 | K41: 292.3
A42: 2025Q3 | B42: 123.6 | C42: 76.3 | D42: 35.3 | E42: 0.5 | F42: 16.9 | G42: 12.3 | H42: 99.8 | I42: 99.8 | J42: 10.4 | K42: 262.7
A43: 2025Q4 | B43: 75.7 | C43: 84.5 | D43: 21.8 | E43: 0.3 | F43: 10.5 | G43: 13.4 | H43: 100 | I43: 100 | J43: 7.7 | K43: 351.1
A44: 2026Q1 | B44: 84.8 | C44: 99.9 | D44: 15.3 | E44: 0.6 | F44: 11.8 | G44: 17.9 | H44: 95.4 | I44: 68.9 | J44: 3.8 | K44: 322.1
A45: 2026Q2 | B45: 156.2 | C45: 97.8 | D45: 13.8 | E45: 0.1 | F45: 23.4 | G45: 15 | H45: 92.5 | I45: 20 | J45: 8.3 | K45: 366.9
A46: 2026Q3 | B46: 168.6 | C46: 122.5 | D46: 6.2 | E46: 0 | F46: 22 | G46: 7 | H46: 90 | I46: 20 | J46: 8 | K46: 310.1
A47: 2026Q4 | B47: 147.9 | C47: 152.5 | D47: 10.1 | E47: 0 | F47: 19.2 | G47: 6.6 | H47: 90 | I47: 20 | J47: 5.6 | K47: 286.2

Sheet Pessimistisk
A1: Cash flow: Pessimistisk scenarie (EUR, nominelt)
A2: Scenarie-indeks (1 = pess., 2 = base, 3 = opt.) | B2: 1
A4: Forudsætninger for scenariet (hentes fra arket Forudsætninger)
A5: Batteriets effekt [MW] | B5: =INDEX(Forudsætninger!$D$6:$F$6,1,$B$2) -> 10
A6: Varighed (1, 2 eller 4 timer) [timer] | B6: =INDEX(Forudsætninger!$D$7:$F$7,1,$B$2) -> 2
A7: Første driftsår (COD) [år] | B7: =INDEX(Forudsætninger!$D$8:$F$8,1,$B$2) -> 2028
A8: Økonomisk levetid [år] | B8: =INDEX(Forudsætninger!$D$9:$F$9,1,$B$2) -> 15
A9: Tilgængelighed inkl. konflikt med RFV's elkedel og gasmotorer [%] | B9: =INDEX(Forudsætninger!$D$10:$F$10,1,$B$2) -> 0.85
A10: Kapacitetstab pr. år (påvirker arbitrage) [%/år] | B10: =INDEX(Forudsætninger!$D$11:$F$11,1,$B$2) -> 0.025
A11: Round-trip-virkningsgrad (AC-AC) [%] | B11: =INDEX(Forudsætninger!$D$12:$F$12,1,$B$2) -> 0.86
A12: Effektrelateret capex (PCS, trafo, HV/MV, BoP, EPC) [EUR/kW] | B12: =INDEX(Forudsætninger!$D$14:$F$14,1,$B$2) -> 250
A13: Energirelateret capex (batteriblokke inkl. montage) [EUR/kWh] | B13: =INDEX(Forudsætninger!$D$15:$F$15,1,$B$2) -> 250
A14: Udvikling, rådgivning, netstudier, finansiering [EUR] | B14: =INDEX(Forudsætninger!$D$16:$F$16,1,$B$2) -> 400000
A15: Tilslutningsbidrag / ombygning af tilslutning [EUR] | B15: =INDEX(Forudsætninger!$D$17:$F$17,1,$B$2) -> 300000
A16: Arbitrage-niveau ift. backtest seneste 12 mdr. [faktor] | B16: =INDEX(Forudsætninger!$D$19:$F$19,1,$B$2) -> 0.836
A17: Realiseringsgrad ift. perfekt forudsigelse (day-ahead) [%] | B17: =INDEX(Forudsætninger!$D$20:$F$20,1,$B$2) -> 0.8
A18: Tillæg fra intraday/ubalance [%] | B18: =INDEX(Forudsætninger!$D$21:$F$21,1,$B$2) -> 0
A19: Real udvikling i arbitrage-indtjening [%/år] | B19: =INDEX(Forudsætninger!$D$22:$F$22,1,$B$2) -> -0.03
A20: Systemydelser (aFRR + mFRR), netto merindtægt år 1 [EUR/MW/år] | B20: =INDEX(Forudsætninger!$D$23:$F$23,1,$B$2) -> 15000
A21: Udvikling i systemydelser [%/år] | B21: =INDEX(Forudsætninger!$D$24:$F$24,1,$B$2) -> -0.15
A22: Gulv for systemydelser [EUR/MW/år] | B22: =INDEX(Forudsætninger!$D$25:$F$25,1,$B$2) -> 0
A23: Energinet forbrugstarif (net + system) [øre/kWh] | B23: =INDEX(Forudsætninger!$D$27:$F$27,1,$B$2) -> 12.5
A24: Netselskabets forbrugstarif (gns. i ladetimer) [øre/kWh] | B24: =INDEX(Forudsætninger!$D$28:$F$28,1,$B$2) -> 5
A25: Elafgift på opladning efter godtgørelse [øre/kWh] | B25: =INDEX(Forudsætninger!$D$29:$F$29,1,$B$2) -> 0.4
A26: Energinet indfødnings- og balancetarif [øre/kWh] | B26: =INDEX(Forudsætninger!$D$30:$F$30,1,$B$2) -> 0.92
A27: Netselskabets indfødningstarif [øre/kWh] | B27: =INDEX(Forudsætninger!$D$31:$F$31,1,$B$2) -> 0.5
A28: Valutakurs [DKK/EUR] | B28: =INDEX(Forudsætninger!$D$32:$F$32,1,$B$2) -> 7.46
A29: Drift og vedligehold (LTSA) [% af anlægscapex] | B29: =INDEX(Forudsætninger!$D$34:$F$34,1,$B$2) -> 0.02
A30: Forsikring [% af anlægscapex] | B30: =INDEX(Forudsætninger!$D$35:$F$35,1,$B$2) -> 0.005
A31: Optimerings-/aggregatorfee [% af markedsindtægt] | B31: =INDEX(Forudsætninger!$D$36:$F$36,1,$B$2) -> 0.15
A32: Betaling til RFV for netadgang og areal [EUR/MW/år] | B32: =INDEX(Forudsætninger!$D$37:$F$37,1,$B$2) -> 10000
A33: Faste omkostninger (adm., revision, BRP, SCADA, abonnementer) [EUR/år] | B33: =INDEX(Forudsætninger!$D$38:$F$38,1,$B$2) -> 60000
A34: Inflation (indeksering fra 2026-niveau) [%/år] | B34: =INDEX(Forudsætninger!$D$40:$F$40,1,$B$2) -> 0.02
A35: Selskabsskat [%] | B35: =INDEX(Forudsætninger!$D$41:$F$41,1,$B$2) -> 0.22
A36: Skattemæssig afskrivning (saldo) [%/år] | B36: =INDEX(Forudsætninger!$D$42:$F$42,1,$B$2) -> 0.25
A37: Diskonteringsrente til NPV (nominel) [%] | B37: =INDEX(Forudsætninger!$D$43:$F$43,1,$B$2) -> 0.08
A39: Afledte størrelser
A40: Energi (MWh) | B40: =$B$5*$B$6 -> 20
A41: Anlægscapex (effekt + energi) | B41: =$B$5*1000*$B$12+$B$5*$B$6*1000*$B$13 -> 7500000
A42: Samlet investering | B42: =B41+$B$14+$B$15 -> 8200000
A43: Samlet investering pr. kWh | B43: =B42/(B40*1000) -> 410
A44: Samlet investering pr. MW | B44: =B42/$B$5 -> 820000
A45: Arbitrage brutto, backtest (EUR/MW/år) | B45: =INDEX(Backtest!$C$20:$C$22,MATCH($B$6,Backtest!$A$20:$A$22,0)) -> 82753.375
A46: MWh afladet, backtest (pr. MW/år) | B46: =INDEX(Backtest!$D$20:$D$22,MATCH($B$6,Backtest!$A$20:$A$22,0)) -> 778.81296
A47: Omkostning pr. MWh opladet (EUR, 2026-niveau) | B47: =($B$23+$B$24+$B$25)*10/$B$28 -> 23.994638
A48: Omkostning pr. MWh afladet (EUR, 2026-niveau) | B48: =($B$26+$B$27)*10/$B$28 -> 1.9034853
A50: Cash flow
A51: År | C51: 0 | D51: 1 | E51: 2 | F51: 3 | G51: 4 | H51: 5 | I51: 6 | J51: 7 | K51: 8 | L51: 9 | M51: 10 | N51: 11 | O51: 12 | P51: 13 | Q51: 14 | R51: 15 | S51: 16 | T51: 17 | U51: 18 | V51: 19 | W51: 20
A52: Kalenderår | D52: =$B$7+D51-1 -> 2028 | E52: =$B$7+E51-1 -> 2029 | F52: =$B$7+F51-1 -> 2030 | G52: =$B$7+G51-1 -> 2031 | H52: =$B$7+H51-1 -> 2032 | I52: =$B$7+I51-1 -> 2033 | J52: =$B$7+J51-1 -> 2034 | K52: =$B$7+K51-1 -> 2035 | ... W52: =$B$7+W51-1 -> 2047
A53: Drift (1/0) | C53: 0 | D53: =IF(D51<=$B$8,1,0) -> 1 | E53: =IF(E51<=$B$8,1,0) -> 1 | F53: =IF(F51<=$B$8,1,0) -> 1 | G53: =IF(G51<=$B$8,1,0) -> 1 | H53: =IF(H51<=$B$8,1,0) -> 1 | I53: =IF(I51<=$B$8,1,0) -> 1 | J53: =IF(J51<=$B$8,1,0) -> 1 | K53: =IF(K51<=$B$8,1,0) -> 1 | ... W53: =IF(W51<=$B$8,1,0) -> 0
A54: Prisindeks (2026 = 1) | C54: 1 | D54: =(1+$B$34)^(D52-2026) -> 1.0404 | E54: =(1+$B$34)^(E52-2026) -> 1.061208 | F54: =(1+$B$34)^(F52-2026) -> 1.0824322 | G54: =(1+$B$34)^(G52-2026) -> 1.1040808 | H54: =(1+$B$34)^(H52-2026) -> 1.1261624 | I54: =(1+$B$34)^(I52-2026) -> 1.1486857 | J54: =(1+$B$34)^(J52-2026) -> 1.1716594 | K54: =(1+$B$34)^(K52-2026) -> 1.1950926 | ... W54: =(1+$B$34)^(W52-2026) -> 1.5156663
A55: Kapacitetsfaktor | C55: 1 | D55: =(1-$B$10)^(D51-1) -> 1 | E55: =(1-$B$10)^(E51-1) -> 0.975 | F55: =(1-$B$10)^(F51-1) -> 0.950625 | G55: =(1-$B$10)^(G51-1) -> 0.92685938 | H55: =(1-$B$10)^(H51-1) -> 0.90368789 | I55: =(1-$B$10)^(I51-1) -> 0.88109569 | J55: =(1-$B$10)^(J51-1) -> 0.8590683 | K55: =(1-$B$10)^(K51-1) -> 0.83759159 | ... W55: =(1-$B$10)^(W51-1) -> 0.61814121
A56: Arbitrage (day-ahead + intraday) | C56: 0 | D56: =$B$5*$B$45*$B$16*$B$17*(1+$B$18)*(1+$B$19)^(D51-1)*D55*$B$9*D54*D53 -> 489442.01 | E56: =$B$5*$B$45*$B$16*$B$17*(1+$B$18)*(1+$B$19)^(E51-1)*E55*$B$9*E54*E53 -> 472147.58 | F56: =$B$5*$B$45*$B$16*$B$17*(1+$B$18)*(1+$B$19)^(F51-1)*F55*$B$9*F54*F53 -> 455464.25 | G56: =$B$5*$B$45*$B$16*$B$17*(1+$B$18)*(1+$B$19)^(G51-1)*G55*$B$9*G54*G53 -> 439370.42 | H56: =$B$5*$B$45*$B$16*$B$17*(1+$B$18)*(1+$B$19)^(H51-1)*H55*$B$9*H54*H53 -> 423845.26 | I56: =$B$5*$B$45*$B$16*$B$17*(1+$B$18)*(1+$B$19)^(I51-1)*I55*$B$9*I54*I53 -> 408868.69 | J56: =$B$5*$B$45*$B$16*$B$17*(1+$B$18)*(1+$B$19)^(J51-1)*J55*$B$9*J54*J53 -> 394421.32 | K56: =$B$5*$B$45*$B$16*$B$17*(1+$B$18)*(1+$B$19)^(K51-1)*K55*$B$9*K54*K53 -> 380484.44 | ... W56: =$B$5*$B$45*$B$16*$B$17*(1+$B$18)*(1+$B$19)^(W51-1)*W55*$B$9*W54*W53 -> 0
A57: Systemydelser, netto merindtægt | C57: 0 | D57: =$B$5*MAX($B$20*(1+$B$21)^(D51-1),$B$22)*$B$9*D54*D53 -> 132651 | E57: =$B$5*MAX($B$20*(1+$B$21)^(E51-1),$B$22)*$B$9*E54*E53 -> 115008.42 | F57: =$B$5*MAX($B$20*(1+$B$21)^(F51-1),$B$22)*$B$9*F54*F53 -> 99712.298 | G57: =$B$5*MAX($B$20*(1+$B$21)^(G51-1),$B$22)*$B$9*G54*G53 -> 86450.562 | H57: =$B$5*MAX($B$20*(1+$B$21)^(H51-1),$B$22)*$B$9*H54*H53 -> 74952.637 | I57: =$B$5*MAX($B$20*(1+$B$21)^(I51-1),$B$22)*$B$9*I54*I53 -> 64983.936 | J57: =$B$5*MAX($B$20*(1+$B$21)^(J51-1),$B$22)*$B$9*J54*J53 -> 56341.073 | K57: =$B$5*MAX($B$20*(1+$B$21)^(K51-1),$B$22)*$B$9*K54*K53 -> 48847.71 | ... W57: =$B$5*MAX($B$20*(1+$B$21)^(W51-1),$B$22)*$B$9*W54*W53 -> 0
A58: Markedsindtægt i alt | C58: =C56+C57 -> 0 | D58: =D56+D57 -> 622093.01 | E58: =E56+E57 -> 587156 | F58: =F56+F57 -> 555176.54 | G58: =G56+G57 -> 525820.98 | H58: =H56+H57 -> 498797.9 | I58: =I56+I57 -> 473852.63 | J58: =J56+J57 -> 450762.39 | ... W58: =W56+W57 -> 0
A59: Nettariffer og elafgift | C59: 0 | D59: =-$B$5*$B$46*D55*$B$9*($B$47/$B$11+$B$48)*D54*D53 -> -205272.28 | E59: =-$B$5*$B$46*E55*$B$9*($B$47/$B$11+$B$48)*E54*E53 -> -204143.28 | F59: =-$B$5*$B$46*F55*$B$9*($B$47/$B$11+$B$48)*F54*F53 -> -203020.49 | G59: =-$B$5*$B$46*G55*$B$9*($B$47/$B$11+$B$48)*G54*G53 -> -201903.88 | H59: =-$B$5*$B$46*H55*$B$9*($B$47/$B$11+$B$48)*H54*H53 -> -200793.41 | I59: =-$B$5*$B$46*I55*$B$9*($B$47/$B$11+$B$48)*I54*I53 -> -199689.05 | J59: =-$B$5*$B$46*J55*$B$9*($B$47/$B$11+$B$48)*J54*J53 -> -198590.76 | K59: =-$B$5*$B$46*K55*$B$9*($B$47/$B$11+$B$48)*K54*K53 -> -197498.51 | ... W59: =-$B$5*$B$46*W55*$B$9*($B$47/$B$11+$B$48)*W54*W53 -> 0
A60: Drift, vedligehold og forsikring | C60: 0 | D60: =-($B$29+$B$30)*$B$41*D54*D53 -> -195075 | E60: =-($B$29+$B$30)*$B$41*E54*E53 -> -198976.5 | F60: =-($B$29+$B$30)*$B$41*F54*F53 -> -202956.03 | G60: =-($B$29+$B$30)*$B$41*G54*G53 -> -207015.15 | H60: =-($B$29+$B$30)*$B$41*H54*H53 -> -211155.45 | I60: =-($B$29+$B$30)*$B$41*I54*I53 -> -215378.56 | J60: =-($B$29+$B$30)*$B$41*J54*J53 -> -219686.13 | K60: =-($B$29+$B$30)*$B$41*K54*K53 -> -224079.86 | ... W60: =-($B$29+$B$30)*$B$41*W54*W53 -> 0
A61: Optimeringsfee | C61: =-$B$31*C58 -> 0 | D61: =-$B$31*D58 -> -93313.952 | E61: =-$B$31*E58 -> -88073.4 | F61: =-$B$31*F58 -> -83276.481 | G61: =-$B$31*G58 -> -78873.147 | H61: =-$B$31*H58 -> -74819.685 | I61: =-$B$31*I58 -> -71077.894 | J61: =-$B$31*J58 -> -67614.358 | ... W61: =-$B$31*W58 -> 0
A62: Betaling til RFV (netadgang og areal) | C62: 0 | D62: =-$B$32*$B$5*D54*D53 -> -104040 | E62: =-$B$32*$B$5*E54*E53 -> -106120.8 | F62: =-$B$32*$B$5*F54*F53 -> -108243.22 | G62: =-$B$32*$B$5*G54*G53 -> -110408.08 | H62: =-$B$32*$B$5*H54*H53 -> -112616.24 | I62: =-$B$32*$B$5*I54*I53 -> -114868.57 | J62: =-$B$32*$B$5*J54*J53 -> -117165.94 | K62: =-$B$32*$B$5*K54*K53 -> -119509.26 | ... W62: =-$B$32*$B$5*W54*W53 -> 0
A63: Faste omkostninger | C63: 0 | D63: =-$B$33*D54*D53 -> -62424 | E63: =-$B$33*E54*E53 -> -63672.48 | F63: =-$B$33*F54*F53 -> -64945.93 | G63: =-$B$33*G54*G53 -> -66244.848 | H63: =-$B$33*H54*H53 -> -67569.745 | I63: =-$B$33*I54*I53 -> -68921.14 | J63: =-$B$33*J54*J53 -> -70299.563 | K63: =-$B$33*K54*K53 -> -71705.554 | ... W63: =-$B$33*W54*W53 -> 0
A64: EBITDA | C64: =C58+C59+C60+C61+C62+C63 -> 0 | D64: =D58+D59+D60+D61+D62+D63 -> -38032.217 | E64: =E58+E59+E60+E61+E62+E63 -> -73830.463 | F64: =F58+F59+F60+F61+F62+F63 -> -107265.61 | G64: =G58+G59+G60+G61+G62+G63 -> -138624.13 | H64: =H58+H59+H60+H61+H62+H63 -> -168156.63 | I64: =I58+I59+I60+I61+I62+I63 -> -196082.58 | J64: =J58+J59+J60+J61+J62+J63 -> -222594.36 | ... W64: =W58+W59+W60+W61+W62+W63 -> 0
A65: Investering | C65: =-$B$42 -> -8200000 | D65: 0 | E65: 0 | F65: 0 | G65: 0 | H65: 0 | I65: 0 | J65: 0 | K65: 0 | L65: 0 | M65: 0 | N65: 0 | O65: 0 | P65: 0 | Q65: 0 | R65: 0 | S65: 0 | T65: 0 | U65: 0 | V65: 0 | W65: 0
A66: Cash flow før skat | C66: =C64+C65 -> -8200000 | D66: =D64+D65 -> -38032.217 | E66: =E64+E65 -> -73830.463 | F66: =F64+F65 -> -107265.61 | G66: =G64+G65 -> -138624.13 | H66: =H64+H65 -> -168156.63 | I66: =I64+I65 -> -196082.58 | J66: =J64+J65 -> -222594.36 | ... W66: =W64+W65 -> 0
A68: Skat
A69: Saldo primo | C69: 0 | D69: =$B$42 -> 8200000 | E69: =D71 -> 6150000 | F69: =E71 -> 4612500 | G69: =F71 -> 3459375 | H69: =G71 -> 2594531.2 | I69: =H71 -> 1945898.4 | J69: =I71 -> 1459423.8 | K69: =J71 -> 1094567.9 | L69: =K71 -> 820925.9 | ... W69: =V71 -> 0
A70: Skattemæssig afskrivning | C70: 0 | D70: =IF(D51=$B$8,D69,D69*$B$36)*D53 -> 2050000 | E70: =IF(E51=$B$8,E69,E69*$B$36)*E53 -> 1537500 | F70: =IF(F51=$B$8,F69,F69*$B$36)*F53 -> 1153125 | G70: =IF(G51=$B$8,G69,G69*$B$36)*G53 -> 864843.75 | H70: =IF(H51=$B$8,H69,H69*$B$36)*H53 -> 648632.81 | I70: =IF(I51=$B$8,I69,I69*$B$36)*I53 -> 486474.61 | J70: =IF(J51=$B$8,J69,J69*$B$36)*J53 -> 364855.96 | K70: =IF(K51=$B$8,K69,K69*$B$36)*K53 -> 273641.97 | ... W70: =IF(W51=$B$8,W69,W69*$B$36)*W53 -> 0
A71: Saldo ultimo | C71: 0 | D71: =D69-D70 -> 6150000 | E71: =E69-E70 -> 4612500 | F71: =F69-F70 -> 3459375 | G71: =G69-G70 -> 2594531.2 | H71: =H69-H70 -> 1945898.4 | I71: =I69-I70 -> 1459423.8 | J71: =J69-J70 -> 1094567.9 | K71: =K69-K70 -> 820925.9 | ... W71: =W69-W70 -> 0
A72: Skattepligtig indkomst før underskud | C72: 0 | D72: =D64-D70 -> -2088032.2 | E72: =E64-E70 -> -1611330.5 | F72: =F64-F70 -> -1260390.6 | G72: =G64-G70 -> -1003467.9 | H72: =H64-H70 -> -816789.45 | I72: =I64-I70 -> -682557.19 | J72: =J64-J70 -> -587450.32 | K72: =K64-K70 -> -521502.82 | ... W72: =W64-W70 -> 0
A73: Fremført underskud primo | C73: 0 | D73: =C75 -> 0 | E73: =D75 -> 2088032.2 | F73: =E75 -> 3699362.7 | G73: =F75 -> 4959753.3 | H73: =G75 -> 5963221.2 | I73: =H75 -> 6780010.6 | J73: =I75 -> 7462567.8 | K73: =J75 -> 8050018.1 | ... W73: =V75 -> 11757479
A74: Anvendt underskud | C74: 0 | D74: =MIN(D73,MAX(D72,0)) -> 0 | E74: =MIN(E73,MAX(E72,0)) -> 0 | F74: =MIN(F73,MAX(F72,0)) -> 0 | G74: =MIN(G73,MAX(G72,0)) -> 0 | H74: =MIN(H73,MAX(H72,0)) -> 0 | I74: =MIN(I73,MAX(I72,0)) -> 0 | J74: =MIN(J73,MAX(J72,0)) -> 0 | K74: =MIN(K73,MAX(K72,0)) -> 0 | ... W74: =MIN(W73,MAX(W72,0)) -> 0
A75: Fremført underskud ultimo | C75: 0 | D75: =D73-D74+MAX(-D72,0) -> 2088032.2 | E75: =E73-E74+MAX(-E72,0) -> 3699362.7 | F75: =F73-F74+MAX(-F72,0) -> 4959753.3 | G75: =G73-G74+MAX(-G72,0) -> 5963221.2 | H75: =H73-H74+MAX(-H72,0) -> 6780010.6 | I75: =I73-I74+MAX(-I72,0) -> 7462567.8 | J75: =J73-J74+MAX(-J72,0) -> 8050018.1 | K75: =K73-K74+MAX(-K72,0) -> 8571520.9 | ... W75: =W73-W74+MAX(-W72,0) -> 11757479
A76: Selskabsskat | C76: 0 | D76: =-MAX(D72-D74,0)*$B$35 -> 0 | E76: =-MAX(E72-E74,0)*$B$35 -> 0 | F76: =-MAX(F72-F74,0)*$B$35 -> 0 | G76: =-MAX(G72-G74,0)*$B$35 -> 0 | H76: =-MAX(H72-H74,0)*$B$35 -> 0 | I76: =-MAX(I72-I74,0)*$B$35 -> 0 | J76: =-MAX(J72-J74,0)*$B$35 -> 0 | K76: =-MAX(K72-K74,0)*$B$35 -> 0 | ... W76: =-MAX(W72-W74,0)*$B$35 -> 0
A77: Cash flow efter skat | C77: =C66+C76 -> -8200000 | D77: =D66+D76 -> -38032.217 | E77: =E66+E76 -> -73830.463 | F77: =F66+F76 -> -107265.61 | G77: =G66+G76 -> -138624.13 | H77: =H66+H76 -> -168156.63 | I77: =I66+I76 -> -196082.58 | J77: =J66+J76 -> -222594.36 | ... W77: =W66+W76 -> 0
A78: Akkumuleret cash flow efter skat | C78: =C77 -> -8200000 | D78: =C78+D77 -> -8238032.2 | E78: =D78+E77 -> -8311862.7 | F78: =E78+F77 -> -8419128.3 | G78: =F78+G77 -> -8557752.4 | H78: =G78+H77 -> -8725909 | I78: =H78+I77 -> -8921991.6 | J78: =I78+J77 -> -9144586 | K78: =J78+K77 -> -9392446.8 | ... W78: =V78+W77 -> -11757479
A79: Tilbagebetalt i år (hjælpelinje) | D79: =IF(AND(D78>=0,C78<0),D51,"") | E79: =IF(AND(E78>=0,D78<0),E51,"") | F79: =IF(AND(F78>=0,E78<0),F51,"") | G79: =IF(AND(G78>=0,F78<0),G51,"") | H79: =IF(AND(H78>=0,G78<0),H51,"") | I79: =IF(AND(I78>=0,H78<0),I51,"") | J79: =IF(AND(J78>=0,I78<0),J51,"") | K79: =IF(AND(K78>=0,J78<0),K51,"") | ... W79: =IF(AND(W78>=0,V78<0),W51,"")
A81: Nøgletal
A82: IRR før skat (projekt, ugearet) | B82: =IFERROR(IRR(C66:W66),"negativ") -> negativ
A83: IRR efter skat (projekt, ugearet) | B83: =IFERROR(IRR(C77:W77),"negativ") -> negativ
A84: NPV efter skat | B84: =NPV($B$37,D77:W77)+C77 -> -9919272.8
A85: Simpel tilbagebetalingstid (år) | B85: =IF(COUNT(D79:W79)=0,"> levetid",MIN(D79:W79)) -> > levetid
A86: Samlet investering | B86: =$B$42 -> 8200000
A87: Investering pr. kWh | B87: =$B$43 -> 410
A88: Investering pr. MW | B88: =$B$44 -> 820000
A89: Markedsindtægt år 1 pr. MW | B89: =D58/$B$5 -> 62209.301
A90: EBITDA år 1 | B90: =D64 -> -38032.217
A91: EBITDA-margin år 1 | B91: =IFERROR(D64/D58,0) -> -0.061135901
A92: EBITDA år 1 / investering | B92: =D64/$B$42 -> -0.0046380752

Sheet Base
A1: Cash flow: Base scenarie (EUR, nominelt)
A2: Scenarie-indeks (1 = pess., 2 = base, 3 = opt.) | B2: 2
A4: Forudsætninger for scenariet (hentes fra arket Forudsætninger)
A5: Batteriets effekt [MW] | B5: =INDEX(Forudsætninger!$D$6:$F$6,1,$B$2) -> 10
A6: Varighed (1, 2 eller 4 timer) [timer] | B6: =INDEX(Forudsætninger!$D$7:$F$7,1,$B$2) -> 2
A7: Første driftsår (COD) [år] | B7: =INDEX(Forudsætninger!$D$8:$F$8,1,$B$2) -> 2028
A8: Økonomisk levetid [år] | B8: =INDEX(Forudsætninger!$D$9:$F$9,1,$B$2) -> 15
A9: Tilgængelighed inkl. konflikt med RFV's elkedel og gasmotorer [%] | B9: =INDEX(Forudsætninger!$D$10:$F$10,1,$B$2) -> 0.92
A10: Kapacitetstab pr. år (påvirker arbitrage) [%/år] | B10: =INDEX(Forudsætninger!$D$11:$F$11,1,$B$2) -> 0.02
A11: Round-trip-virkningsgrad (AC-AC) [%] | B11: =INDEX(Forudsætninger!$D$12:$F$12,1,$B$2) -> 0.86
A12: Effektrelateret capex (PCS, trafo, HV/MV, BoP, EPC) [EUR/kW] | B12: =INDEX(Forudsætninger!$D$14:$F$14,1,$B$2) -> 200
A13: Energirelateret capex (batteriblokke inkl. montage) [EUR/kWh] | B13: =INDEX(Forudsætninger!$D$15:$F$15,1,$B$2) -> 200
A14: Udvikling, rådgivning, netstudier, finansiering [EUR] | B14: =INDEX(Forudsætninger!$D$16:$F$16,1,$B$2) -> 250000
A15: Tilslutningsbidrag / ombygning af tilslutning [EUR] | B15: =INDEX(Forudsætninger!$D$17:$F$17,1,$B$2) -> 0
A16: Arbitrage-niveau ift. backtest seneste 12 mdr. [faktor] | B16: =INDEX(Forudsætninger!$D$19:$F$19,1,$B$2) -> 1
A17: Realiseringsgrad ift. perfekt forudsigelse (day-ahead) [%] | B17: =INDEX(Forudsætninger!$D$20:$F$20,1,$B$2) -> 0.85
A18: Tillæg fra intraday/ubalance [%] | B18: =INDEX(Forudsætninger!$D$21:$F$21,1,$B$2) -> 0.1
A19: Real udvikling i arbitrage-indtjening [%/år] | B19: =INDEX(Forudsætninger!$D$22:$F$22,1,$B$2) -> -0.01
A20: Systemydelser (aFRR + mFRR), netto merindtægt år 1 [EUR/MW/år] | B20: =INDEX(Forudsætninger!$D$23:$F$23,1,$B$2) -> 30000
A21: Udvikling i systemydelser [%/år] | B21: =INDEX(Forudsætninger!$D$24:$F$24,1,$B$2) -> -0.05
A22: Gulv for systemydelser [EUR/MW/år] | B22: =INDEX(Forudsætninger!$D$25:$F$25,1,$B$2) -> 10000
A23: Energinet forbrugstarif (net + system) [øre/kWh] | B23: =INDEX(Forudsætninger!$D$27:$F$27,1,$B$2) -> 10.5
A24: Netselskabets forbrugstarif (gns. i ladetimer) [øre/kWh] | B24: =INDEX(Forudsætninger!$D$28:$F$28,1,$B$2) -> 3
A25: Elafgift på opladning efter godtgørelse [øre/kWh] | B25: =INDEX(Forudsætninger!$D$29:$F$29,1,$B$2) -> 0.4
A26: Energinet indfødnings- og balancetarif [øre/kWh] | B26: =INDEX(Forudsætninger!$D$30:$F$30,1,$B$2) -> 0.92
A27: Netselskabets indfødningstarif [øre/kWh] | B27: =INDEX(Forudsætninger!$D$31:$F$31,1,$B$2) -> 0.5
A28: Valutakurs [DKK/EUR] | B28: =INDEX(Forudsætninger!$D$32:$F$32,1,$B$2) -> 7.46
A29: Drift og vedligehold (LTSA) [% af anlægscapex] | B29: =INDEX(Forudsætninger!$D$34:$F$34,1,$B$2) -> 0.015
A30: Forsikring [% af anlægscapex] | B30: =INDEX(Forudsætninger!$D$35:$F$35,1,$B$2) -> 0.004
A31: Optimerings-/aggregatorfee [% af markedsindtægt] | B31: =INDEX(Forudsætninger!$D$36:$F$36,1,$B$2) -> 0.1
A32: Betaling til RFV for netadgang og areal [EUR/MW/år] | B32: =INDEX(Forudsætninger!$D$37:$F$37,1,$B$2) -> 6000
A33: Faste omkostninger (adm., revision, BRP, SCADA, abonnementer) [EUR/år] | B33: =INDEX(Forudsætninger!$D$38:$F$38,1,$B$2) -> 40000
A34: Inflation (indeksering fra 2026-niveau) [%/år] | B34: =INDEX(Forudsætninger!$D$40:$F$40,1,$B$2) -> 0.02
A35: Selskabsskat [%] | B35: =INDEX(Forudsætninger!$D$41:$F$41,1,$B$2) -> 0.22
A36: Skattemæssig afskrivning (saldo) [%/år] | B36: =INDEX(Forudsætninger!$D$42:$F$42,1,$B$2) -> 0.25
A37: Diskonteringsrente til NPV (nominel) [%] | B37: =INDEX(Forudsætninger!$D$43:$F$43,1,$B$2) -> 0.08
A39: Afledte størrelser
A40: Energi (MWh) | B40: =$B$5*$B$6 -> 20
A41: Anlægscapex (effekt + energi) | B41: =$B$5*1000*$B$12+$B$5*$B$6*1000*$B$13 -> 6000000
A42: Samlet investering | B42: =B41+$B$14+$B$15 -> 6250000
A43: Samlet investering pr. kWh | B43: =B42/(B40*1000) -> 312.5
A44: Samlet investering pr. MW | B44: =B42/$B$5 -> 625000
A45: Arbitrage brutto, backtest (EUR/MW/år) | B45: =INDEX(Backtest!$C$20:$C$22,MATCH($B$6,Backtest!$A$20:$A$22,0)) -> 82753.375
A46: MWh afladet, backtest (pr. MW/år) | B46: =INDEX(Backtest!$D$20:$D$22,MATCH($B$6,Backtest!$A$20:$A$22,0)) -> 778.81296
A47: Omkostning pr. MWh opladet (EUR, 2026-niveau) | B47: =($B$23+$B$24+$B$25)*10/$B$28 -> 18.632708
A48: Omkostning pr. MWh afladet (EUR, 2026-niveau) | B48: =($B$26+$B$27)*10/$B$28 -> 1.9034853
A50: Cash flow
A51: År | C51: 0 | D51: 1 | E51: 2 | F51: 3 | G51: 4 | H51: 5 | I51: 6 | J51: 7 | K51: 8 | L51: 9 | M51: 10 | N51: 11 | O51: 12 | P51: 13 | Q51: 14 | R51: 15 | S51: 16 | T51: 17 | U51: 18 | V51: 19 | W51: 20
A52: Kalenderår | D52: =$B$7+D51-1 -> 2028 | E52: =$B$7+E51-1 -> 2029 | F52: =$B$7+F51-1 -> 2030 | G52: =$B$7+G51-1 -> 2031 | H52: =$B$7+H51-1 -> 2032 | I52: =$B$7+I51-1 -> 2033 | J52: =$B$7+J51-1 -> 2034 | K52: =$B$7+K51-1 -> 2035 | ... W52: =$B$7+W51-1 -> 2047
A53: Drift (1/0) | C53: 0 | D53: =IF(D51<=$B$8,1,0) -> 1 | E53: =IF(E51<=$B$8,1,0) -> 1 | F53: =IF(F51<=$B$8,1,0) -> 1 | G53: =IF(G51<=$B$8,1,0) -> 1 | H53: =IF(H51<=$B$8,1,0) -> 1 | I53: =IF(I51<=$B$8,1,0) -> 1 | J53: =IF(J51<=$B$8,1,0) -> 1 | K53: =IF(K51<=$B$8,1,0) -> 1 | ... W53: =IF(W51<=$B$8,1,0) -> 0
A54: Prisindeks (2026 = 1) | C54: 1 | D54: =(1+$B$34)^(D52-2026) -> 1.0404 | E54: =(1+$B$34)^(E52-2026) -> 1.061208 | F54: =(1+$B$34)^(F52-2026) -> 1.0824322 | G54: =(1+$B$34)^(G52-2026) -> 1.1040808 | H54: =(1+$B$34)^(H52-2026) -> 1.1261624 | I54: =(1+$B$34)^(I52-2026) -> 1.1486857 | J54: =(1+$B$34)^(J52-2026) -> 1.1716594 | K54: =(1+$B$34)^(K52-2026) -> 1.1950926 | ... W54: =(1+$B$34)^(W52-2026) -> 1.5156663
A55: Kapacitetsfaktor | C55: 1 | D55: =(1-$B$10)^(D51-1) -> 1 | E55: =(1-$B$10)^(E51-1) -> 0.98 | F55: =(1-$B$10)^(F51-1) -> 0.9604 | G55: =(1-$B$10)^(G51-1) -> 0.941192 | H55: =(1-$B$10)^(H51-1) -> 0.92236816 | I55: =(1-$B$10)^(I51-1) -> 0.9039208 | J55: =(1-$B$10)^(J51-1) -> 0.88584238 | K55: =(1-$B$10)^(K51-1) -> 0.86812553 | ... W55: =(1-$B$10)^(W51-1) -> 0.68123262
A56: Arbitrage (day-ahead + intraday) | C56: 0 | D56: =$B$5*$B$45*$B$16*$B$17*(1+$B$18)*(1+$B$19)^(D51-1)*D55*$B$9*D54*D53 -> 740603.05 | E56: =$B$5*$B$45*$B$16*$B$17*(1+$B$18)*(1+$B$19)^(E51-1)*E55*$B$9*E54*E53 -> 732903.74 | F56: =$B$5*$B$45*$B$16*$B$17*(1+$B$18)*(1+$B$19)^(F51-1)*F55*$B$9*F54*F53 -> 725284.47 | G56: =$B$5*$B$45*$B$16*$B$17*(1+$B$18)*(1+$B$19)^(G51-1)*G55*$B$9*G54*G53 -> 717744.41 | H56: =$B$5*$B$45*$B$16*$B$17*(1+$B$18)*(1+$B$19)^(H51-1)*H55*$B$9*H54*H53 -> 710282.74 | I56: =$B$5*$B$45*$B$16*$B$17*(1+$B$18)*(1+$B$19)^(I51-1)*I55*$B$9*I54*I53 -> 702898.64 | J56: =$B$5*$B$45*$B$16*$B$17*(1+$B$18)*(1+$B$19)^(J51-1)*J55*$B$9*J54*J53 -> 695591.31 | K56: =$B$5*$B$45*$B$16*$B$17*(1+$B$18)*(1+$B$19)^(K51-1)*K55*$B$9*K54*K53 -> 688359.94 | ... W56: =$B$5*$B$45*$B$16*$B$17*(1+$B$18)*(1+$B$19)^(W51-1)*W55*$B$9*W54*W53 -> 0
A57: Systemydelser, netto merindtægt | C57: 0 | D57: =$B$5*MAX($B$20*(1+$B$21)^(D51-1),$B$22)*$B$9*D54*D53 -> 287150.4 | E57: =$B$5*MAX($B$20*(1+$B$21)^(E51-1),$B$22)*$B$9*E54*E53 -> 278248.74 | F57: =$B$5*MAX($B$20*(1+$B$21)^(F51-1),$B$22)*$B$9*F54*F53 -> 269623.03 | G57: =$B$5*MAX($B$20*(1+$B$21)^(G51-1),$B$22)*$B$9*G54*G53 -> 261264.71 | H57: =$B$5*MAX($B$20*(1+$B$21)^(H51-1),$B$22)*$B$9*H54*H53 -> 253165.51 | I57: =$B$5*MAX($B$20*(1+$B$21)^(I51-1),$B$22)*$B$9*I54*I53 -> 245317.38 | J57: =$B$5*MAX($B$20*(1+$B$21)^(J51-1),$B$22)*$B$9*J54*J53 -> 237712.54 | K57: =$B$5*MAX($B$20*(1+$B$21)^(K51-1),$B$22)*$B$9*K54*K53 -> 230343.45 | ... W57: =$B$5*MAX($B$20*(1+$B$21)^(W51-1),$B$22)*$B$9*W54*W53 -> 0
A58: Markedsindtægt i alt | C58: =C56+C57 -> 0 | D58: =D56+D57 -> 1027753.4 | E58: =E56+E57 -> 1011152.5 | F58: =F56+F57 -> 994907.5 | G58: =G56+G57 -> 979009.13 | H58: =H56+H57 -> 963448.25 | I58: =I56+I57 -> 948216.02 | J58: =J56+J57 -> 933303.85 | ... W58: =W56+W57 -> 0
A59: Nettariffer og elafgift | C59: 0 | D59: =-$B$5*$B$46*D55*$B$9*($B$47/$B$11+$B$48)*D54*D53 -> -175699.42 | E59: =-$B$5*$B$46*E55*$B$9*($B$47/$B$11+$B$48)*E54*E53 -> -175629.14 | F59: =-$B$5*$B$46*F55*$B$9*($B$47/$B$11+$B$48)*F54*F53 -> -175558.88 | G59: =-$B$5*$B$46*G55*$B$9*($B$47/$B$11+$B$48)*G54*G53 -> -175488.66 | H59: =-$B$5*$B$46*H55*$B$9*($B$47/$B$11+$B$48)*H54*H53 -> -175418.47 | I59: =-$B$5*$B$46*I55*$B$9*($B$47/$B$11+$B$48)*I54*I53 -> -175348.3 | J59: =-$B$5*$B$46*J55*$B$9*($B$47/$B$11+$B$48)*J54*J53 -> -175278.16 | K59: =-$B$5*$B$46*K55*$B$9*($B$47/$B$11+$B$48)*K54*K53 -> -175208.05 | ... W59: =-$B$5*$B$46*W55*$B$9*($B$47/$B$11+$B$48)*W54*W53 -> 0
A60: Drift, vedligehold og forsikring | C60: 0 | D60: =-($B$29+$B$30)*$B$41*D54*D53 -> -118605.6 | E60: =-($B$29+$B$30)*$B$41*E54*E53 -> -120977.71 | F60: =-($B$29+$B$30)*$B$41*F54*F53 -> -123397.27 | G60: =-($B$29+$B$30)*$B$41*G54*G53 -> -125865.21 | H60: =-($B$29+$B$30)*$B$41*H54*H53 -> -128382.52 | I60: =-($B$29+$B$30)*$B$41*I54*I53 -> -130950.17 | J60: =-($B$29+$B$30)*$B$41*J54*J53 -> -133569.17 | K60: =-($B$29+$B$30)*$B$41*K54*K53 -> -136240.55 | ... W60: =-($B$29+$B$30)*$B$41*W54*W53 -> 0
A61: Optimeringsfee | C61: =-$B$31*C58 -> 0 | D61: =-$B$31*D58 -> -102775.34 | E61: =-$B$31*E58 -> -101115.25 | F61: =-$B$31*F58 -> -99490.75 | G61: =-$B$31*G58 -> -97900.913 | H61: =-$B$31*H58 -> -96344.825 | I61: =-$B$31*I58 -> -94821.602 | J61: =-$B$31*J58 -> -93330.385 | ... W61: =-$B$31*W58 -> 0
A62: Betaling til RFV (netadgang og areal) | C62: 0 | D62: =-$B$32*$B$5*D54*D53 -> -62424 | E62: =-$B$32*$B$5*E54*E53 -> -63672.48 | F62: =-$B$32*$B$5*F54*F53 -> -64945.93 | G62: =-$B$32*$B$5*G54*G53 -> -66244.848 | H62: =-$B$32*$B$5*H54*H53 -> -67569.745 | I62: =-$B$32*$B$5*I54*I53 -> -68921.14 | J62: =-$B$32*$B$5*J54*J53 -> -70299.563 | K62: =-$B$32*$B$5*K54*K53 -> -71705.554 | ... W62: =-$B$32*$B$5*W54*W53 -> 0
A63: Faste omkostninger | C63: 0 | D63: =-$B$33*D54*D53 -> -41616 | E63: =-$B$33*E54*E53 -> -42448.32 | F63: =-$B$33*F54*F53 -> -43297.286 | G63: =-$B$33*G54*G53 -> -44163.232 | H63: =-$B$33*H54*H53 -> -45046.497 | I63: =-$B$33*I54*I53 -> -45947.427 | J63: =-$B$33*J54*J53 -> -46866.375 | K63: =-$B$33*K54*K53 -> -47803.703 | ... W63: =-$B$33*W54*W53 -> 0
A64: EBITDA | C64: =C58+C59+C60+C61+C62+C63 -> 0 | D64: =D58+D59+D60+D61+D62+D63 -> 526633.09 | E64: =E58+E59+E60+E61+E62+E63 -> 507309.58 | F64: =F58+F59+F60+F61+F62+F63 -> 488217.38 | G64: =G58+G59+G60+G61+G62+G63 -> 469346.26 | H64: =H58+H59+H60+H61+H62+H63 -> 450686.2 | I64: =I58+I59+I60+I61+I62+I63 -> 432227.39 | J64: =J58+J59+J60+J61+J62+J63 -> 413960.2 | ... W64: =W58+W59+W60+W61+W62+W63 -> 0
A65: Investering | C65: =-$B$42 -> -6250000 | D65: 0 | E65: 0 | F65: 0 | G65: 0 | H65: 0 | I65: 0 | J65: 0 | K65: 0 | L65: 0 | M65: 0 | N65: 0 | O65: 0 | P65: 0 | Q65: 0 | R65: 0 | S65: 0 | T65: 0 | U65: 0 | V65: 0 | W65: 0
A66: Cash flow før skat | C66: =C64+C65 -> -6250000 | D66: =D64+D65 -> 526633.09 | E66: =E64+E65 -> 507309.58 | F66: =F64+F65 -> 488217.38 | G66: =G64+G65 -> 469346.26 | H66: =H64+H65 -> 450686.2 | I66: =I64+I65 -> 432227.39 | J66: =J64+J65 -> 413960.2 | ... W66: =W64+W65 -> 0
A68: Skat
A69: Saldo primo | C69: 0 | D69: =$B$42 -> 6250000 | E69: =D71 -> 4687500 | F69: =E71 -> 3515625 | G69: =F71 -> 2636718.8 | H69: =G71 -> 1977539.1 | I69: =H71 -> 1483154.3 | J69: =I71 -> 1112365.7 | K69: =J71 -> 834274.29 | L69: =K71 -> 625705.72 | ... W69: =V71 -> 0
A70: Skattemæssig afskrivning | C70: 0 | D70: =IF(D51=$B$8,D69,D69*$B$36)*D53 -> 1562500 | E70: =IF(E51=$B$8,E69,E69*$B$36)*E53 -> 1171875 | F70: =IF(F51=$B$8,F69,F69*$B$36)*F53 -> 878906.25 | G70: =IF(G51=$B$8,G69,G69*$B$36)*G53 -> 659179.69 | H70: =IF(H51=$B$8,H69,H69*$B$36)*H53 -> 494384.77 | I70: =IF(I51=$B$8,I69,I69*$B$36)*I53 -> 370788.57 | J70: =IF(J51=$B$8,J69,J69*$B$36)*J53 -> 278091.43 | K70: =IF(K51=$B$8,K69,K69*$B$36)*K53 -> 208568.57 | ... W70: =IF(W51=$B$8,W69,W69*$B$36)*W53 -> 0
A71: Saldo ultimo | C71: 0 | D71: =D69-D70 -> 4687500 | E71: =E69-E70 -> 3515625 | F71: =F69-F70 -> 2636718.8 | G71: =G69-G70 -> 1977539.1 | H71: =H69-H70 -> 1483154.3 | I71: =I69-I70 -> 1112365.7 | J71: =J69-J70 -> 834274.29 | K71: =K69-K70 -> 625705.72 | ... W71: =W69-W70 -> 0
A72: Skattepligtig indkomst før underskud | C72: 0 | D72: =D64-D70 -> -1035866.9 | E72: =E64-E70 -> -664565.42 | F72: =F64-F70 -> -390688.87 | G72: =G64-G70 -> -189833.43 | H72: =H64-H70 -> -43698.565 | I72: =I64-I70 -> 61438.812 | J72: =J64-J70 -> 135868.76 | K72: =K64-K70 -> 187306.62 | ... W72: =W64-W70 -> 0
A73: Fremført underskud primo | C73: 0 | D73: =C75 -> 0 | E73: =D75 -> 1035866.9 | F73: =E75 -> 1700432.3 | G73: =F75 -> 2091121.2 | H73: =G75 -> 2280954.6 | I73: =H75 -> 2324653.2 | J73: =I75 -> 2263214.4 | K73: =J75 -> 2127345.6 | ... W73: =V75 -> 287596.1
A74: Anvendt underskud | C74: 0 | D74: =MIN(D73,MAX(D72,0)) -> 0 | E74: =MIN(E73,MAX(E72,0)) -> 0 | F74: =MIN(F73,MAX(F72,0)) -> 0 | G74: =MIN(G73,MAX(G72,0)) -> 0 | H74: =MIN(H73,MAX(H72,0)) -> 0 | I74: =MIN(I73,MAX(I72,0)) -> 61438.812 | J74: =MIN(J73,MAX(J72,0)) -> 135868.76 | K74: =MIN(K73,MAX(K72,0)) -> 187306.62 | ... W74: =MIN(W73,MAX(W72,0)) -> 0
A75: Fremført underskud ultimo | C75: 0 | D75: =D73-D74+MAX(-D72,0) -> 1035866.9 | E75: =E73-E74+MAX(-E72,0) -> 1700432.3 | F75: =F73-F74+MAX(-F72,0) -> 2091121.2 | G75: =G73-G74+MAX(-G72,0) -> 2280954.6 | H75: =H73-H74+MAX(-H72,0) -> 2324653.2 | I75: =I73-I74+MAX(-I72,0) -> 2263214.4 | J75: =J73-J74+MAX(-J72,0) -> 2127345.6 | K75: =K73-K74+MAX(-K72,0) -> 1940039 | ... W75: =W73-W74+MAX(-W72,0) -> 287596.1
A76: Selskabsskat | C76: 0 | D76: =-MAX(D72-D74,0)*$B$35 -> 0 | E76: =-MAX(E72-E74,0)*$B$35 -> 0 | F76: =-MAX(F72-F74,0)*$B$35 -> 0 | G76: =-MAX(G72-G74,0)*$B$35 -> 0 | H76: =-MAX(H72-H74,0)*$B$35 -> 0 | I76: =-MAX(I72-I74,0)*$B$35 -> 0 | J76: =-MAX(J72-J74,0)*$B$35 -> 0 | K76: =-MAX(K72-K74,0)*$B$35 -> 0 | ... W76: =-MAX(W72-W74,0)*$B$35 -> 0
A77: Cash flow efter skat | C77: =C66+C76 -> -6250000 | D77: =D66+D76 -> 526633.09 | E77: =E66+E76 -> 507309.58 | F77: =F66+F76 -> 488217.38 | G77: =G66+G76 -> 469346.26 | H77: =H66+H76 -> 450686.2 | I77: =I66+I76 -> 432227.39 | J77: =J66+J76 -> 413960.2 | ... W77: =W66+W76 -> 0
A78: Akkumuleret cash flow efter skat | C78: =C77 -> -6250000 | D78: =C78+D77 -> -5723366.9 | E78: =D78+E77 -> -5216057.3 | F78: =E78+F77 -> -4727840 | G78: =F78+G77 -> -4258493.7 | H78: =G78+H77 -> -3807807.5 | I78: =H78+I77 -> -3375580.1 | J78: =I78+J77 -> -2961619.9 | K78: =J78+K77 -> -2565744.7 | ... W78: =V78+W77 -> -287596.1
A79: Tilbagebetalt i år (hjælpelinje) | D79: =IF(AND(D78>=0,C78<0),D51,"") | E79: =IF(AND(E78>=0,D78<0),E51,"") | F79: =IF(AND(F78>=0,E78<0),F51,"") | G79: =IF(AND(G78>=0,F78<0),G51,"") | H79: =IF(AND(H78>=0,G78<0),H51,"") | I79: =IF(AND(I78>=0,H78<0),I51,"") | J79: =IF(AND(J78>=0,I78<0),J51,"") | K79: =IF(AND(K78>=0,J78<0),K51,"") | ... W79: =IF(AND(W78>=0,V78<0),W51,"")
A81: Nøgletal
A82: IRR før skat (projekt, ugearet) | B82: =IFERROR(IRR(C66:W66),"negativ") -> -0.0065111185
A83: IRR efter skat (projekt, ugearet) | B83: =IFERROR(IRR(C77:W77),"negativ") -> -0.0065111185
A84: NPV efter skat | B84: =NPV($B$37,D77:W77)+C77 -> -2629940.7
A85: Simpel tilbagebetalingstid (år) | B85: =IF(COUNT(D79:W79)=0,"> levetid",MIN(D79:W79)) -> > levetid
A86: Samlet investering | B86: =$B$42 -> 6250000
A87: Investering pr. kWh | B87: =$B$43 -> 312.5
A88: Investering pr. MW | B88: =$B$44 -> 625000
A89: Markedsindtægt år 1 pr. MW | B89: =D58/$B$5 -> 102775.34
A90: EBITDA år 1 | B90: =D64 -> 526633.09
A91: EBITDA-margin år 1 | B91: =IFERROR(D64/D58,0) -> 0.51241189
A92: EBITDA år 1 / investering | B92: =D64/$B$42 -> 0.084261294

Sheet Optimistisk
A1: Cash flow: Optimistisk scenarie (EUR, nominelt)
A2: Scenarie-indeks (1 = pess., 2 = base, 3 = opt.) | B2: 3
A4: Forudsætninger for scenariet (hentes fra arket Forudsætninger)
A5: Batteriets effekt [MW] | B5: =INDEX(Forudsætninger!$D$6:$F$6,1,$B$2) -> 10
A6: Varighed (1, 2 eller 4 timer) [timer] | B6: =INDEX(Forudsætninger!$D$7:$F$7,1,$B$2) -> 2
A7: Første driftsår (COD) [år] | B7: =INDEX(Forudsætninger!$D$8:$F$8,1,$B$2) -> 2028
A8: Økonomisk levetid [år] | B8: =INDEX(Forudsætninger!$D$9:$F$9,1,$B$2) -> 15
A9: Tilgængelighed inkl. konflikt med RFV's elkedel og gasmotorer [%] | B9: =INDEX(Forudsætninger!$D$10:$F$10,1,$B$2) -> 0.97
A10: Kapacitetstab pr. år (påvirker arbitrage) [%/år] | B10: =INDEX(Forudsætninger!$D$11:$F$11,1,$B$2) -> 0.015
A11: Round-trip-virkningsgrad (AC-AC) [%] | B11: =INDEX(Forudsætninger!$D$12:$F$12,1,$B$2) -> 0.86
A12: Effektrelateret capex (PCS, trafo, HV/MV, BoP, EPC) [EUR/kW] | B12: =INDEX(Forudsætninger!$D$14:$F$14,1,$B$2) -> 160
A13: Energirelateret capex (batteriblokke inkl. montage) [EUR/kWh] | B13: =INDEX(Forudsætninger!$D$15:$F$15,1,$B$2) -> 170
A14: Udvikling, rådgivning, netstudier, finansiering [EUR] | B14: =INDEX(Forudsætninger!$D$16:$F$16,1,$B$2) -> 150000
A15: Tilslutningsbidrag / ombygning af tilslutning [EUR] | B15: =INDEX(Forudsætninger!$D$17:$F$17,1,$B$2) -> 0
A16: Arbitrage-niveau ift. backtest seneste 12 mdr. [faktor] | B16: =INDEX(Forudsætninger!$D$19:$F$19,1,$B$2) -> 1.126
A17: Realiseringsgrad ift. perfekt forudsigelse (day-ahead) [%] | B17: =INDEX(Forudsætninger!$D$20:$F$20,1,$B$2) -> 0.9
A18: Tillæg fra intraday/ubalance [%] | B18: =INDEX(Forudsætninger!$D$21:$F$21,1,$B$2) -> 0.2
A19: Real udvikling i arbitrage-indtjening [%/år] | B19: =INDEX(Forudsætninger!$D$22:$F$22,1,$B$2) -> 0.01
A20: Systemydelser (aFRR + mFRR), netto merindtægt år 1 [EUR/MW/år] | B20: =INDEX(Forudsætninger!$D$23:$F$23,1,$B$2) -> 70000
A21: Udvikling i systemydelser [%/år] | B21: =INDEX(Forudsætninger!$D$24:$F$24,1,$B$2) -> -0.05
A22: Gulv for systemydelser [EUR/MW/år] | B22: =INDEX(Forudsætninger!$D$25:$F$25,1,$B$2) -> 20000
A23: Energinet forbrugstarif (net + system) [øre/kWh] | B23: =INDEX(Forudsætninger!$D$27:$F$27,1,$B$2) -> 10.5
A24: Netselskabets forbrugstarif (gns. i ladetimer) [øre/kWh] | B24: =INDEX(Forudsætninger!$D$28:$F$28,1,$B$2) -> 2
A25: Elafgift på opladning efter godtgørelse [øre/kWh] | B25: =INDEX(Forudsætninger!$D$29:$F$29,1,$B$2) -> 0.4
A26: Energinet indfødnings- og balancetarif [øre/kWh] | B26: =INDEX(Forudsætninger!$D$30:$F$30,1,$B$2) -> 0.92
A27: Netselskabets indfødningstarif [øre/kWh] | B27: =INDEX(Forudsætninger!$D$31:$F$31,1,$B$2) -> 0.5
A28: Valutakurs [DKK/EUR] | B28: =INDEX(Forudsætninger!$D$32:$F$32,1,$B$2) -> 7.46
A29: Drift og vedligehold (LTSA) [% af anlægscapex] | B29: =INDEX(Forudsætninger!$D$34:$F$34,1,$B$2) -> 0.012
A30: Forsikring [% af anlægscapex] | B30: =INDEX(Forudsætninger!$D$35:$F$35,1,$B$2) -> 0.003
A31: Optimerings-/aggregatorfee [% af markedsindtægt] | B31: =INDEX(Forudsætninger!$D$36:$F$36,1,$B$2) -> 0.07
A32: Betaling til RFV for netadgang og areal [EUR/MW/år] | B32: =INDEX(Forudsætninger!$D$37:$F$37,1,$B$2) -> 3000
A33: Faste omkostninger (adm., revision, BRP, SCADA, abonnementer) [EUR/år] | B33: =INDEX(Forudsætninger!$D$38:$F$38,1,$B$2) -> 30000
A34: Inflation (indeksering fra 2026-niveau) [%/år] | B34: =INDEX(Forudsætninger!$D$40:$F$40,1,$B$2) -> 0.02
A35: Selskabsskat [%] | B35: =INDEX(Forudsætninger!$D$41:$F$41,1,$B$2) -> 0.22
A36: Skattemæssig afskrivning (saldo) [%/år] | B36: =INDEX(Forudsætninger!$D$42:$F$42,1,$B$2) -> 0.25
A37: Diskonteringsrente til NPV (nominel) [%] | B37: =INDEX(Forudsætninger!$D$43:$F$43,1,$B$2) -> 0.08
A39: Afledte størrelser
A40: Energi (MWh) | B40: =$B$5*$B$6 -> 20
A41: Anlægscapex (effekt + energi) | B41: =$B$5*1000*$B$12+$B$5*$B$6*1000*$B$13 -> 5000000
A42: Samlet investering | B42: =B41+$B$14+$B$15 -> 5150000
A43: Samlet investering pr. kWh | B43: =B42/(B40*1000) -> 257.5
A44: Samlet investering pr. MW | B44: =B42/$B$5 -> 515000
A45: Arbitrage brutto, backtest (EUR/MW/år) | B45: =INDEX(Backtest!$C$20:$C$22,MATCH($B$6,Backtest!$A$20:$A$22,0)) -> 82753.375
A46: MWh afladet, backtest (pr. MW/år) | B46: =INDEX(Backtest!$D$20:$D$22,MATCH($B$6,Backtest!$A$20:$A$22,0)) -> 778.81296
A47: Omkostning pr. MWh opladet (EUR, 2026-niveau) | B47: =($B$23+$B$24+$B$25)*10/$B$28 -> 17.292225
A48: Omkostning pr. MWh afladet (EUR, 2026-niveau) | B48: =($B$26+$B$27)*10/$B$28 -> 1.9034853
A50: Cash flow
A51: År | C51: 0 | D51: 1 | E51: 2 | F51: 3 | G51: 4 | H51: 5 | I51: 6 | J51: 7 | K51: 8 | L51: 9 | M51: 10 | N51: 11 | O51: 12 | P51: 13 | Q51: 14 | R51: 15 | S51: 16 | T51: 17 | U51: 18 | V51: 19 | W51: 20
A52: Kalenderår | D52: =$B$7+D51-1 -> 2028 | E52: =$B$7+E51-1 -> 2029 | F52: =$B$7+F51-1 -> 2030 | G52: =$B$7+G51-1 -> 2031 | H52: =$B$7+H51-1 -> 2032 | I52: =$B$7+I51-1 -> 2033 | J52: =$B$7+J51-1 -> 2034 | K52: =$B$7+K51-1 -> 2035 | ... W52: =$B$7+W51-1 -> 2047
A53: Drift (1/0) | C53: 0 | D53: =IF(D51<=$B$8,1,0) -> 1 | E53: =IF(E51<=$B$8,1,0) -> 1 | F53: =IF(F51<=$B$8,1,0) -> 1 | G53: =IF(G51<=$B$8,1,0) -> 1 | H53: =IF(H51<=$B$8,1,0) -> 1 | I53: =IF(I51<=$B$8,1,0) -> 1 | J53: =IF(J51<=$B$8,1,0) -> 1 | K53: =IF(K51<=$B$8,1,0) -> 1 | ... W53: =IF(W51<=$B$8,1,0) -> 0
A54: Prisindeks (2026 = 1) | C54: 1 | D54: =(1+$B$34)^(D52-2026) -> 1.0404 | E54: =(1+$B$34)^(E52-2026) -> 1.061208 | F54: =(1+$B$34)^(F52-2026) -> 1.0824322 | G54: =(1+$B$34)^(G52-2026) -> 1.1040808 | H54: =(1+$B$34)^(H52-2026) -> 1.1261624 | I54: =(1+$B$34)^(I52-2026) -> 1.1486857 | J54: =(1+$B$34)^(J52-2026) -> 1.1716594 | K54: =(1+$B$34)^(K52-2026) -> 1.1950926 | ... W54: =(1+$B$34)^(W52-2026) -> 1.5156663
A55: Kapacitetsfaktor | C55: 1 | D55: =(1-$B$10)^(D51-1) -> 1 | E55: =(1-$B$10)^(E51-1) -> 0.985 | F55: =(1-$B$10)^(F51-1) -> 0.970225 | G55: =(1-$B$10)^(G51-1) -> 0.95567163 | H55: =(1-$B$10)^(H51-1) -> 0.94133655 | I55: =(1-$B$10)^(I51-1) -> 0.9272165 | J55: =(1-$B$10)^(J51-1) -> 0.91330825 | K55: =(1-$B$10)^(K51-1) -> 0.89960863 | ... W55: =(1-$B$10)^(W51-1) -> 0.75039232
A56: Arbitrage (day-ahead + intraday) | C56: 0 | D56: =$B$5*$B$45*$B$16*$B$17*(1+$B$18)*(1+$B$19)^(D51-1)*D55*$B$9*D54*D53 -> 1015593.6 | E56: =$B$5*$B$45*$B$16*$B$17*(1+$B$18)*(1+$B$19)^(E51-1)*E55*$B$9*E54*E53 -> 1030570.5 | F56: =$B$5*$B$45*$B$16*$B$17*(1+$B$18)*(1+$B$19)^(F51-1)*F55*$B$9*F54*F53 -> 1045768.3 | G56: =$B$5*$B$45*$B$16*$B$17*(1+$B$18)*(1+$B$19)^(G51-1)*G55*$B$9*G54*G53 -> 1061190.3 | H56: =$B$5*$B$45*$B$16*$B$17*(1+$B$18)*(1+$B$19)^(H51-1)*H55*$B$9*H54*H53 -> 1076839.7 | I56: =$B$5*$B$45*$B$16*$B$17*(1+$B$18)*(1+$B$19)^(I51-1)*I55*$B$9*I54*I53 -> 1092719.8 | J56: =$B$5*$B$45*$B$16*$B$17*(1+$B$18)*(1+$B$19)^(J51-1)*J55*$B$9*J54*J53 -> 1108834.1 | K56: =$B$5*$B$45*$B$16*$B$17*(1+$B$18)*(1+$B$19)^(K51-1)*K55*$B$9*K54*K53 -> 1125186.1 | ... W56: =$B$5*$B$45*$B$16*$B$17*(1+$B$18)*(1+$B$19)^(W51-1)*W55*$B$9*W54*W53 -> 0
A57: Systemydelser, netto merindtægt | C57: 0 | D57: =$B$5*MAX($B$20*(1+$B$21)^(D51-1),$B$22)*$B$9*D54*D53 -> 706431.6 | E57: =$B$5*MAX($B$20*(1+$B$21)^(E51-1),$B$22)*$B$9*E54*E53 -> 684532.22 | F57: =$B$5*MAX($B$20*(1+$B$21)^(F51-1),$B$22)*$B$9*F54*F53 -> 663311.72 | G57: =$B$5*MAX($B$20*(1+$B$21)^(G51-1),$B$22)*$B$9*G54*G53 -> 642749.06 | H57: =$B$5*MAX($B$20*(1+$B$21)^(H51-1),$B$22)*$B$9*H54*H53 -> 622823.84 | I57: =$B$5*MAX($B$20*(1+$B$21)^(I51-1),$B$22)*$B$9*I54*I53 -> 603516.3 | J57: =$B$5*MAX($B$20*(1+$B$21)^(J51-1),$B$22)*$B$9*J54*J53 -> 584807.29 | K57: =$B$5*MAX($B$20*(1+$B$21)^(K51-1),$B$22)*$B$9*K54*K53 -> 566678.27 | ... W57: =$B$5*MAX($B$20*(1+$B$21)^(W51-1),$B$22)*$B$9*W54*W53 -> 0
A58: Markedsindtægt i alt | C58: =C56+C57 -> 0 | D58: =D56+D57 -> 1722025.2 | E58: =E56+E57 -> 1715102.7 | F58: =F56+F57 -> 1709080.1 | G58: =G56+G57 -> 1703939.3 | H58: =H56+H57 -> 1699663.5 | I58: =I56+I57 -> 1696236.1 | J58: =J56+J57 -> 1693641.4 | ... W58: =W56+W57 -> 0
A59: Nettariffer og elafgift | C59: 0 | D59: =-$B$5*$B$46*D55*$B$9*($B$47/$B$11+$B$48)*D54*D53 -> -172997.4 | E59: =-$B$5*$B$46*E55*$B$9*($B$47/$B$11+$B$48)*E54*E53 -> -173810.49 | F59: =-$B$5*$B$46*F55*$B$9*($B$47/$B$11+$B$48)*F54*F53 -> -174627.4 | G59: =-$B$5*$B$46*G55*$B$9*($B$47/$B$11+$B$48)*G54*G53 -> -175448.14 | H59: =-$B$5*$B$46*H55*$B$9*($B$47/$B$11+$B$48)*H54*H53 -> -176272.75 | I59: =-$B$5*$B$46*I55*$B$9*($B$47/$B$11+$B$48)*I54*I53 -> -177101.23 | J59: =-$B$5*$B$46*J55*$B$9*($B$47/$B$11+$B$48)*J54*J53 -> -177933.61 | K59: =-$B$5*$B$46*K55*$B$9*($B$47/$B$11+$B$48)*K54*K53 -> -178769.9 | ... W59: =-$B$5*$B$46*W55*$B$9*($B$47/$B$11+$B$48)*W54*W53 -> 0
A60: Drift, vedligehold og forsikring | C60: 0 | D60: =-($B$29+$B$30)*$B$41*D54*D53 -> -78030 | E60: =-($B$29+$B$30)*$B$41*E54*E53 -> -79590.6 | F60: =-($B$29+$B$30)*$B$41*F54*F53 -> -81182.412 | G60: =-($B$29+$B$30)*$B$41*G54*G53 -> -82806.06 | H60: =-($B$29+$B$30)*$B$41*H54*H53 -> -84462.181 | I60: =-($B$29+$B$30)*$B$41*I54*I53 -> -86151.425 | J60: =-($B$29+$B$30)*$B$41*J54*J53 -> -87874.454 | K60: =-($B$29+$B$30)*$B$41*K54*K53 -> -89631.943 | ... W60: =-($B$29+$B$30)*$B$41*W54*W53 -> 0
A61: Optimeringsfee | C61: =-$B$31*C58 -> 0 | D61: =-$B$31*D58 -> -120541.76 | E61: =-$B$31*E58 -> -120057.19 | F61: =-$B$31*F58 -> -119635.6 | G61: =-$B$31*G58 -> -119275.75 | H61: =-$B$31*H58 -> -118976.44 | I61: =-$B$31*I58 -> -118736.53 | J61: =-$B$31*J58 -> -118554.9 | ... W61: =-$B$31*W58 -> 0
A62: Betaling til RFV (netadgang og areal) | C62: 0 | D62: =-$B$32*$B$5*D54*D53 -> -31212 | E62: =-$B$32*$B$5*E54*E53 -> -31836.24 | F62: =-$B$32*$B$5*F54*F53 -> -32472.965 | G62: =-$B$32*$B$5*G54*G53 -> -33122.424 | H62: =-$B$32*$B$5*H54*H53 -> -33784.873 | I62: =-$B$32*$B$5*I54*I53 -> -34460.57 | J62: =-$B$32*$B$5*J54*J53 -> -35149.781 | K62: =-$B$32*$B$5*K54*K53 -> -35852.777 | ... W62: =-$B$32*$B$5*W54*W53 -> 0
A63: Faste omkostninger | C63: 0 | D63: =-$B$33*D54*D53 -> -31212 | E63: =-$B$33*E54*E53 -> -31836.24 | F63: =-$B$33*F54*F53 -> -32472.965 | G63: =-$B$33*G54*G53 -> -33122.424 | H63: =-$B$33*H54*H53 -> -33784.873 | I63: =-$B$33*I54*I53 -> -34460.57 | J63: =-$B$33*J54*J53 -> -35149.781 | K63: =-$B$33*K54*K53 -> -35852.777 | ... W63: =-$B$33*W54*W53 -> 0
A64: EBITDA | C64: =C58+C59+C60+C61+C62+C63 -> 0 | D64: =D58+D59+D60+D61+D62+D63 -> 1288032 | E64: =E58+E59+E60+E61+E62+E63 -> 1277972 | F64: =F58+F59+F60+F61+F62+F63 -> 1268688.7 | G64: =G58+G59+G60+G61+G62+G63 -> 1260164.5 | H64: =H58+H59+H60+H61+H62+H63 -> 1252382.4 | I64: =I58+I59+I60+I61+I62+I63 -> 1245325.8 | J64: =J58+J59+J60+J61+J62+J63 -> 1238978.9 | ... W64: =W58+W59+W60+W61+W62+W63 -> 0
A65: Investering | C65: =-$B$42 -> -5150000 | D65: 0 | E65: 0 | F65: 0 | G65: 0 | H65: 0 | I65: 0 | J65: 0 | K65: 0 | L65: 0 | M65: 0 | N65: 0 | O65: 0 | P65: 0 | Q65: 0 | R65: 0 | S65: 0 | T65: 0 | U65: 0 | V65: 0 | W65: 0
A66: Cash flow før skat | C66: =C64+C65 -> -5150000 | D66: =D64+D65 -> 1288032 | E66: =E64+E65 -> 1277972 | F66: =F64+F65 -> 1268688.7 | G66: =G64+G65 -> 1260164.5 | H66: =H64+H65 -> 1252382.4 | I66: =I64+I65 -> 1245325.8 | J66: =J64+J65 -> 1238978.9 | ... W66: =W64+W65 -> 0
A68: Skat
A69: Saldo primo | C69: 0 | D69: =$B$42 -> 5150000 | E69: =D71 -> 3862500 | F69: =E71 -> 2896875 | G69: =F71 -> 2172656.2 | H69: =G71 -> 1629492.2 | I69: =H71 -> 1222119.1 | J69: =I71 -> 916589.36 | K69: =J71 -> 687442.02 | L69: =K71 -> 515581.51 | ... W69: =V71 -> 0
A70: Skattemæssig afskrivning | C70: 0 | D70: =IF(D51=$B$8,D69,D69*$B$36)*D53 -> 1287500 | E70: =IF(E51=$B$8,E69,E69*$B$36)*E53 -> 965625 | F70: =IF(F51=$B$8,F69,F69*$B$36)*F53 -> 724218.75 | G70: =IF(G51=$B$8,G69,G69*$B$36)*G53 -> 543164.06 | H70: =IF(H51=$B$8,H69,H69*$B$36)*H53 -> 407373.05 | I70: =IF(I51=$B$8,I69,I69*$B$36)*I53 -> 305529.79 | J70: =IF(J51=$B$8,J69,J69*$B$36)*J53 -> 229147.34 | K70: =IF(K51=$B$8,K69,K69*$B$36)*K53 -> 171860.5 | ... W70: =IF(W51=$B$8,W69,W69*$B$36)*W53 -> 0
A71: Saldo ultimo | C71: 0 | D71: =D69-D70 -> 3862500 | E71: =E69-E70 -> 2896875 | F71: =F69-F70 -> 2172656.2 | G71: =G69-G70 -> 1629492.2 | H71: =H69-H70 -> 1222119.1 | I71: =I69-I70 -> 916589.36 | J71: =J69-J70 -> 687442.02 | K71: =K69-K70 -> 515581.51 | ... W71: =W69-W70 -> 0
A72: Skattepligtig indkomst før underskud | C72: 0 | D72: =D64-D70 -> 531.99714 | E72: =E64-E70 -> 312346.98 | F72: =F64-F70 -> 544469.97 | G72: =G64-G70 -> 717000.47 | H72: =H64-H70 -> 845009.33 | I72: =I64-I70 -> 939796 | J72: =J64-J70 -> 1009831.6 | K72: =K64-K70 -> 1061466 | ... W72: =W64-W70 -> 0
A73: Fremført underskud primo | C73: 0 | D73: =C75 -> 0 | E73: =D75 -> 0 | F73: =E75 -> 0 | G73: =F75 -> 0 | H73: =G75 -> 0 | I73: =H75 -> 0 | J73: =I75 -> 0 | K73: =J75 -> 0 | ... W73: =V75 -> 0
A74: Anvendt underskud | C74: 0 | D74: =MIN(D73,MAX(D72,0)) -> 0 | E74: =MIN(E73,MAX(E72,0)) -> 0 | F74: =MIN(F73,MAX(F72,0)) -> 0 | G74: =MIN(G73,MAX(G72,0)) -> 0 | H74: =MIN(H73,MAX(H72,0)) -> 0 | I74: =MIN(I73,MAX(I72,0)) -> 0 | J74: =MIN(J73,MAX(J72,0)) -> 0 | K74: =MIN(K73,MAX(K72,0)) -> 0 | ... W74: =MIN(W73,MAX(W72,0)) -> 0
A75: Fremført underskud ultimo | C75: 0 | D75: =D73-D74+MAX(-D72,0) -> 0 | E75: =E73-E74+MAX(-E72,0) -> 0 | F75: =F73-F74+MAX(-F72,0) -> 0 | G75: =G73-G74+MAX(-G72,0) -> 0 | H75: =H73-H74+MAX(-H72,0) -> 0 | I75: =I73-I74+MAX(-I72,0) -> 0 | J75: =J73-J74+MAX(-J72,0) -> 0 | K75: =K73-K74+MAX(-K72,0) -> 0 | ... W75: =W73-W74+MAX(-W72,0) -> 0
A76: Selskabsskat | C76: 0 | D76: =-MAX(D72-D74,0)*$B$35 -> -117.03937 | E76: =-MAX(E72-E74,0)*$B$35 -> -68716.335 | F76: =-MAX(F72-F74,0)*$B$35 -> -119783.39 | G76: =-MAX(G72-G74,0)*$B$35 -> -157740.1 | H76: =-MAX(H72-H74,0)*$B$35 -> -185902.05 | I76: =-MAX(I72-I74,0)*$B$35 -> -206755.12 | J76: =-MAX(J72-J74,0)*$B$35 -> -222162.95 | K76: =-MAX(K72-K74,0)*$B$35 -> -233522.52 | ... W76: =-MAX(W72-W74,0)*$B$35 -> 0
A77: Cash flow efter skat | C77: =C66+C76 -> -5150000 | D77: =D66+D76 -> 1287915 | E77: =E66+E76 -> 1209255.6 | F77: =F66+F76 -> 1148905.3 | G77: =G66+G76 -> 1102424.4 | H77: =H66+H76 -> 1066480.3 | I77: =I66+I76 -> 1038570.7 | J77: =J66+J76 -> 1016816 | ... W77: =W66+W76 -> 0
A78: Akkumuleret cash flow efter skat | C78: =C77 -> -5150000 | D78: =C78+D77 -> -3862085 | E78: =D78+E77 -> -2652829.4 | F78: =E78+F77 -> -1503924.1 | G78: =F78+G77 -> -401499.64 | H78: =G78+H77 -> 664980.68 | I78: =H78+I77 -> 1703551.3 | J78: =I78+J77 -> 2720367.3 | K78: =J78+K77 -> 3720171.3 | ... W78: =V78+W77 -> 10487305
A79: Tilbagebetalt i år (hjælpelinje) | D79: =IF(AND(D78>=0,C78<0),D51,"") | E79: =IF(AND(E78>=0,D78<0),E51,"") | F79: =IF(AND(F78>=0,E78<0),F51,"") | G79: =IF(AND(G78>=0,F78<0),G51,"") | H79: =IF(AND(H78>=0,G78<0),H51,"") -> 5 | I79: =IF(AND(I78>=0,H78<0),I51,"") | J79: =IF(AND(J78>=0,I78<0),J51,"") | K79: =IF(AND(K78>=0,J78<0),K51,"") | ... W79: =IF(AND(W78>=0,V78<0),W51,"")
A81: Nøgletal
A82: IRR før skat (projekt, ugearet) | B82: =IFERROR(IRR(C66:W66),"negativ") -> 0.23418177
A83: IRR efter skat (projekt, ugearet) | B83: =IFERROR(IRR(C77:W77),"negativ") -> 0.20329599
A84: NPV efter skat | B84: =NPV($B$37,D77:W77)+C77 -> 4038497.4
A85: Simpel tilbagebetalingstid (år) | B85: =IF(COUNT(D79:W79)=0,"> levetid",MIN(D79:W79)) -> 5
A86: Samlet investering | B86: =$B$42 -> 5150000
A87: Investering pr. kWh | B87: =$B$43 -> 257.5
A88: Investering pr. MW | B88: =$B$44 -> 515000
A89: Markedsindtægt år 1 pr. MW | B89: =D58/$B$5 -> 172202.52
A90: EBITDA år 1 | B90: =D64 -> 1288032
A91: EBITDA-margin år 1 | B91: =IFERROR(D64/D58,0) -> 0.74797513
A92: EBITDA år 1 / investering | B92: =D64/$B$42 -> 0.2501033

Sheet Følsomhed
A1: Følsomhed: IRR før skat i base-scenariet ved ændret investering og markedsindtægt
A2: Markedsindtægt skaleres (arbitrage + systemydelser); nettariffer følger volumen og skaleres ikke. Drift og forsikring følger investeringen. Ændr faktorerne i de gule celler.
A4: Markedsindtægt (faktor) ned / investering (faktor) hen | B4: 0.6 | C4: 0.8 | D4: 0.9 | E4: 1 | F4: 1.1 | G4: 1.2
A5: 0.7 | B5: =IFERROR(IRR(B14:V14),"negativ") -> -0.028822658 | C5: =IFERROR(IRR(B15:V15),"negativ") -> -0.083620099 | D5: =IFERROR(IRR(B16:V16),"negativ") -> -0.10737553 | E5: =IFERROR(IRR(B17:V17),"negativ") -> negativ | F5: =IFERROR(IRR(B18:V18),"negativ") -> negativ | G5: =IFERROR(IRR(B19:V19),"negativ") -> negativ
A6: 0.85 | B6: =IFERROR(IRR(B20:V20),"negativ") -> 0.040689133 | C6: =IFERROR(IRR(B21:V21),"negativ") -> -0.014401728 | D6: =IFERROR(IRR(B22:V22),"negativ") -> -0.036089053 | E6: =IFERROR(IRR(B23:V23),"negativ") -> -0.055428956 | F6: =IFERROR(IRR(B24:V24),"negativ") -> -0.073105692 | G6: =IFERROR(IRR(B25:V25),"negativ") -> -0.089613227
A7: 1 | B7: =IFERROR(IRR(B26:V26),"negativ") -> 0.095455337 | C7: =IFERROR(IRR(B27:V27),"negativ") -> 0.035692246 | D7: =IFERROR(IRR(B28:V28),"negativ") -> 0.013097621 | E7: =IFERROR(IRR(B29:V29),"negativ") -> -0.0065111185 | F7: =IFERROR(IRR(B30:V30),"negativ") -> -0.02392159 | G7: =IFERROR(IRR(B31:V31),"negativ") -> -0.039673975
A8: 1.15 | B8: =IFERROR(IRR(B32:V32),"negativ") -> 0.14352006 | C8: =IFERROR(IRR(B33:V33),"negativ") -> 0.077698472 | D8: =IFERROR(IRR(B34:V34),"negativ") -> 0.053440653 | E8: =IFERROR(IRR(B35:V35),"negativ") -> 0.032719424 | F8: =IFERROR(IRR(B36:V36),"negativ") -> 0.01461031 | G8: =IFERROR(IRR(B37:V37),"negativ") -> -0.0015119058
A9: 1.3 | B9: =IFERROR(IRR(B38:V38),"negativ") -> 0.18787181 | C9: =IFERROR(IRR(B39:V39),"negativ") -> 0.11526374 | D9: =IFERROR(IRR(B40:V40),"negativ") -> 0.089001224 | E9: =IFERROR(IRR(B41:V41),"negativ") -> 0.066817838 | F9: =IFERROR(IRR(B42:V42),"negativ") -> 0.047640347 | G9: =IFERROR(IRR(B43:V43),"negativ") -> 0.030748294
A10: 1.5 | B10: =IFERROR(IRR(B44:V44),"negativ") -> 0.24362723 | C10: =IFERROR(IRR(B45:V45),"negativ") -> 0.1612362 | D10: =IFERROR(IRR(B46:V46),"negativ") -> 0.13199252 | E10: =IFERROR(IRR(B47:V47),"negativ") -> 0.10756616 | F10: =IFERROR(IRR(B48:V48),"negativ") -> 0.086673876 | G10: =IFERROR(IRR(B49:V49),"negativ") -> 0.06845956
A13: Hjælpeberegning (cash flow før skat pr. kombination)
A14: ="Indtægt "&TEXT($A$5,"0%")&" / investering "&TEXT(B$4,"0%") -> Indtægt 70% / investering 60% | B14: =Base!C65*B$4 -> -3750000 | C14: =$A$5*Base!D58*(1-Base!$B$31)+Base!D59+B$4*Base!D60+Base!D62+Base!D63 -> 296581.9 | D14: =$A$5*Base!E58*(1-Base!$B$31)+Base!E59+B$4*Base!E60+Base!E62+Base!E63 -> 282689.5 | E14: =$A$5*Base!F58*(1-Base!$B$31)+Base!F59+B$4*Base!F60+Base!F62+Base!F63 -> 268951.26 | F14: =$A$5*Base!G58*(1-Base!$B$31)+Base!G59+B$4*Base!G60+Base!G62+Base!G63 -> 255359.88 | G14: =$A$5*Base!H58*(1-Base!$B$31)+Base!H59+B$4*Base!H60+Base!H62+Base!H63 -> 241908.18 | H14: =$A$5*Base!I58*(1-Base!$B$31)+Base!I59+B$4*Base!I60+Base!I62+Base!I63 -> 228589.13 | I14: =$A$5*Base!J58*(1-Base!$B$31)+Base!J59+B$4*Base!J60+Base!J62+Base!J63 -> 215395.82 | J14: =$A$5*Base!K58*(1-Base!$B$31)+Base!K59+B$4*Base!K60+Base!K62+Base!K63 -> 202321.5 | K14: =$A$5*Base!L58*(1-Base!$B$31)+Base!L59+B$4*Base!L60+Base!L62+Base!L63 -> 189359.5 | L14: =$A$5*Base!M58*(1-Base!$B$31)+Base!M59+B$4*Base!M60+Base!M62+Base!M63 -> 176503.3 | M14: =$A$5*Base!N58*(1-Base!$B$31)+Base!N59+B$4*Base!N60+Base!N62+Base!N63 -> 163746.48 | N14: =$A$5*Base!O58*(1-Base!$B$31)+Base!O59+B$4*Base!O60+Base!O62+Base!O63 -> 151082.72 | O14: =$A$5*Base!P58*(1-Base!$B$31)+Base!P59+B$4*Base!P60+Base!P62+Base!P63 -> 138505.81 | P14: =$A$5*Base!Q58*(1-Base!$B$31)+Base!Q59+B$4*Base!Q60+Base!Q62+Base!Q63 -> 126009.64 | Q14: =$A$5*Base!R58*(1-Base!$B$31)+Base!R59+B$4*Base!R60+Base!R62+Base!R63 -> 113588.18 | R14: =$A$5*Base!S58*(1-Base!$B$31)+Base!S59+B$4*Base!S60+Base!S62+Base!S63 -> 0 | S14: =$A$5*Base!T58*(1-Base!$B$31)+Base!T59+B$4*Base!T60+Base!T62+Base!T63 -> 0 | T14: =$A$5*Base!U58*(1-Base!$B$31)+Base!U59+B$4*Base!U60+Base!U62+Base!U63 -> 0 | U14: =$A$5*Base!V58*(1-Base!$B$31)+Base!V59+B$4*Base!V60+Base!V62+Base!V63 -> 0 | V14: =$A$5*Base!W58*(1-Base!$B$31)+Base!W59+B$4*Base!W60+Base!W62+Base!W63 -> 0
A15: ="Indtægt "&TEXT($A$5,"0%")&" / investering "&TEXT(C$4,"0%") -> Indtægt 70% / investering 80% | B15: =Base!C65*C$4 -> -5000000 | C15: =$A$5*Base!D58*(1-Base!$B$31)+Base!D59+C$4*Base!D60+Base!D62+Base!D63 -> 272860.78 | D15: =$A$5*Base!E58*(1-Base!$B$31)+Base!E59+C$4*Base!E60+Base!E62+Base!E63 -> 258493.95 | E15: =$A$5*Base!F58*(1-Base!$B$31)+Base!F59+C$4*Base!F60+Base!F62+Base!F63 -> 244271.81 | F15: =$A$5*Base!G58*(1-Base!$B$31)+Base!G59+C$4*Base!G60+Base!G62+Base!G63 -> 230186.84 | G15: =$A$5*Base!H58*(1-Base!$B$31)+Base!H59+C$4*Base!H60+Base!H62+Base!H63 -> 216231.68 | H15: =$A$5*Base!I58*(1-Base!$B$31)+Base!I59+C$4*Base!I60+Base!I62+Base!I63 -> 202399.09 | I15: =$A$5*Base!J58*(1-Base!$B$31)+Base!J59+C$4*Base!J60+Base!J62+Base!J63 -> 188681.99 | J15: =$A$5*Base!K58*(1-Base!$B$31)+Base!K59+C$4*Base!K60+Base!K62+Base!K63 -> 175073.39 | K15: =$A$5*Base!L58*(1-Base!$B$31)+Base!L59+C$4*Base!L60+Base!L62+Base!L63 -> 161566.43 | L15: =$A$5*Base!M58*(1-Base!$B$31)+Base!M59+C$4*Base!M60+Base!M62+Base!M63 -> 148154.37 | M15: =$A$5*Base!N58*(1-Base!$B$31)+Base!N59+C$4*Base!N60+Base!N62+Base!N63 -> 134830.57 | N15: =$A$5*Base!O58*(1-Base!$B$31)+Base!O59+C$4*Base!O60+Base!O62+Base!O63 -> 121588.49 | O15: =$A$5*Base!P58*(1-Base!$B$31)+Base!P59+C$4*Base!P60+Base!P62+Base!P63 -> 108421.7 | P15: =$A$5*Base!Q58*(1-Base!$B$31)+Base!Q59+C$4*Base!Q60+Base!Q62+Base!Q63 -> 95323.843 | Q15: =$A$5*Base!R58*(1-Base!$B$31)+Base!R59+C$4*Base!R60+Base!R62+Base!R63 -> 82288.67 | R15: =$A$5*Base!S58*(1-Base!$B$31)+Base!S59+C$4*Base!S60+Base!S62+Base!S63 -> 0 | S15: =$A$5*Base!T58*(1-Base!$B$31)+Base!T59+C$4*Base!T60+Base!T62+Base!T63 -> 0 | T15: =$A$5*Base!U58*(1-Base!$B$31)+Base!U59+C$4*Base!U60+Base!U62+Base!U63 -> 0 | U15: =$A$5*Base!V58*(1-Base!$B$31)+Base!V59+C$4*Base!V60+Base!V62+Base!V63 -> 0 | V15: =$A$5*Base!W58*(1-Base!$B$31)+Base!W59+C$4*Base!W60+Base!W62+Base!W63 -> 0
A16: ="Indtægt "&TEXT($A$5,"0%")&" / investering "&TEXT(D$4,"0%") -> Indtægt 70% / investering 90% | B16: =Base!C65*D$4 -> -5625000 | C16: =$A$5*Base!D58*(1-Base!$B$31)+Base!D59+D$4*Base!D60+Base!D62+Base!D63 -> 261000.22 | D16: =$A$5*Base!E58*(1-Base!$B$31)+Base!E59+D$4*Base!E60+Base!E62+Base!E63 -> 246396.18 | E16: =$A$5*Base!F58*(1-Base!$B$31)+Base!F59+D$4*Base!F60+Base!F62+Base!F63 -> 231932.08 | F16: =$A$5*Base!G58*(1-Base!$B$31)+Base!G59+D$4*Base!G60+Base!G62+Base!G63 -> 217600.32 | G16: =$A$5*Base!H58*(1-Base!$B$31)+Base!H59+D$4*Base!H60+Base!H62+Base!H63 -> 203393.43 | H16: =$A$5*Base!I58*(1-Base!$B$31)+Base!I59+D$4*Base!I60+Base!I62+Base!I63 -> 189304.08 | I16: =$A$5*Base!J58*(1-Base!$B$31)+Base!J59+D$4*Base!J60+Base!J62+Base!J63 -> 175325.07 | J16: =$A$5*Base!K58*(1-Base!$B$31)+Base!K59+D$4*Base!K60+Base!K62+Base!K63 -> 161449.33 | K16: =$A$5*Base!L58*(1-Base!$B$31)+Base!L59+D$4*Base!L60+Base!L62+Base!L63 -> 147669.89 | L16: =$A$5*Base!M58*(1-Base!$B$31)+Base!M59+D$4*Base!M60+Base!M62+Base!M63 -> 133979.9 | M16: =$A$5*Base!N58*(1-Base!$B$31)+Base!N59+D$4*Base!N60+Base!N62+Base!N63 -> 120372.61 | N16: =$A$5*Base!O58*(1-Base!$B$31)+Base!O59+D$4*Base!O60+Base!O62+Base!O63 -> 106841.38 | O16: =$A$5*Base!P58*(1-Base!$B$31)+Base!P59+D$4*Base!P60+Base!P62+Base!P63 -> 93379.639 | P16: =$A$5*Base!Q58*(1-Base!$B$31)+Base!Q59+D$4*Base!Q60+Base!Q62+Base!Q63 -> 79980.944 | Q16: =$A$5*Base!R58*(1-Base!$B$31)+Base!R59+D$4*Base!R60+Base!R62+Base!R63 -> 66638.913 | R16: =$A$5*Base!S58*(1-Base!$B$31)+Base!S59+D$4*Base!S60+Base!S62+Base!S63 -> 0 | S16: =$A$5*Base!T58*(1-Base!$B$31)+Base!T59+D$4*Base!T60+Base!T62+Base!T63 -> 0 | T16: =$A$5*Base!U58*(1-Base!$B$31)+Base!U59+D$4*Base!U60+Base!U62+Base!U63 -> 0 | U16: =$A$5*Base!V58*(1-Base!$B$31)+Base!V59+D$4*Base!V60+Base!V62+Base!V63 -> 0 | V16: =$A$5*Base!W58*(1-Base!$B$31)+Base!W59+D$4*Base!W60+Base!W62+Base!W63 -> 0
A17: ="Indtægt "&TEXT($A$5,"0%")&" / investering "&TEXT(E$4,"0%") -> Indtægt 70% / investering 100% | B17: =Base!C65*E$4 -> -6250000 | C17: =$A$5*Base!D58*(1-Base!$B$31)+Base!D59+E$4*Base!D60+Base!D62+Base!D63 -> 249139.66 | D17: =$A$5*Base!E58*(1-Base!$B$31)+Base!E59+E$4*Base!E60+Base!E62+Base!E63 -> 234298.41 | E17: =$A$5*Base!F58*(1-Base!$B$31)+Base!F59+E$4*Base!F60+Base!F62+Base!F63 -> 219592.36 | F17: =$A$5*Base!G58*(1-Base!$B$31)+Base!G59+E$4*Base!G60+Base!G62+Base!G63 -> 205013.8 | G17: =$A$5*Base!H58*(1-Base!$B$31)+Base!H59+E$4*Base!H60+Base!H62+Base!H63 -> 190555.17 | H17: =$A$5*Base!I58*(1-Base!$B$31)+Base!I59+E$4*Base!I60+Base!I62+Base!I63 -> 176209.06 | I17: =$A$5*Base!J58*(1-Base!$B$31)+Base!J59+E$4*Base!J60+Base!J62+Base!J63 -> 161968.16 | J17: =$A$5*Base!K58*(1-Base!$B$31)+Base!K59+E$4*Base!K60+Base!K62+Base!K63 -> 147825.28 | K17: =$A$5*Base!L58*(1-Base!$B$31)+Base!L59+E$4*Base!L60+Base!L62+Base!L63 -> 133773.36 | L17: =$A$5*Base!M58*(1-Base!$B$31)+Base!M59+E$4*Base!M60+Base!M62+Base!M63 -> 119805.44 | M17: =$A$5*Base!N58*(1-Base!$B$31)+Base!N59+E$4*Base!N60+Base!N62+Base!N63 -> 105914.66 | N17: =$A$5*Base!O58*(1-Base!$B$31)+Base!O59+E$4*Base!O60+Base!O62+Base!O63 -> 92094.259 | O17: =$A$5*Base!P58*(1-Base!$B$31)+Base!P59+E$4*Base!P60+Base!P62+Base!P63 -> 78337.581 | P17: =$A$5*Base!Q58*(1-Base!$B$31)+Base!Q59+E$4*Base!Q60+Base!Q62+Base!Q63 -> 64638.045 | Q17: =$A$5*Base!R58*(1-Base!$B$31)+Base!R59+E$4*Base!R60+Base!R62+Base!R63 -> 50989.156 | R17: =$A$5*Base!S58*(1-Base!$B$31)+Base!S59+E$4*Base!S60+Base!S62+Base!S63 -> 0 | S17: =$A$5*Base!T58*(1-Base!$B$31)+Base!T59+E$4*Base!T60+Base!T62+Base!T63 -> 0 | T17: =$A$5*Base!U58*(1-Base!$B$31)+Base!U59+E$4*Base!U60+Base!U62+Base!U63 -> 0 | U17: =$A$5*Base!V58*(1-Base!$B$31)+Base!V59+E$4*Base!V60+Base!V62+Base!V63 -> 0 | V17: =$A$5*Base!W58*(1-Base!$B$31)+Base!W59+E$4*Base!W60+Base!W62+Base!W63 -> 0
A18: ="Indtægt "&TEXT($A$5,"0%")&" / investering "&TEXT(F$4,"0%") -> Indtægt 70% / investering 110% | B18: =Base!C65*F$4 -> -6875000 | C18: =$A$5*Base!D58*(1-Base!$B$31)+Base!D59+F$4*Base!D60+Base!D62+Base!D63 -> 237279.1 | D18: =$A$5*Base!E58*(1-Base!$B$31)+Base!E59+F$4*Base!E60+Base!E62+Base!E63 -> 222200.64 | E18: =$A$5*Base!F58*(1-Base!$B$31)+Base!F59+F$4*Base!F60+Base!F62+Base!F63 -> 207252.63 | F18: =$A$5*Base!G58*(1-Base!$B$31)+Base!G59+F$4*Base!G60+Base!G62+Base!G63 -> 192427.28 | G18: =$A$5*Base!H58*(1-Base!$B$31)+Base!H59+F$4*Base!H60+Base!H62+Base!H63 -> 177716.92 | H18: =$A$5*Base!I58*(1-Base!$B$31)+Base!I59+F$4*Base!I60+Base!I62+Base!I63 -> 163114.04 | I18: =$A$5*Base!J58*(1-Base!$B$31)+Base!J59+F$4*Base!J60+Base!J62+Base!J63 -> 148611.24 | J18: =$A$5*Base!K58*(1-Base!$B$31)+Base!K59+F$4*Base!K60+Base!K62+Base!K63 -> 134201.22 | K18: =$A$5*Base!L58*(1-Base!$B$31)+Base!L59+F$4*Base!L60+Base!L62+Base!L63 -> 119876.82 | L18: =$A$5*Base!M58*(1-Base!$B$31)+Base!M59+F$4*Base!M60+Base!M62+Base!M63 -> 105630.97 | M18: =$A$5*Base!N58*(1-Base!$B$31)+Base!N59+F$4*Base!N60+Base!N62+Base!N63 -> 91456.7 | N18: =$A$5*Base!O58*(1-Base!$B$31)+Base!O59+F$4*Base!O60+Base!O62+Base!O63 -> 77347.144 | O18: =$A$5*Base!P58*(1-Base!$B$31)+Base!P59+F$4*Base!P60+Base!P62+Base!P63 -> 63295.523 | P18: =$A$5*Base!Q58*(1-Base!$B$31)+Base!Q59+F$4*Base!Q60+Base!Q62+Base!Q63 -> 49295.146 | Q18: =$A$5*Base!R58*(1-Base!$B$31)+Base!R59+F$4*Base!R60+Base!R62+Base!R63 -> 35339.399 | R18: =$A$5*Base!S58*(1-Base!$B$31)+Base!S59+F$4*Base!S60+Base!S62+Base!S63 -> 0 | S18: =$A$5*Base!T58*(1-Base!$B$31)+Base!T59+F$4*Base!T60+Base!T62+Base!T63 -> 0 | T18: =$A$5*Base!U58*(1-Base!$B$31)+Base!U59+F$4*Base!U60+Base!U62+Base!U63 -> 0 | U18: =$A$5*Base!V58*(1-Base!$B$31)+Base!V59+F$4*Base!V60+Base!V62+Base!V63 -> 0 | V18: =$A$5*Base!W58*(1-Base!$B$31)+Base!W59+F$4*Base!W60+Base!W62+Base!W63 -> 0
A19: ="Indtægt "&TEXT($A$5,"0%")&" / investering "&TEXT(G$4,"0%") -> Indtægt 70% / investering 120% | B19: =Base!C65*G$4 -> -7500000 | C19: =$A$5*Base!D58*(1-Base!$B$31)+Base!D59+G$4*Base!D60+Base!D62+Base!D63 -> 225418.54 | D19: =$A$5*Base!E58*(1-Base!$B$31)+Base!E59+G$4*Base!E60+Base!E62+Base!E63 -> 210102.87 | E19: =$A$5*Base!F58*(1-Base!$B$31)+Base!F59+G$4*Base!F60+Base!F62+Base!F63 -> 194912.9 | F19: =$A$5*Base!G58*(1-Base!$B$31)+Base!G59+G$4*Base!G60+Base!G62+Base!G63 -> 179840.75 | G19: =$A$5*Base!H58*(1-Base!$B$31)+Base!H59+G$4*Base!H60+Base!H62+Base!H63 -> 164878.67 | H19: =$A$5*Base!I58*(1-Base!$B$31)+Base!I59+G$4*Base!I60+Base!I62+Base!I63 -> 150019.03 | I19: =$A$5*Base!J58*(1-Base!$B$31)+Base!J59+G$4*Base!J60+Base!J62+Base!J63 -> 135254.32 | J19: =$A$5*Base!K58*(1-Base!$B$31)+Base!K59+G$4*Base!K60+Base!K62+Base!K63 -> 120577.17 | K19: =$A$5*Base!L58*(1-Base!$B$31)+Base!L59+G$4*Base!L60+Base!L62+Base!L63 -> 105980.29 | L19: =$A$5*Base!M58*(1-Base!$B$31)+Base!M59+G$4*Base!M60+Base!M62+Base!M63 -> 91456.502 | M19: =$A$5*Base!N58*(1-Base!$B$31)+Base!N59+G$4*Base!N60+Base!N62+Base!N63 -> 76998.743 | N19: =$A$5*Base!O58*(1-Base!$B$31)+Base!O59+G$4*Base!O60+Base!O62+Base!O63 -> 62600.028 | O19: =$A$5*Base!P58*(1-Base!$B$31)+Base!P59+G$4*Base!P60+Base!P62+Base!P63 -> 48253.466 | P19: =$A$5*Base!Q58*(1-Base!$B$31)+Base!Q59+G$4*Base!Q60+Base!Q62+Base!Q63 -> 33952.247 | Q19: =$A$5*Base!R58*(1-Base!$B$31)+Base!R59+G$4*Base!R60+Base!R62+Base!R63 -> 19689.642 | R19: =$A$5*Base!S58*(1-Base!$B$31)+Base!S59+G$4*Base!S60+Base!S62+Base!S63 -> 0 | S19: =$A$5*Base!T58*(1-Base!$B$31)+Base!T59+G$4*Base!T60+Base!T62+Base!T63 -> 0 | T19: =$A$5*Base!U58*(1-Base!$B$31)+Base!U59+G$4*Base!U60+Base!U62+Base!U63 -> 0 | U19: =$A$5*Base!V58*(1-Base!$B$31)+Base!V59+G$4*Base!V60+Base!V62+Base!V63 -> 0 | V19: =$A$5*Base!W58*(1-Base!$B$31)+Base!W59+G$4*Base!W60+Base!W62+Base!W63 -> 0
A20: ="Indtægt "&TEXT($A$6,"0%")&" / investering "&TEXT(B$4,"0%") -> Indtægt 85% / investering 60% | B20: =Base!C65*B$4 -> -3750000 | C20: =$A$6*Base!D58*(1-Base!$B$31)+Base!D59+B$4*Base!D60+Base!D62+Base!D63 -> 435328.61 | D20: =$A$6*Base!E58*(1-Base!$B$31)+Base!E59+B$4*Base!E60+Base!E62+Base!E63 -> 419195.08 | E20: =$A$6*Base!F58*(1-Base!$B$31)+Base!F59+B$4*Base!F60+Base!F62+Base!F63 -> 403263.78 | F20: =$A$6*Base!G58*(1-Base!$B$31)+Base!G59+B$4*Base!G60+Base!G62+Base!G63 -> 387526.11 | G20: =$A$6*Base!H58*(1-Base!$B$31)+Base!H59+B$4*Base!H60+Base!H62+Base!H63 -> 371973.69 | H20: =$A$6*Base!I58*(1-Base!$B$31)+Base!I59+B$4*Base!I60+Base!I62+Base!I63 -> 356598.29 | I20: =$A$6*Base!J58*(1-Base!$B$31)+Base!J59+B$4*Base!J60+Base!J62+Base!J63 -> 341391.84 | J20: =$A$6*Base!K58*(1-Base!$B$31)+Base!K59+B$4*Base!K60+Base!K62+Base!K63 -> 326346.46 | K20: =$A$6*Base!L58*(1-Base!$B$31)+Base!L59+B$4*Base!L60+Base!L62+Base!L63 -> 311454.39 | L20: =$A$6*Base!M58*(1-Base!$B$31)+Base!M59+B$4*Base!M60+Base!M62+Base!M63 -> 296708.04 | M20: =$A$6*Base!N58*(1-Base!$B$31)+Base!N59+B$4*Base!N60+Base!N62+Base!N63 -> 282099.97 | N20: =$A$6*Base!O58*(1-Base!$B$31)+Base!O59+B$4*Base!O60+Base!O62+Base!O63 -> 267622.86 | O20: =$A$6*Base!P58*(1-Base!$B$31)+Base!P59+B$4*Base!P60+Base!P62+Base!P63 -> 253269.52 | P20: =$A$6*Base!Q58*(1-Base!$B$31)+Base!Q59+B$4*Base!Q60+Base!Q62+Base!Q63 -> 239032.89 | Q20: =$A$6*Base!R58*(1-Base!$B$31)+Base!R59+B$4*Base!R60+Base!R62+Base!R63 -> 224906.05 | R20: =$A$6*Base!S58*(1-Base!$B$31)+Base!S59+B$4*Base!S60+Base!S62+Base!S63 -> 0 | S20: =$A$6*Base!T58*(1-Base!$B$31)+Base!T59+B$4*Base!T60+Base!T62+Base!T63 -> 0 | T20: =$A$6*Base!U58*(1-Base!$B$31)+Base!U59+B$4*Base!U60+Base!U62+Base!U63 -> 0 | U20: =$A$6*Base!V58*(1-Base!$B$31)+Base!V59+B$4*Base!V60+Base!V62+Base!V63 -> 0 | V20: =$A$6*Base!W58*(1-Base!$B$31)+Base!W59+B$4*Base!W60+Base!W62+Base!W63 -> 0
A21: ="Indtægt "&TEXT($A$6,"0%")&" / investering "&TEXT(C$4,"0%") -> Indtægt 85% / investering 80% | B21: =Base!C65*C$4 -> -5000000 | C21: =$A$6*Base!D58*(1-Base!$B$31)+Base!D59+C$4*Base!D60+Base!D62+Base!D63 -> 411607.49 | D21: =$A$6*Base!E58*(1-Base!$B$31)+Base!E59+C$4*Base!E60+Base!E62+Base!E63 -> 394999.54 | E21: =$A$6*Base!F58*(1-Base!$B$31)+Base!F59+C$4*Base!F60+Base!F62+Base!F63 -> 378584.32 | F21: =$A$6*Base!G58*(1-Base!$B$31)+Base!G59+C$4*Base!G60+Base!G62+Base!G63 -> 362353.07 | G21: =$A$6*Base!H58*(1-Base!$B$31)+Base!H59+C$4*Base!H60+Base!H62+Base!H63 -> 346297.19 | H21: =$A$6*Base!I58*(1-Base!$B$31)+Base!I59+C$4*Base!I60+Base!I62+Base!I63 -> 330408.26 | I21: =$A$6*Base!J58*(1-Base!$B$31)+Base!J59+C$4*Base!J60+Base!J62+Base!J63 -> 314678.01 | J21: =$A$6*Base!K58*(1-Base!$B$31)+Base!K59+C$4*Base!K60+Base!K62+Base!K63 -> 299098.35 | K21: =$A$6*Base!L58*(1-Base!$B$31)+Base!L59+C$4*Base!L60+Base!L62+Base!L63 -> 283661.32 | L21: =$A$6*Base!M58*(1-Base!$B$31)+Base!M59+C$4*Base!M60+Base!M62+Base!M63 -> 268359.11 | M21: =$A$6*Base!N58*(1-Base!$B$31)+Base!N59+C$4*Base!N60+Base!N62+Base!N63 -> 253184.06 | N21: =$A$6*Base!O58*(1-Base!$B$31)+Base!O59+C$4*Base!O60+Base!O62+Base!O63 -> 238128.63 | O21: =$A$6*Base!P58*(1-Base!$B$31)+Base!P59+C$4*Base!P60+Base!P62+Base!P63 -> 223185.4 | P21: =$A$6*Base!Q58*(1-Base!$B$31)+Base!Q59+C$4*Base!Q60+Base!Q62+Base!Q63 -> 208347.09 | Q21: =$A$6*Base!R58*(1-Base!$B$31)+Base!R59+C$4*Base!R60+Base!R62+Base!R63 -> 193606.53 | R21: =$A$6*Base!S58*(1-Base!$B$31)+Base!S59+C$4*Base!S60+Base!S62+Base!S63 -> 0 | S21: =$A$6*Base!T58*(1-Base!$B$31)+Base!T59+C$4*Base!T60+Base!T62+Base!T63 -> 0 | T21: =$A$6*Base!U58*(1-Base!$B$31)+Base!U59+C$4*Base!U60+Base!U62+Base!U63 -> 0 | U21: =$A$6*Base!V58*(1-Base!$B$31)+Base!V59+C$4*Base!V60+Base!V62+Base!V63 -> 0 | V21: =$A$6*Base!W58*(1-Base!$B$31)+Base!W59+C$4*Base!W60+Base!W62+Base!W63 -> 0
A22: ="Indtægt "&TEXT($A$6,"0%")&" / investering "&TEXT(D$4,"0%") -> Indtægt 85% / investering 90% | B22: =Base!C65*D$4 -> -5625000 | C22: =$A$6*Base!D58*(1-Base!$B$31)+Base!D59+D$4*Base!D60+Base!D62+Base!D63 -> 399746.93 | D22: =$A$6*Base!E58*(1-Base!$B$31)+Base!E59+D$4*Base!E60+Base!E62+Base!E63 -> 382901.77 | E22: =$A$6*Base!F58*(1-Base!$B$31)+Base!F59+D$4*Base!F60+Base!F62+Base!F63 -> 366244.6 | F22: =$A$6*Base!G58*(1-Base!$B$31)+Base!G59+D$4*Base!G60+Base!G62+Base!G63 -> 349766.55 | G22: =$A$6*Base!H58*(1-Base!$B$31)+Base!H59+D$4*Base!H60+Base!H62+Base!H63 -> 333458.94 | H22: =$A$6*Base!I58*(1-Base!$B$31)+Base!I59+D$4*Base!I60+Base!I62+Base!I63 -> 317313.24 | I22: =$A$6*Base!J58*(1-Base!$B$31)+Base!J59+D$4*Base!J60+Base!J62+Base!J63 -> 301321.09 | J22: =$A$6*Base!K58*(1-Base!$B$31)+Base!K59+D$4*Base!K60+Base!K62+Base!K63 -> 285474.29 | K22: =$A$6*Base!L58*(1-Base!$B$31)+Base!L59+D$4*Base!L60+Base!L62+Base!L63 -> 269764.78 | L22: =$A$6*Base!M58*(1-Base!$B$31)+Base!M59+D$4*Base!M60+Base!M62+Base!M63 -> 254184.64 | M22: =$A$6*Base!N58*(1-Base!$B$31)+Base!N59+D$4*Base!N60+Base!N62+Base!N63 -> 238726.1 | N22: =$A$6*Base!O58*(1-Base!$B$31)+Base!O59+D$4*Base!O60+Base!O62+Base!O63 -> 223381.51 | O22: =$A$6*Base!P58*(1-Base!$B$31)+Base!P59+D$4*Base!P60+Base!P62+Base!P63 -> 208143.34 | P22: =$A$6*Base!Q58*(1-Base!$B$31)+Base!Q59+D$4*Base!Q60+Base!Q62+Base!Q63 -> 193004.19 | Q22: =$A$6*Base!R58*(1-Base!$B$31)+Base!R59+D$4*Base!R60+Base!R62+Base!R63 -> 177956.77 | R22: =$A$6*Base!S58*(1-Base!$B$31)+Base!S59+D$4*Base!S60+Base!S62+Base!S63 -> 0 | S22: =$A$6*Base!T58*(1-Base!$B$31)+Base!T59+D$4*Base!T60+Base!T62+Base!T63 -> 0 | T22: =$A$6*Base!U58*(1-Base!$B$31)+Base!U59+D$4*Base!U60+Base!U62+Base!U63 -> 0 | U22: =$A$6*Base!V58*(1-Base!$B$31)+Base!V59+D$4*Base!V60+Base!V62+Base!V63 -> 0 | V22: =$A$6*Base!W58*(1-Base!$B$31)+Base!W59+D$4*Base!W60+Base!W62+Base!W63 -> 0
A23: ="Indtægt "&TEXT($A$6,"0%")&" / investering "&TEXT(E$4,"0%") -> Indtægt 85% / investering 100% | B23: =Base!C65*E$4 -> -6250000 | C23: =$A$6*Base!D58*(1-Base!$B$31)+Base!D59+E$4*Base!D60+Base!D62+Base!D63 -> 387886.37 | D23: =$A$6*Base!E58*(1-Base!$B$31)+Base!E59+E$4*Base!E60+Base!E62+Base!E63 -> 370804 | E23: =$A$6*Base!F58*(1-Base!$B$31)+Base!F59+E$4*Base!F60+Base!F62+Base!F63 -> 353904.87 | F23: =$A$6*Base!G58*(1-Base!$B$31)+Base!G59+E$4*Base!G60+Base!G62+Base!G63 -> 337180.03 | G23: =$A$6*Base!H58*(1-Base!$B$31)+Base!H59+E$4*Base!H60+Base!H62+Base!H63 -> 320620.69 | H23: =$A$6*Base!I58*(1-Base!$B$31)+Base!I59+E$4*Base!I60+Base!I62+Base!I63 -> 304218.22 | I23: =$A$6*Base!J58*(1-Base!$B$31)+Base!J59+E$4*Base!J60+Base!J62+Base!J63 -> 287964.18 | J23: =$A$6*Base!K58*(1-Base!$B$31)+Base!K59+E$4*Base!K60+Base!K62+Base!K63 -> 271850.24 | K23: =$A$6*Base!L58*(1-Base!$B$31)+Base!L59+E$4*Base!L60+Base!L62+Base!L63 -> 255868.24 | L23: =$A$6*Base!M58*(1-Base!$B$31)+Base!M59+E$4*Base!M60+Base!M62+Base!M63 -> 240010.18 | M23: =$A$6*Base!N58*(1-Base!$B$31)+Base!N59+E$4*Base!N60+Base!N62+Base!N63 -> 224268.15 | N23: =$A$6*Base!O58*(1-Base!$B$31)+Base!O59+E$4*Base!O60+Base!O62+Base!O63 -> 208634.39 | O23: =$A$6*Base!P58*(1-Base!$B$31)+Base!P59+E$4*Base!P60+Base!P62+Base!P63 -> 193101.28 | P23: =$A$6*Base!Q58*(1-Base!$B$31)+Base!Q59+E$4*Base!Q60+Base!Q62+Base!Q63 -> 177661.3 | Q23: =$A$6*Base!R58*(1-Base!$B$31)+Base!R59+E$4*Base!R60+Base!R62+Base!R63 -> 162307.02 | R23: =$A$6*Base!S58*(1-Base!$B$31)+Base!S59+E$4*Base!S60+Base!S62+Base!S63 -> 0 | S23: =$A$6*Base!T58*(1-Base!$B$31)+Base!T59+E$4*Base!T60+Base!T62+Base!T63 -> 0 | T23: =$A$6*Base!U58*(1-Base!$B$31)+Base!U59+E$4*Base!U60+Base!U62+Base!U63 -> 0 | U23: =$A$6*Base!V58*(1-Base!$B$31)+Base!V59+E$4*Base!V60+Base!V62+Base!V63 -> 0 | V23: =$A$6*Base!W58*(1-Base!$B$31)+Base!W59+E$4*Base!W60+Base!W62+Base!W63 -> 0
A24: ="Indtægt "&TEXT($A$6,"0%")&" / investering "&TEXT(F$4,"0%") -> Indtægt 85% / investering 110% | B24: =Base!C65*F$4 -> -6875000 | C24: =$A$6*Base!D58*(1-Base!$B$31)+Base!D59+F$4*Base!D60+Base!D62+Base!D63 -> 376025.81 | D24: =$A$6*Base!E58*(1-Base!$B$31)+Base!E59+F$4*Base!E60+Base!E62+Base!E63 -> 358706.22 | E24: =$A$6*Base!F58*(1-Base!$B$31)+Base!F59+F$4*Base!F60+Base!F62+Base!F63 -> 341565.14 | F24: =$A$6*Base!G58*(1-Base!$B$31)+Base!G59+F$4*Base!G60+Base!G62+Base!G63 -> 324593.51 | G24: =$A$6*Base!H58*(1-Base!$B$31)+Base!H59+F$4*Base!H60+Base!H62+Base!H63 -> 307782.44 | H24: =$A$6*Base!I58*(1-Base!$B$31)+Base!I59+F$4*Base!I60+Base!I62+Base!I63 -> 291123.21 | I24: =$A$6*Base!J58*(1-Base!$B$31)+Base!J59+F$4*Base!J60+Base!J62+Base!J63 -> 274607.26 | J24: =$A$6*Base!K58*(1-Base!$B$31)+Base!K59+F$4*Base!K60+Base!K62+Base!K63 -> 258226.18 | K24: =$A$6*Base!L58*(1-Base!$B$31)+Base!L59+F$4*Base!L60+Base!L62+Base!L63 -> 241971.71 | L24: =$A$6*Base!M58*(1-Base!$B$31)+Base!M59+F$4*Base!M60+Base!M62+Base!M63 -> 225835.71 | M24: =$A$6*Base!N58*(1-Base!$B$31)+Base!N59+F$4*Base!N60+Base!N62+Base!N63 -> 209810.19 | N24: =$A$6*Base!O58*(1-Base!$B$31)+Base!O59+F$4*Base!O60+Base!O62+Base!O63 -> 193887.28 | O24: =$A$6*Base!P58*(1-Base!$B$31)+Base!P59+F$4*Base!P60+Base!P62+Base!P63 -> 178059.23 | P24: =$A$6*Base!Q58*(1-Base!$B$31)+Base!Q59+F$4*Base!Q60+Base!Q62+Base!Q63 -> 162318.4 | Q24: =$A$6*Base!R58*(1-Base!$B$31)+Base!R59+F$4*Base!R60+Base!R62+Base!R63 -> 146657.26 | R24: =$A$6*Base!S58*(1-Base!$B$31)+Base!S59+F$4*Base!S60+Base!S62+Base!S63 -> 0 | S24: =$A$6*Base!T58*(1-Base!$B$31)+Base!T59+F$4*Base!T60+Base!T62+Base!T63 -> 0 | T24: =$A$6*Base!U58*(1-Base!$B$31)+Base!U59+F$4*Base!U60+Base!U62+Base!U63 -> 0 | U24: =$A$6*Base!V58*(1-Base!$B$31)+Base!V59+F$4*Base!V60+Base!V62+Base!V63 -> 0 | V24: =$A$6*Base!W58*(1-Base!$B$31)+Base!W59+F$4*Base!W60+Base!W62+Base!W63 -> 0
A25: ="Indtægt "&TEXT($A$6,"0%")&" / investering "&TEXT(G$4,"0%") -> Indtægt 85% / investering 120% | B25: =Base!C65*G$4 -> -7500000 | C25: =$A$6*Base!D58*(1-Base!$B$31)+Base!D59+G$4*Base!D60+Base!D62+Base!D63 -> 364165.25 | D25: =$A$6*Base!E58*(1-Base!$B$31)+Base!E59+G$4*Base!E60+Base!E62+Base!E63 -> 346608.45 | E25: =$A$6*Base!F58*(1-Base!$B$31)+Base!F59+G$4*Base!F60+Base!F62+Base!F63 -> 329225.42 | F25: =$A$6*Base!G58*(1-Base!$B$31)+Base!G59+G$4*Base!G60+Base!G62+Base!G63 -> 312006.99 | G25: =$A$6*Base!H58*(1-Base!$B$31)+Base!H59+G$4*Base!H60+Base!H62+Base!H63 -> 294944.18 | H25: =$A$6*Base!I58*(1-Base!$B$31)+Base!I59+G$4*Base!I60+Base!I62+Base!I63 -> 278028.19 | I25: =$A$6*Base!J58*(1-Base!$B$31)+Base!J59+G$4*Base!J60+Base!J62+Base!J63 -> 261250.34 | J25: =$A$6*Base!K58*(1-Base!$B$31)+Base!K59+G$4*Base!K60+Base!K62+Base!K63 -> 244602.13 | K25: =$A$6*Base!L58*(1-Base!$B$31)+Base!L59+G$4*Base!L60+Base!L62+Base!L63 -> 228075.17 | L25: =$A$6*Base!M58*(1-Base!$B$31)+Base!M59+G$4*Base!M60+Base!M62+Base!M63 -> 211661.24 | M25: =$A$6*Base!N58*(1-Base!$B$31)+Base!N59+G$4*Base!N60+Base!N62+Base!N63 -> 195352.23 | N25: =$A$6*Base!O58*(1-Base!$B$31)+Base!O59+G$4*Base!O60+Base!O62+Base!O63 -> 179140.16 | O25: =$A$6*Base!P58*(1-Base!$B$31)+Base!P59+G$4*Base!P60+Base!P62+Base!P63 -> 163017.17 | P25: =$A$6*Base!Q58*(1-Base!$B$31)+Base!Q59+G$4*Base!Q60+Base!Q62+Base!Q63 -> 146975.5 | Q25: =$A$6*Base!R58*(1-Base!$B$31)+Base!R59+G$4*Base!R60+Base!R62+Base!R63 -> 131007.5 | R25: =$A$6*Base!S58*(1-Base!$B$31)+Base!S59+G$4*Base!S60+Base!S62+Base!S63 -> 0 | S25: =$A$6*Base!T58*(1-Base!$B$31)+Base!T59+G$4*Base!T60+Base!T62+Base!T63 -> 0 | T25: =$A$6*Base!U58*(1-Base!$B$31)+Base!U59+G$4*Base!U60+Base!U62+Base!U63 -> 0 | U25: =$A$6*Base!V58*(1-Base!$B$31)+Base!V59+G$4*Base!V60+Base!V62+Base!V63 -> 0 | V25: =$A$6*Base!W58*(1-Base!$B$31)+Base!W59+G$4*Base!W60+Base!W62+Base!W63 -> 0
A26: ="Indtægt "&TEXT($A$7,"0%")&" / investering "&TEXT(B$4,"0%") -> Indtægt 100% / investering 60% | B26: =Base!C65*B$4 -> -3750000 | C26: =$A$7*Base!D58*(1-Base!$B$31)+Base!D59+B$4*Base!D60+Base!D62+Base!D63 -> 574075.33 | D26: =$A$7*Base!E58*(1-Base!$B$31)+Base!E59+B$4*Base!E60+Base!E62+Base!E63 -> 555700.66 | E26: =$A$7*Base!F58*(1-Base!$B$31)+Base!F59+B$4*Base!F60+Base!F62+Base!F63 -> 537576.29 | F26: =$A$7*Base!G58*(1-Base!$B$31)+Base!G59+B$4*Base!G60+Base!G62+Base!G63 -> 519692.35 | G26: =$A$7*Base!H58*(1-Base!$B$31)+Base!H59+B$4*Base!H60+Base!H62+Base!H63 -> 502039.21 | H26: =$A$7*Base!I58*(1-Base!$B$31)+Base!I59+B$4*Base!I60+Base!I62+Base!I63 -> 484607.45 | I26: =$A$7*Base!J58*(1-Base!$B$31)+Base!J59+B$4*Base!J60+Base!J62+Base!J63 -> 467387.86 | J26: =$A$7*Base!K58*(1-Base!$B$31)+Base!K59+B$4*Base!K60+Base!K62+Base!K63 -> 450371.42 | K26: =$A$7*Base!L58*(1-Base!$B$31)+Base!L59+B$4*Base!L60+Base!L62+Base!L63 -> 433549.27 | L26: =$A$7*Base!M58*(1-Base!$B$31)+Base!M59+B$4*Base!M60+Base!M62+Base!M63 -> 416912.78 | M26: =$A$7*Base!N58*(1-Base!$B$31)+Base!N59+B$4*Base!N60+Base!N62+Base!N63 -> 400453.46 | N26: =$A$7*Base!O58*(1-Base!$B$31)+Base!O59+B$4*Base!O60+Base!O62+Base!O63 -> 384162.99 | O26: =$A$7*Base!P58*(1-Base!$B$31)+Base!P59+B$4*Base!P60+Base!P62+Base!P63 -> 368033.22 | P26: =$A$7*Base!Q58*(1-Base!$B$31)+Base!Q59+B$4*Base!Q60+Base!Q62+Base!Q63 -> 352056.14 | Q26: =$A$7*Base!R58*(1-Base!$B$31)+Base!R59+B$4*Base!R60+Base!R62+Base!R63 -> 336223.91 | R26: =$A$7*Base!S58*(1-Base!$B$31)+Base!S59+B$4*Base!S60+Base!S62+Base!S63 -> 0 | S26: =$A$7*Base!T58*(1-Base!$B$31)+Base!T59+B$4*Base!T60+Base!T62+Base!T63 -> 0 | T26: =$A$7*Base!U58*(1-Base!$B$31)+Base!U59+B$4*Base!U60+Base!U62+Base!U63 -> 0 | U26: =$A$7*Base!V58*(1-Base!$B$31)+Base!V59+B$4*Base!V60+Base!V62+Base!V63 -> 0 | V26: =$A$7*Base!W58*(1-Base!$B$31)+Base!W59+B$4*Base!W60+Base!W62+Base!W63 -> 0
A27: ="Indtægt "&TEXT($A$7,"0%")&" / investering "&TEXT(C$4,"0%") -> Indtægt 100% / investering 80% | B27: =Base!C65*C$4 -> -5000000 | C27: =$A$7*Base!D58*(1-Base!$B$31)+Base!D59+C$4*Base!D60+Base!D62+Base!D63 -> 550354.21 | D27: =$A$7*Base!E58*(1-Base!$B$31)+Base!E59+C$4*Base!E60+Base!E62+Base!E63 -> 531505.12 | E27: =$A$7*Base!F58*(1-Base!$B$31)+Base!F59+C$4*Base!F60+Base!F62+Base!F63 -> 512896.83 | F27: =$A$7*Base!G58*(1-Base!$B$31)+Base!G59+C$4*Base!G60+Base!G62+Base!G63 -> 494519.3 | G27: =$A$7*Base!H58*(1-Base!$B$31)+Base!H59+C$4*Base!H60+Base!H62+Base!H63 -> 476362.7 | H27: =$A$7*Base!I58*(1-Base!$B$31)+Base!I59+C$4*Base!I60+Base!I62+Base!I63 -> 458417.42 | I27: =$A$7*Base!J58*(1-Base!$B$31)+Base!J59+C$4*Base!J60+Base!J62+Base!J63 -> 440674.03 | J27: =$A$7*Base!K58*(1-Base!$B$31)+Base!K59+C$4*Base!K60+Base!K62+Base!K63 -> 423123.3 | K27: =$A$7*Base!L58*(1-Base!$B$31)+Base!L59+C$4*Base!L60+Base!L62+Base!L63 -> 405756.2 | L27: =$A$7*Base!M58*(1-Base!$B$31)+Base!M59+C$4*Base!M60+Base!M62+Base!M63 -> 388563.85 | M27: =$A$7*Base!N58*(1-Base!$B$31)+Base!N59+C$4*Base!N60+Base!N62+Base!N63 -> 371537.55 | N27: =$A$7*Base!O58*(1-Base!$B$31)+Base!O59+C$4*Base!O60+Base!O62+Base!O63 -> 354668.76 | O27: =$A$7*Base!P58*(1-Base!$B$31)+Base!P59+C$4*Base!P60+Base!P62+Base!P63 -> 337949.1 | P27: =$A$7*Base!Q58*(1-Base!$B$31)+Base!Q59+C$4*Base!Q60+Base!Q62+Base!Q63 -> 321370.34 | Q27: =$A$7*Base!R58*(1-Base!$B$31)+Base!R59+C$4*Base!R60+Base!R62+Base!R63 -> 304924.39 | R27: =$A$7*Base!S58*(1-Base!$B$31)+Base!S59+C$4*Base!S60+Base!S62+Base!S63 -> 0 | S27: =$A$7*Base!T58*(1-Base!$B$31)+Base!T59+C$4*Base!T60+Base!T62+Base!T63 -> 0 | T27: =$A$7*Base!U58*(1-Base!$B$31)+Base!U59+C$4*Base!U60+Base!U62+Base!U63 -> 0 | U27: =$A$7*Base!V58*(1-Base!$B$31)+Base!V59+C$4*Base!V60+Base!V62+Base!V63 -> 0 | V27: =$A$7*Base!W58*(1-Base!$B$31)+Base!W59+C$4*Base!W60+Base!W62+Base!W63 -> 0
A28: ="Indtægt "&TEXT($A$7,"0%")&" / investering "&TEXT(D$4,"0%") -> Indtægt 100% / investering 90% | B28: =Base!C65*D$4 -> -5625000 | C28: =$A$7*Base!D58*(1-Base!$B$31)+Base!D59+D$4*Base!D60+Base!D62+Base!D63 -> 538493.65 | D28: =$A$7*Base!E58*(1-Base!$B$31)+Base!E59+D$4*Base!E60+Base!E62+Base!E63 -> 519407.35 | E28: =$A$7*Base!F58*(1-Base!$B$31)+Base!F59+D$4*Base!F60+Base!F62+Base!F63 -> 500557.11 | F28: =$A$7*Base!G58*(1-Base!$B$31)+Base!G59+D$4*Base!G60+Base!G62+Base!G63 -> 481932.78 | G28: =$A$7*Base!H58*(1-Base!$B$31)+Base!H59+D$4*Base!H60+Base!H62+Base!H63 -> 463524.45 | H28: =$A$7*Base!I58*(1-Base!$B$31)+Base!I59+D$4*Base!I60+Base!I62+Base!I63 -> 445322.4 | I28: =$A$7*Base!J58*(1-Base!$B$31)+Base!J59+D$4*Base!J60+Base!J62+Base!J63 -> 427317.11 | J28: =$A$7*Base!K58*(1-Base!$B$31)+Base!K59+D$4*Base!K60+Base!K62+Base!K63 -> 409499.25 | K28: =$A$7*Base!L58*(1-Base!$B$31)+Base!L59+D$4*Base!L60+Base!L62+Base!L63 -> 391859.66 | L28: =$A$7*Base!M58*(1-Base!$B$31)+Base!M59+D$4*Base!M60+Base!M62+Base!M63 -> 374389.38 | M28: =$A$7*Base!N58*(1-Base!$B$31)+Base!N59+D$4*Base!N60+Base!N62+Base!N63 -> 357079.59 | N28: =$A$7*Base!O58*(1-Base!$B$31)+Base!O59+D$4*Base!O60+Base!O62+Base!O63 -> 339921.64 | O28: =$A$7*Base!P58*(1-Base!$B$31)+Base!P59+D$4*Base!P60+Base!P62+Base!P63 -> 322907.05 | P28: =$A$7*Base!Q58*(1-Base!$B$31)+Base!Q59+D$4*Base!Q60+Base!Q62+Base!Q63 -> 306027.45 | Q28: =$A$7*Base!R58*(1-Base!$B$31)+Base!R59+D$4*Base!R60+Base!R62+Base!R63 -> 289274.63 | R28: =$A$7*Base!S58*(1-Base!$B$31)+Base!S59+D$4*Base!S60+Base!S62+Base!S63 -> 0 | S28: =$A$7*Base!T58*(1-Base!$B$31)+Base!T59+D$4*Base!T60+Base!T62+Base!T63 -> 0 | T28: =$A$7*Base!U58*(1-Base!$B$31)+Base!U59+D$4*Base!U60+Base!U62+Base!U63 -> 0 | U28: =$A$7*Base!V58*(1-Base!$B$31)+Base!V59+D$4*Base!V60+Base!V62+Base!V63 -> 0 | V28: =$A$7*Base!W58*(1-Base!$B$31)+Base!W59+D$4*Base!W60+Base!W62+Base!W63 -> 0
A29: ="Indtægt "&TEXT($A$7,"0%")&" / investering "&TEXT(E$4,"0%") -> Indtægt 100% / investering 100% | B29: =Base!C65*E$4 -> -6250000 | C29: =$A$7*Base!D58*(1-Base!$B$31)+Base!D59+E$4*Base!D60+Base!D62+Base!D63 -> 526633.09 | D29: =$A$7*Base!E58*(1-Base!$B$31)+Base!E59+E$4*Base!E60+Base!E62+Base!E63 -> 507309.58 | E29: =$A$7*Base!F58*(1-Base!$B$31)+Base!F59+E$4*Base!F60+Base!F62+Base!F63 -> 488217.38 | F29: =$A$7*Base!G58*(1-Base!$B$31)+Base!G59+E$4*Base!G60+Base!G62+Base!G63 -> 469346.26 | G29: =$A$7*Base!H58*(1-Base!$B$31)+Base!H59+E$4*Base!H60+Base!H62+Base!H63 -> 450686.2 | H29: =$A$7*Base!I58*(1-Base!$B$31)+Base!I59+E$4*Base!I60+Base!I62+Base!I63 -> 432227.39 | I29: =$A$7*Base!J58*(1-Base!$B$31)+Base!J59+E$4*Base!J60+Base!J62+Base!J63 -> 413960.2 | J29: =$A$7*Base!K58*(1-Base!$B$31)+Base!K59+E$4*Base!K60+Base!K62+Base!K63 -> 395875.19 | K29: =$A$7*Base!L58*(1-Base!$B$31)+Base!L59+E$4*Base!L60+Base!L62+Base!L63 -> 377963.13 | L29: =$A$7*Base!M58*(1-Base!$B$31)+Base!M59+E$4*Base!M60+Base!M62+Base!M63 -> 360214.91 | M29: =$A$7*Base!N58*(1-Base!$B$31)+Base!N59+E$4*Base!N60+Base!N62+Base!N63 -> 342621.63 | N29: =$A$7*Base!O58*(1-Base!$B$31)+Base!O59+E$4*Base!O60+Base!O62+Base!O63 -> 325174.53 | O29: =$A$7*Base!P58*(1-Base!$B$31)+Base!P59+E$4*Base!P60+Base!P62+Base!P63 -> 307864.99 | P29: =$A$7*Base!Q58*(1-Base!$B$31)+Base!Q59+E$4*Base!Q60+Base!Q62+Base!Q63 -> 290684.55 | Q29: =$A$7*Base!R58*(1-Base!$B$31)+Base!R59+E$4*Base!R60+Base!R62+Base!R63 -> 273624.88 | R29: =$A$7*Base!S58*(1-Base!$B$31)+Base!S59+E$4*Base!S60+Base!S62+Base!S63 -> 0 | S29: =$A$7*Base!T58*(1-Base!$B$31)+Base!T59+E$4*Base!T60+Base!T62+Base!T63 -> 0 | T29: =$A$7*Base!U58*(1-Base!$B$31)+Base!U59+E$4*Base!U60+Base!U62+Base!U63 -> 0 | U29: =$A$7*Base!V58*(1-Base!$B$31)+Base!V59+E$4*Base!V60+Base!V62+Base!V63 -> 0 | V29: =$A$7*Base!W58*(1-Base!$B$31)+Base!W59+E$4*Base!W60+Base!W62+Base!W63 -> 0
A30: ="Indtægt "&TEXT($A$7,"0%")&" / investering "&TEXT(F$4,"0%") -> Indtægt 100% / investering 110% | B30: =Base!C65*F$4 -> -6875000 | C30: =$A$7*Base!D58*(1-Base!$B$31)+Base!D59+F$4*Base!D60+Base!D62+Base!D63 -> 514772.53 | D30: =$A$7*Base!E58*(1-Base!$B$31)+Base!E59+F$4*Base!E60+Base!E62+Base!E63 -> 495211.81 | E30: =$A$7*Base!F58*(1-Base!$B$31)+Base!F59+F$4*Base!F60+Base!F62+Base!F63 -> 475877.65 | F30: =$A$7*Base!G58*(1-Base!$B$31)+Base!G59+F$4*Base!G60+Base!G62+Base!G63 -> 456759.74 | G30: =$A$7*Base!H58*(1-Base!$B$31)+Base!H59+F$4*Base!H60+Base!H62+Base!H63 -> 437847.95 | H30: =$A$7*Base!I58*(1-Base!$B$31)+Base!I59+F$4*Base!I60+Base!I62+Base!I63 -> 419132.37 | I30: =$A$7*Base!J58*(1-Base!$B$31)+Base!J59+F$4*Base!J60+Base!J62+Base!J63 -> 400603.28 | J30: =$A$7*Base!K58*(1-Base!$B$31)+Base!K59+F$4*Base!K60+Base!K62+Base!K63 -> 382251.14 | K30: =$A$7*Base!L58*(1-Base!$B$31)+Base!L59+F$4*Base!L60+Base!L62+Base!L63 -> 364066.59 | L30: =$A$7*Base!M58*(1-Base!$B$31)+Base!M59+F$4*Base!M60+Base!M62+Base!M63 -> 346040.45 | M30: =$A$7*Base!N58*(1-Base!$B$31)+Base!N59+F$4*Base!N60+Base!N62+Base!N63 -> 328163.68 | N30: =$A$7*Base!O58*(1-Base!$B$31)+Base!O59+F$4*Base!O60+Base!O62+Base!O63 -> 310427.41 | O30: =$A$7*Base!P58*(1-Base!$B$31)+Base!P59+F$4*Base!P60+Base!P62+Base!P63 -> 292822.93 | P30: =$A$7*Base!Q58*(1-Base!$B$31)+Base!Q59+F$4*Base!Q60+Base!Q62+Base!Q63 -> 275341.65 | Q30: =$A$7*Base!R58*(1-Base!$B$31)+Base!R59+F$4*Base!R60+Base!R62+Base!R63 -> 257975.12 | R30: =$A$7*Base!S58*(1-Base!$B$31)+Base!S59+F$4*Base!S60+Base!S62+Base!S63 -> 0 | S30: =$A$7*Base!T58*(1-Base!$B$31)+Base!T59+F$4*Base!T60+Base!T62+Base!T63 -> 0 | T30: =$A$7*Base!U58*(1-Base!$B$31)+Base!U59+F$4*Base!U60+Base!U62+Base!U63 -> 0 | U30: =$A$7*Base!V58*(1-Base!$B$31)+Base!V59+F$4*Base!V60+Base!V62+Base!V63 -> 0 | V30: =$A$7*Base!W58*(1-Base!$B$31)+Base!W59+F$4*Base!W60+Base!W62+Base!W63 -> 0
A31: ="Indtægt "&TEXT($A$7,"0%")&" / investering "&TEXT(G$4,"0%") -> Indtægt 100% / investering 120% | B31: =Base!C65*G$4 -> -7500000 | C31: =$A$7*Base!D58*(1-Base!$B$31)+Base!D59+G$4*Base!D60+Base!D62+Base!D63 -> 502911.97 | D31: =$A$7*Base!E58*(1-Base!$B$31)+Base!E59+G$4*Base!E60+Base!E62+Base!E63 -> 483114.04 | E31: =$A$7*Base!F58*(1-Base!$B$31)+Base!F59+G$4*Base!F60+Base!F62+Base!F63 -> 463537.93 | F31: =$A$7*Base!G58*(1-Base!$B$31)+Base!G59+G$4*Base!G60+Base!G62+Base!G63 -> 444173.22 | G31: =$A$7*Base!H58*(1-Base!$B$31)+Base!H59+G$4*Base!H60+Base!H62+Base!H63 -> 425009.7 | H31: =$A$7*Base!I58*(1-Base!$B$31)+Base!I59+G$4*Base!I60+Base!I62+Base!I63 -> 406037.35 | I31: =$A$7*Base!J58*(1-Base!$B$31)+Base!J59+G$4*Base!J60+Base!J62+Base!J63 -> 387246.36 | J31: =$A$7*Base!K58*(1-Base!$B$31)+Base!K59+G$4*Base!K60+Base!K62+Base!K63 -> 368627.08 | K31: =$A$7*Base!L58*(1-Base!$B$31)+Base!L59+G$4*Base!L60+Base!L62+Base!L63 -> 350170.05 | L31: =$A$7*Base!M58*(1-Base!$B$31)+Base!M59+G$4*Base!M60+Base!M62+Base!M63 -> 331865.98 | M31: =$A$7*Base!N58*(1-Base!$B$31)+Base!N59+G$4*Base!N60+Base!N62+Base!N63 -> 313705.72 | N31: =$A$7*Base!O58*(1-Base!$B$31)+Base!O59+G$4*Base!O60+Base!O62+Base!O63 -> 295680.3 | O31: =$A$7*Base!P58*(1-Base!$B$31)+Base!P59+G$4*Base!P60+Base!P62+Base!P63 -> 277780.87 | P31: =$A$7*Base!Q58*(1-Base!$B$31)+Base!Q59+G$4*Base!Q60+Base!Q62+Base!Q63 -> 259998.75 | Q31: =$A$7*Base!R58*(1-Base!$B$31)+Base!R59+G$4*Base!R60+Base!R62+Base!R63 -> 242325.36 | R31: =$A$7*Base!S58*(1-Base!$B$31)+Base!S59+G$4*Base!S60+Base!S62+Base!S63 -> 0 | S31: =$A$7*Base!T58*(1-Base!$B$31)+Base!T59+G$4*Base!T60+Base!T62+Base!T63 -> 0 | T31: =$A$7*Base!U58*(1-Base!$B$31)+Base!U59+G$4*Base!U60+Base!U62+Base!U63 -> 0 | U31: =$A$7*Base!V58*(1-Base!$B$31)+Base!V59+G$4*Base!V60+Base!V62+Base!V63 -> 0 | V31: =$A$7*Base!W58*(1-Base!$B$31)+Base!W59+G$4*Base!W60+Base!W62+Base!W63 -> 0
A32: ="Indtægt "&TEXT($A$8,"0%")&" / investering "&TEXT(B$4,"0%") -> Indtægt 115% / investering 60% | B32: =Base!C65*B$4 -> -3750000 | C32: =$A$8*Base!D58*(1-Base!$B$31)+Base!D59+B$4*Base!D60+Base!D62+Base!D63 -> 712822.04 | D32: =$A$8*Base!E58*(1-Base!$B$31)+Base!E59+B$4*Base!E60+Base!E62+Base!E63 -> 692206.25 | E32: =$A$8*Base!F58*(1-Base!$B$31)+Base!F59+B$4*Base!F60+Base!F62+Base!F63 -> 671888.8 | F32: =$A$8*Base!G58*(1-Base!$B$31)+Base!G59+B$4*Base!G60+Base!G62+Base!G63 -> 651858.58 | G32: =$A$8*Base!H58*(1-Base!$B$31)+Base!H59+B$4*Base!H60+Base!H62+Base!H63 -> 632104.72 | H32: =$A$8*Base!I58*(1-Base!$B$31)+Base!I59+B$4*Base!I60+Base!I62+Base!I63 -> 612616.62 | I32: =$A$8*Base!J58*(1-Base!$B$31)+Base!J59+B$4*Base!J60+Base!J62+Base!J63 -> 593383.88 | J32: =$A$8*Base!K58*(1-Base!$B$31)+Base!K59+B$4*Base!K60+Base!K62+Base!K63 -> 574396.37 | K32: =$A$8*Base!L58*(1-Base!$B$31)+Base!L59+B$4*Base!L60+Base!L62+Base!L63 -> 555644.16 | L32: =$A$8*Base!M58*(1-Base!$B$31)+Base!M59+B$4*Base!M60+Base!M62+Base!M63 -> 537117.52 | M32: =$A$8*Base!N58*(1-Base!$B$31)+Base!N59+B$4*Base!N60+Base!N62+Base!N63 -> 518806.95 | N32: =$A$8*Base!O58*(1-Base!$B$31)+Base!O59+B$4*Base!O60+Base!O62+Base!O63 -> 500703.13 | O32: =$A$8*Base!P58*(1-Base!$B$31)+Base!P59+B$4*Base!P60+Base!P62+Base!P63 -> 482796.92 | P32: =$A$8*Base!Q58*(1-Base!$B$31)+Base!Q59+B$4*Base!Q60+Base!Q62+Base!Q63 -> 465079.39 | Q32: =$A$8*Base!R58*(1-Base!$B$31)+Base!R59+B$4*Base!R60+Base!R62+Base!R63 -> 447541.77 | R32: =$A$8*Base!S58*(1-Base!$B$31)+Base!S59+B$4*Base!S60+Base!S62+Base!S63 -> 0 | S32: =$A$8*Base!T58*(1-Base!$B$31)+Base!T59+B$4*Base!T60+Base!T62+Base!T63 -> 0 | T32: =$A$8*Base!U58*(1-Base!$B$31)+Base!U59+B$4*Base!U60+Base!U62+Base!U63 -> 0 | U32: =$A$8*Base!V58*(1-Base!$B$31)+Base!V59+B$4*Base!V60+Base!V62+Base!V63 -> 0 | V32: =$A$8*Base!W58*(1-Base!$B$31)+Base!W59+B$4*Base!W60+Base!W62+Base!W63 -> 0
A33: ="Indtægt "&TEXT($A$8,"0%")&" / investering "&TEXT(C$4,"0%") -> Indtægt 115% / investering 80% | B33: =Base!C65*C$4 -> -5000000 | C33: =$A$8*Base!D58*(1-Base!$B$31)+Base!D59+C$4*Base!D60+Base!D62+Base!D63 -> 689100.92 | D33: =$A$8*Base!E58*(1-Base!$B$31)+Base!E59+C$4*Base!E60+Base!E62+Base!E63 -> 668010.71 | E33: =$A$8*Base!F58*(1-Base!$B$31)+Base!F59+C$4*Base!F60+Base!F62+Base!F63 -> 647209.35 | F33: =$A$8*Base!G58*(1-Base!$B$31)+Base!G59+C$4*Base!G60+Base!G62+Base!G63 -> 626685.54 | G33: =$A$8*Base!H58*(1-Base!$B$31)+Base!H59+C$4*Base!H60+Base!H62+Base!H63 -> 606428.22 | H33: =$A$8*Base!I58*(1-Base!$B$31)+Base!I59+C$4*Base!I60+Base!I62+Base!I63 -> 586426.58 | I33: =$A$8*Base!J58*(1-Base!$B$31)+Base!J59+C$4*Base!J60+Base!J62+Base!J63 -> 566670.05 | J33: =$A$8*Base!K58*(1-Base!$B$31)+Base!K59+C$4*Base!K60+Base!K62+Base!K63 -> 547148.26 | K33: =$A$8*Base!L58*(1-Base!$B$31)+Base!L59+C$4*Base!L60+Base!L62+Base!L63 -> 527851.09 | L33: =$A$8*Base!M58*(1-Base!$B$31)+Base!M59+C$4*Base!M60+Base!M62+Base!M63 -> 508768.59 | M33: =$A$8*Base!N58*(1-Base!$B$31)+Base!N59+C$4*Base!N60+Base!N62+Base!N63 -> 489891.04 | N33: =$A$8*Base!O58*(1-Base!$B$31)+Base!O59+C$4*Base!O60+Base!O62+Base!O63 -> 471208.89 | O33: =$A$8*Base!P58*(1-Base!$B$31)+Base!P59+C$4*Base!P60+Base!P62+Base!P63 -> 452712.81 | P33: =$A$8*Base!Q58*(1-Base!$B$31)+Base!Q59+C$4*Base!Q60+Base!Q62+Base!Q63 -> 434393.6 | Q33: =$A$8*Base!R58*(1-Base!$B$31)+Base!R59+C$4*Base!R60+Base!R62+Base!R63 -> 416242.25 | R33: =$A$8*Base!S58*(1-Base!$B$31)+Base!S59+C$4*Base!S60+Base!S62+Base!S63 -> 0 | S33: =$A$8*Base!T58*(1-Base!$B$31)+Base!T59+C$4*Base!T60+Base!T62+Base!T63 -> 0 | T33: =$A$8*Base!U58*(1-Base!$B$31)+Base!U59+C$4*Base!U60+Base!U62+Base!U63 -> 0 | U33: =$A$8*Base!V58*(1-Base!$B$31)+Base!V59+C$4*Base!V60+Base!V62+Base!V63 -> 0 | V33: =$A$8*Base!W58*(1-Base!$B$31)+Base!W59+C$4*Base!W60+Base!W62+Base!W63 -> 0
A34: ="Indtægt "&TEXT($A$8,"0%")&" / investering "&TEXT(D$4,"0%") -> Indtægt 115% / investering 90% | B34: =Base!C65*D$4 -> -5625000 | C34: =$A$8*Base!D58*(1-Base!$B$31)+Base!D59+D$4*Base!D60+Base!D62+Base!D63 -> 677240.36 | D34: =$A$8*Base!E58*(1-Base!$B$31)+Base!E59+D$4*Base!E60+Base!E62+Base!E63 -> 655912.94 | E34: =$A$8*Base!F58*(1-Base!$B$31)+Base!F59+D$4*Base!F60+Base!F62+Base!F63 -> 634869.62 | F34: =$A$8*Base!G58*(1-Base!$B$31)+Base!G59+D$4*Base!G60+Base!G62+Base!G63 -> 614099.01 | G34: =$A$8*Base!H58*(1-Base!$B$31)+Base!H59+D$4*Base!H60+Base!H62+Base!H63 -> 593589.97 | H34: =$A$8*Base!I58*(1-Base!$B$31)+Base!I59+D$4*Base!I60+Base!I62+Base!I63 -> 573331.57 | I34: =$A$8*Base!J58*(1-Base!$B$31)+Base!J59+D$4*Base!J60+Base!J62+Base!J63 -> 553313.13 | J34: =$A$8*Base!K58*(1-Base!$B$31)+Base!K59+D$4*Base!K60+Base!K62+Base!K63 -> 533524.21 | K34: =$A$8*Base!L58*(1-Base!$B$31)+Base!L59+D$4*Base!L60+Base!L62+Base!L63 -> 513954.55 | L34: =$A$8*Base!M58*(1-Base!$B$31)+Base!M59+D$4*Base!M60+Base!M62+Base!M63 -> 494594.12 | M34: =$A$8*Base!N58*(1-Base!$B$31)+Base!N59+D$4*Base!N60+Base!N62+Base!N63 -> 475433.08 | N34: =$A$8*Base!O58*(1-Base!$B$31)+Base!O59+D$4*Base!O60+Base!O62+Base!O63 -> 456461.78 | O34: =$A$8*Base!P58*(1-Base!$B$31)+Base!P59+D$4*Base!P60+Base!P62+Base!P63 -> 437670.75 | P34: =$A$8*Base!Q58*(1-Base!$B$31)+Base!Q59+D$4*Base!Q60+Base!Q62+Base!Q63 -> 419050.7 | Q34: =$A$8*Base!R58*(1-Base!$B$31)+Base!R59+D$4*Base!R60+Base!R62+Base!R63 -> 400592.5 | R34: =$A$8*Base!S58*(1-Base!$B$31)+Base!S59+D$4*Base!S60+Base!S62+Base!S63 -> 0 | S34: =$A$8*Base!T58*(1-Base!$B$31)+Base!T59+D$4*Base!T60+Base!T62+Base!T63 -> 0 | T34: =$A$8*Base!U58*(1-Base!$B$31)+Base!U59+D$4*Base!U60+Base!U62+Base!U63 -> 0 | U34: =$A$8*Base!V58*(1-Base!$B$31)+Base!V59+D$4*Base!V60+Base!V62+Base!V63 -> 0 | V34: =$A$8*Base!W58*(1-Base!$B$31)+Base!W59+D$4*Base!W60+Base!W62+Base!W63 -> 0
A35: ="Indtægt "&TEXT($A$8,"0%")&" / investering "&TEXT(E$4,"0%") -> Indtægt 115% / investering 100% | B35: =Base!C65*E$4 -> -6250000 | C35: =$A$8*Base!D58*(1-Base!$B$31)+Base!D59+E$4*Base!D60+Base!D62+Base!D63 -> 665379.8 | D35: =$A$8*Base!E58*(1-Base!$B$31)+Base!E59+E$4*Base!E60+Base!E62+Base!E63 -> 643815.16 | E35: =$A$8*Base!F58*(1-Base!$B$31)+Base!F59+E$4*Base!F60+Base!F62+Base!F63 -> 622529.89 | F35: =$A$8*Base!G58*(1-Base!$B$31)+Base!G59+E$4*Base!G60+Base!G62+Base!G63 -> 601512.49 | G35: =$A$8*Base!H58*(1-Base!$B$31)+Base!H59+E$4*Base!H60+Base!H62+Base!H63 -> 580751.71 | H35: =$A$8*Base!I58*(1-Base!$B$31)+Base!I59+E$4*Base!I60+Base!I62+Base!I63 -> 560236.55 | I35: =$A$8*Base!J58*(1-Base!$B$31)+Base!J59+E$4*Base!J60+Base!J62+Base!J63 -> 539956.21 | J35: =$A$8*Base!K58*(1-Base!$B$31)+Base!K59+E$4*Base!K60+Base!K62+Base!K63 -> 519900.15 | K35: =$A$8*Base!L58*(1-Base!$B$31)+Base!L59+E$4*Base!L60+Base!L62+Base!L63 -> 500058.01 | L35: =$A$8*Base!M58*(1-Base!$B$31)+Base!M59+E$4*Base!M60+Base!M62+Base!M63 -> 480419.65 | M35: =$A$8*Base!N58*(1-Base!$B$31)+Base!N59+E$4*Base!N60+Base!N62+Base!N63 -> 460975.12 | N35: =$A$8*Base!O58*(1-Base!$B$31)+Base!O59+E$4*Base!O60+Base!O62+Base!O63 -> 441714.66 | O35: =$A$8*Base!P58*(1-Base!$B$31)+Base!P59+E$4*Base!P60+Base!P62+Base!P63 -> 422628.69 | P35: =$A$8*Base!Q58*(1-Base!$B$31)+Base!Q59+E$4*Base!Q60+Base!Q62+Base!Q63 -> 403707.8 | Q35: =$A$8*Base!R58*(1-Base!$B$31)+Base!R59+E$4*Base!R60+Base!R62+Base!R63 -> 384942.74 | R35: =$A$8*Base!S58*(1-Base!$B$31)+Base!S59+E$4*Base!S60+Base!S62+Base!S63 -> 0 | S35: =$A$8*Base!T58*(1-Base!$B$31)+Base!T59+E$4*Base!T60+Base!T62+Base!T63 -> 0 | T35: =$A$8*Base!U58*(1-Base!$B$31)+Base!U59+E$4*Base!U60+Base!U62+Base!U63 -> 0 | U35: =$A$8*Base!V58*(1-Base!$B$31)+Base!V59+E$4*Base!V60+Base!V62+Base!V63 -> 0 | V35: =$A$8*Base!W58*(1-Base!$B$31)+Base!W59+E$4*Base!W60+Base!W62+Base!W63 -> 0
A36: ="Indtægt "&TEXT($A$8,"0%")&" / investering "&TEXT(F$4,"0%") -> Indtægt 115% / investering 110% | B36: =Base!C65*F$4 -> -6875000 | C36: =$A$8*Base!D58*(1-Base!$B$31)+Base!D59+F$4*Base!D60+Base!D62+Base!D63 -> 653519.24 | D36: =$A$8*Base!E58*(1-Base!$B$31)+Base!E59+F$4*Base!E60+Base!E62+Base!E63 -> 631717.39 | E36: =$A$8*Base!F58*(1-Base!$B$31)+Base!F59+F$4*Base!F60+Base!F62+Base!F63 -> 610190.17 | F36: =$A$8*Base!G58*(1-Base!$B$31)+Base!G59+F$4*Base!G60+Base!G62+Base!G63 -> 588925.97 | G36: =$A$8*Base!H58*(1-Base!$B$31)+Base!H59+F$4*Base!H60+Base!H62+Base!H63 -> 567913.46 | H36: =$A$8*Base!I58*(1-Base!$B$31)+Base!I59+F$4*Base!I60+Base!I62+Base!I63 -> 547141.53 | I36: =$A$8*Base!J58*(1-Base!$B$31)+Base!J59+F$4*Base!J60+Base!J62+Base!J63 -> 526599.3 | J36: =$A$8*Base!K58*(1-Base!$B$31)+Base!K59+F$4*Base!K60+Base!K62+Base!K63 -> 506276.1 | K36: =$A$8*Base!L58*(1-Base!$B$31)+Base!L59+F$4*Base!L60+Base!L62+Base!L63 -> 486161.48 | L36: =$A$8*Base!M58*(1-Base!$B$31)+Base!M59+F$4*Base!M60+Base!M62+Base!M63 -> 466245.19 | M36: =$A$8*Base!N58*(1-Base!$B$31)+Base!N59+F$4*Base!N60+Base!N62+Base!N63 -> 446517.17 | N36: =$A$8*Base!O58*(1-Base!$B$31)+Base!O59+F$4*Base!O60+Base!O62+Base!O63 -> 426967.55 | O36: =$A$8*Base!P58*(1-Base!$B$31)+Base!P59+F$4*Base!P60+Base!P62+Base!P63 -> 407586.63 | P36: =$A$8*Base!Q58*(1-Base!$B$31)+Base!Q59+F$4*Base!Q60+Base!Q62+Base!Q63 -> 388364.9 | Q36: =$A$8*Base!R58*(1-Base!$B$31)+Base!R59+F$4*Base!R60+Base!R62+Base!R63 -> 369292.98 | R36: =$A$8*Base!S58*(1-Base!$B$31)+Base!S59+F$4*Base!S60+Base!S62+Base!S63 -> 0 | S36: =$A$8*Base!T58*(1-Base!$B$31)+Base!T59+F$4*Base!T60+Base!T62+Base!T63 -> 0 | T36: =$A$8*Base!U58*(1-Base!$B$31)+Base!U59+F$4*Base!U60+Base!U62+Base!U63 -> 0 | U36: =$A$8*Base!V58*(1-Base!$B$31)+Base!V59+F$4*Base!V60+Base!V62+Base!V63 -> 0 | V36: =$A$8*Base!W58*(1-Base!$B$31)+Base!W59+F$4*Base!W60+Base!W62+Base!W63 -> 0
A37: ="Indtægt "&TEXT($A$8,"0%")&" / investering "&TEXT(G$4,"0%") -> Indtægt 115% / investering 120% | B37: =Base!C65*G$4 -> -7500000 | C37: =$A$8*Base!D58*(1-Base!$B$31)+Base!D59+G$4*Base!D60+Base!D62+Base!D63 -> 641658.68 | D37: =$A$8*Base!E58*(1-Base!$B$31)+Base!E59+G$4*Base!E60+Base!E62+Base!E63 -> 619619.62 | E37: =$A$8*Base!F58*(1-Base!$B$31)+Base!F59+G$4*Base!F60+Base!F62+Base!F63 -> 597850.44 | F37: =$A$8*Base!G58*(1-Base!$B$31)+Base!G59+G$4*Base!G60+Base!G62+Base!G63 -> 576339.45 | G37: =$A$8*Base!H58*(1-Base!$B$31)+Base!H59+G$4*Base!H60+Base!H62+Base!H63 -> 555075.21 | H37: =$A$8*Base!I58*(1-Base!$B$31)+Base!I59+G$4*Base!I60+Base!I62+Base!I63 -> 534046.52 | I37: =$A$8*Base!J58*(1-Base!$B$31)+Base!J59+G$4*Base!J60+Base!J62+Base!J63 -> 513242.38 | J37: =$A$8*Base!K58*(1-Base!$B$31)+Base!K59+G$4*Base!K60+Base!K62+Base!K63 -> 492652.04 | K37: =$A$8*Base!L58*(1-Base!$B$31)+Base!L59+G$4*Base!L60+Base!L62+Base!L63 -> 472264.94 | L37: =$A$8*Base!M58*(1-Base!$B$31)+Base!M59+G$4*Base!M60+Base!M62+Base!M63 -> 452070.72 | M37: =$A$8*Base!N58*(1-Base!$B$31)+Base!N59+G$4*Base!N60+Base!N62+Base!N63 -> 432059.21 | N37: =$A$8*Base!O58*(1-Base!$B$31)+Base!O59+G$4*Base!O60+Base!O62+Base!O63 -> 412220.43 | O37: =$A$8*Base!P58*(1-Base!$B$31)+Base!P59+G$4*Base!P60+Base!P62+Base!P63 -> 392544.58 | P37: =$A$8*Base!Q58*(1-Base!$B$31)+Base!Q59+G$4*Base!Q60+Base!Q62+Base!Q63 -> 373022 | Q37: =$A$8*Base!R58*(1-Base!$B$31)+Base!R59+G$4*Base!R60+Base!R62+Base!R63 -> 353643.22 | R37: =$A$8*Base!S58*(1-Base!$B$31)+Base!S59+G$4*Base!S60+Base!S62+Base!S63 -> 0 | S37: =$A$8*Base!T58*(1-Base!$B$31)+Base!T59+G$4*Base!T60+Base!T62+Base!T63 -> 0 | T37: =$A$8*Base!U58*(1-Base!$B$31)+Base!U59+G$4*Base!U60+Base!U62+Base!U63 -> 0 | U37: =$A$8*Base!V58*(1-Base!$B$31)+Base!V59+G$4*Base!V60+Base!V62+Base!V63 -> 0 | V37: =$A$8*Base!W58*(1-Base!$B$31)+Base!W59+G$4*Base!W60+Base!W62+Base!W63 -> 0
A38: ="Indtægt "&TEXT($A$9,"0%")&" / investering "&TEXT(B$4,"0%") -> Indtægt 130% / investering 60% | B38: =Base!C65*B$4 -> -3750000 | C38: =$A$9*Base!D58*(1-Base!$B$31)+Base!D59+B$4*Base!D60+Base!D62+Base!D63 -> 851568.76 | D38: =$A$9*Base!E58*(1-Base!$B$31)+Base!E59+B$4*Base!E60+Base!E62+Base!E63 -> 828711.83 | E38: =$A$9*Base!F58*(1-Base!$B$31)+Base!F59+B$4*Base!F60+Base!F62+Base!F63 -> 806201.31 | F38: =$A$9*Base!G58*(1-Base!$B$31)+Base!G59+B$4*Base!G60+Base!G62+Base!G63 -> 784024.81 | G38: =$A$9*Base!H58*(1-Base!$B$31)+Base!H59+B$4*Base!H60+Base!H62+Base!H63 -> 762170.23 | H38: =$A$9*Base!I58*(1-Base!$B$31)+Base!I59+B$4*Base!I60+Base!I62+Base!I63 -> 740625.78 | I38: =$A$9*Base!J58*(1-Base!$B$31)+Base!J59+B$4*Base!J60+Base!J62+Base!J63 -> 719379.9 | J38: =$A$9*Base!K58*(1-Base!$B$31)+Base!K59+B$4*Base!K60+Base!K62+Base!K63 -> 698421.33 | K38: =$A$9*Base!L58*(1-Base!$B$31)+Base!L59+B$4*Base!L60+Base!L62+Base!L63 -> 677739.04 | L38: =$A$9*Base!M58*(1-Base!$B$31)+Base!M59+B$4*Base!M60+Base!M62+Base!M63 -> 657322.26 | M38: =$A$9*Base!N58*(1-Base!$B$31)+Base!N59+B$4*Base!N60+Base!N62+Base!N63 -> 637160.44 | N38: =$A$9*Base!O58*(1-Base!$B$31)+Base!O59+B$4*Base!O60+Base!O62+Base!O63 -> 617243.26 | O38: =$A$9*Base!P58*(1-Base!$B$31)+Base!P59+B$4*Base!P60+Base!P62+Base!P63 -> 597560.63 | P38: =$A$9*Base!Q58*(1-Base!$B$31)+Base!Q59+B$4*Base!Q60+Base!Q62+Base!Q63 -> 578102.64 | Q38: =$A$9*Base!R58*(1-Base!$B$31)+Base!R59+B$4*Base!R60+Base!R62+Base!R63 -> 558859.63 | R38: =$A$9*Base!S58*(1-Base!$B$31)+Base!S59+B$4*Base!S60+Base!S62+Base!S63 -> 0 | S38: =$A$9*Base!T58*(1-Base!$B$31)+Base!T59+B$4*Base!T60+Base!T62+Base!T63 -> 0 | T38: =$A$9*Base!U58*(1-Base!$B$31)+Base!U59+B$4*Base!U60+Base!U62+Base!U63 -> 0 | U38: =$A$9*Base!V58*(1-Base!$B$31)+Base!V59+B$4*Base!V60+Base!V62+Base!V63 -> 0 | V38: =$A$9*Base!W58*(1-Base!$B$31)+Base!W59+B$4*Base!W60+Base!W62+Base!W63 -> 0
A39: ="Indtægt "&TEXT($A$9,"0%")&" / investering "&TEXT(C$4,"0%") -> Indtægt 130% / investering 80% | B39: =Base!C65*C$4 -> -5000000 | C39: =$A$9*Base!D58*(1-Base!$B$31)+Base!D59+C$4*Base!D60+Base!D62+Base!D63 -> 827847.64 | D39: =$A$9*Base!E58*(1-Base!$B$31)+Base!E59+C$4*Base!E60+Base!E62+Base!E63 -> 804516.29 | E39: =$A$9*Base!F58*(1-Base!$B$31)+Base!F59+C$4*Base!F60+Base!F62+Base!F63 -> 781521.86 | F39: =$A$9*Base!G58*(1-Base!$B$31)+Base!G59+C$4*Base!G60+Base!G62+Base!G63 -> 758851.77 | G39: =$A$9*Base!H58*(1-Base!$B$31)+Base!H59+C$4*Base!H60+Base!H62+Base!H63 -> 736493.73 | H39: =$A$9*Base!I58*(1-Base!$B$31)+Base!I59+C$4*Base!I60+Base!I62+Base!I63 -> 714435.74 | I39: =$A$9*Base!J58*(1-Base!$B$31)+Base!J59+C$4*Base!J60+Base!J62+Base!J63 -> 692666.07 | J39: =$A$9*Base!K58*(1-Base!$B$31)+Base!K59+C$4*Base!K60+Base!K62+Base!K63 -> 671173.22 | K39: =$A$9*Base!L58*(1-Base!$B$31)+Base!L59+C$4*Base!L60+Base!L62+Base!L63 -> 649945.97 | L39: =$A$9*Base!M58*(1-Base!$B$31)+Base!M59+C$4*Base!M60+Base!M62+Base!M63 -> 628973.33 | M39: =$A$9*Base!N58*(1-Base!$B$31)+Base!N59+C$4*Base!N60+Base!N62+Base!N63 -> 608244.53 | N39: =$A$9*Base!O58*(1-Base!$B$31)+Base!O59+C$4*Base!O60+Base!O62+Base!O63 -> 587749.03 | O39: =$A$9*Base!P58*(1-Base!$B$31)+Base!P59+C$4*Base!P60+Base!P62+Base!P63 -> 567476.51 | P39: =$A$9*Base!Q58*(1-Base!$B$31)+Base!Q59+C$4*Base!Q60+Base!Q62+Base!Q63 -> 547416.85 | Q39: =$A$9*Base!R58*(1-Base!$B$31)+Base!R59+C$4*Base!R60+Base!R62+Base!R63 -> 527560.11 | R39: =$A$9*Base!S58*(1-Base!$B$31)+Base!S59+C$4*Base!S60+Base!S62+Base!S63 -> 0 | S39: =$A$9*Base!T58*(1-Base!$B$31)+Base!T59+C$4*Base!T60+Base!T62+Base!T63 -> 0 | T39: =$A$9*Base!U58*(1-Base!$B$31)+Base!U59+C$4*Base!U60+Base!U62+Base!U63 -> 0 | U39: =$A$9*Base!V58*(1-Base!$B$31)+Base!V59+C$4*Base!V60+Base!V62+Base!V63 -> 0 | V39: =$A$9*Base!W58*(1-Base!$B$31)+Base!W59+C$4*Base!W60+Base!W62+Base!W63 -> 0
A40: ="Indtægt "&TEXT($A$9,"0%")&" / investering "&TEXT(D$4,"0%") -> Indtægt 130% / investering 90% | B40: =Base!C65*D$4 -> -5625000 | C40: =$A$9*Base!D58*(1-Base!$B$31)+Base!D59+D$4*Base!D60+Base!D62+Base!D63 -> 815987.08 | D40: =$A$9*Base!E58*(1-Base!$B$31)+Base!E59+D$4*Base!E60+Base!E62+Base!E63 -> 792418.52 | E40: =$A$9*Base!F58*(1-Base!$B$31)+Base!F59+D$4*Base!F60+Base!F62+Base!F63 -> 769182.13 | F40: =$A$9*Base!G58*(1-Base!$B$31)+Base!G59+D$4*Base!G60+Base!G62+Base!G63 -> 746265.25 | G40: =$A$9*Base!H58*(1-Base!$B$31)+Base!H59+D$4*Base!H60+Base!H62+Base!H63 -> 723655.48 | H40: =$A$9*Base!I58*(1-Base!$B$31)+Base!I59+D$4*Base!I60+Base!I62+Base!I63 -> 701340.73 | I40: =$A$9*Base!J58*(1-Base!$B$31)+Base!J59+D$4*Base!J60+Base!J62+Base!J63 -> 679309.15 | J40: =$A$9*Base!K58*(1-Base!$B$31)+Base!K59+D$4*Base!K60+Base!K62+Base!K63 -> 657549.16 | K40: =$A$9*Base!L58*(1-Base!$B$31)+Base!L59+D$4*Base!L60+Base!L62+Base!L63 -> 636049.43 | L40: =$A$9*Base!M58*(1-Base!$B$31)+Base!M59+D$4*Base!M60+Base!M62+Base!M63 -> 614798.86 | M40: =$A$9*Base!N58*(1-Base!$B$31)+Base!N59+D$4*Base!N60+Base!N62+Base!N63 -> 593786.57 | N40: =$A$9*Base!O58*(1-Base!$B$31)+Base!O59+D$4*Base!O60+Base!O62+Base!O63 -> 573001.91 | O40: =$A$9*Base!P58*(1-Base!$B$31)+Base!P59+D$4*Base!P60+Base!P62+Base!P63 -> 552434.45 | P40: =$A$9*Base!Q58*(1-Base!$B$31)+Base!Q59+D$4*Base!Q60+Base!Q62+Base!Q63 -> 532073.95 | Q40: =$A$9*Base!R58*(1-Base!$B$31)+Base!R59+D$4*Base!R60+Base!R62+Base!R63 -> 511910.36 | R40: =$A$9*Base!S58*(1-Base!$B$31)+Base!S59+D$4*Base!S60+Base!S62+Base!S63 -> 0 | S40: =$A$9*Base!T58*(1-Base!$B$31)+Base!T59+D$4*Base!T60+Base!T62+Base!T63 -> 0 | T40: =$A$9*Base!U58*(1-Base!$B$31)+Base!U59+D$4*Base!U60+Base!U62+Base!U63 -> 0 | U40: =$A$9*Base!V58*(1-Base!$B$31)+Base!V59+D$4*Base!V60+Base!V62+Base!V63 -> 0 | V40: =$A$9*Base!W58*(1-Base!$B$31)+Base!W59+D$4*Base!W60+Base!W62+Base!W63 -> 0
A41: ="Indtægt "&TEXT($A$9,"0%")&" / investering "&TEXT(E$4,"0%") -> Indtægt 130% / investering 100% | B41: =Base!C65*E$4 -> -6250000 | C41: =$A$9*Base!D58*(1-Base!$B$31)+Base!D59+E$4*Base!D60+Base!D62+Base!D63 -> 804126.52 | D41: =$A$9*Base!E58*(1-Base!$B$31)+Base!E59+E$4*Base!E60+Base!E62+Base!E63 -> 780320.75 | E41: =$A$9*Base!F58*(1-Base!$B$31)+Base!F59+E$4*Base!F60+Base!F62+Base!F63 -> 756842.41 | F41: =$A$9*Base!G58*(1-Base!$B$31)+Base!G59+E$4*Base!G60+Base!G62+Base!G63 -> 733678.72 | G41: =$A$9*Base!H58*(1-Base!$B$31)+Base!H59+E$4*Base!H60+Base!H62+Base!H63 -> 710817.23 | H41: =$A$9*Base!I58*(1-Base!$B$31)+Base!I59+E$4*Base!I60+Base!I62+Base!I63 -> 688245.71 | I41: =$A$9*Base!J58*(1-Base!$B$31)+Base!J59+E$4*Base!J60+Base!J62+Base!J63 -> 665952.23 | J41: =$A$9*Base!K58*(1-Base!$B$31)+Base!K59+E$4*Base!K60+Base!K62+Base!K63 -> 643925.11 | K41: =$A$9*Base!L58*(1-Base!$B$31)+Base!L59+E$4*Base!L60+Base!L62+Base!L63 -> 622152.9 | L41: =$A$9*Base!M58*(1-Base!$B$31)+Base!M59+E$4*Base!M60+Base!M62+Base!M63 -> 600624.39 | M41: =$A$9*Base!N58*(1-Base!$B$31)+Base!N59+E$4*Base!N60+Base!N62+Base!N63 -> 579328.61 | N41: =$A$9*Base!O58*(1-Base!$B$31)+Base!O59+E$4*Base!O60+Base!O62+Base!O63 -> 558254.8 | O41: =$A$9*Base!P58*(1-Base!$B$31)+Base!P59+E$4*Base!P60+Base!P62+Base!P63 -> 537392.39 | P41: =$A$9*Base!Q58*(1-Base!$B$31)+Base!Q59+E$4*Base!Q60+Base!Q62+Base!Q63 -> 516731.05 | Q41: =$A$9*Base!R58*(1-Base!$B$31)+Base!R59+E$4*Base!R60+Base!R62+Base!R63 -> 496260.6 | R41: =$A$9*Base!S58*(1-Base!$B$31)+Base!S59+E$4*Base!S60+Base!S62+Base!S63 -> 0 | S41: =$A$9*Base!T58*(1-Base!$B$31)+Base!T59+E$4*Base!T60+Base!T62+Base!T63 -> 0 | T41: =$A$9*Base!U58*(1-Base!$B$31)+Base!U59+E$4*Base!U60+Base!U62+Base!U63 -> 0 | U41: =$A$9*Base!V58*(1-Base!$B$31)+Base!V59+E$4*Base!V60+Base!V62+Base!V63 -> 0 | V41: =$A$9*Base!W58*(1-Base!$B$31)+Base!W59+E$4*Base!W60+Base!W62+Base!W63 -> 0
A42: ="Indtægt "&TEXT($A$9,"0%")&" / investering "&TEXT(F$4,"0%") -> Indtægt 130% / investering 110% | B42: =Base!C65*F$4 -> -6875000 | C42: =$A$9*Base!D58*(1-Base!$B$31)+Base!D59+F$4*Base!D60+Base!D62+Base!D63 -> 792265.96 | D42: =$A$9*Base!E58*(1-Base!$B$31)+Base!E59+F$4*Base!E60+Base!E62+Base!E63 -> 768222.98 | E42: =$A$9*Base!F58*(1-Base!$B$31)+Base!F59+F$4*Base!F60+Base!F62+Base!F63 -> 744502.68 | F42: =$A$9*Base!G58*(1-Base!$B$31)+Base!G59+F$4*Base!G60+Base!G62+Base!G63 -> 721092.2 | G42: =$A$9*Base!H58*(1-Base!$B$31)+Base!H59+F$4*Base!H60+Base!H62+Base!H63 -> 697978.98 | H42: =$A$9*Base!I58*(1-Base!$B$31)+Base!I59+F$4*Base!I60+Base!I62+Base!I63 -> 675150.69 | I42: =$A$9*Base!J58*(1-Base!$B$31)+Base!J59+F$4*Base!J60+Base!J62+Base!J63 -> 652595.32 | J42: =$A$9*Base!K58*(1-Base!$B$31)+Base!K59+F$4*Base!K60+Base!K62+Base!K63 -> 630301.05 | K42: =$A$9*Base!L58*(1-Base!$B$31)+Base!L59+F$4*Base!L60+Base!L62+Base!L63 -> 608256.36 | L42: =$A$9*Base!M58*(1-Base!$B$31)+Base!M59+F$4*Base!M60+Base!M62+Base!M63 -> 586449.92 | M42: =$A$9*Base!N58*(1-Base!$B$31)+Base!N59+F$4*Base!N60+Base!N62+Base!N63 -> 564870.66 | N42: =$A$9*Base!O58*(1-Base!$B$31)+Base!O59+F$4*Base!O60+Base!O62+Base!O63 -> 543507.68 | O42: =$A$9*Base!P58*(1-Base!$B$31)+Base!P59+F$4*Base!P60+Base!P62+Base!P63 -> 522350.34 | P42: =$A$9*Base!Q58*(1-Base!$B$31)+Base!Q59+F$4*Base!Q60+Base!Q62+Base!Q63 -> 501388.15 | Q42: =$A$9*Base!R58*(1-Base!$B$31)+Base!R59+F$4*Base!R60+Base!R62+Base!R63 -> 480610.84 | R42: =$A$9*Base!S58*(1-Base!$B$31)+Base!S59+F$4*Base!S60+Base!S62+Base!S63 -> 0 | S42: =$A$9*Base!T58*(1-Base!$B$31)+Base!T59+F$4*Base!T60+Base!T62+Base!T63 -> 0 | T42: =$A$9*Base!U58*(1-Base!$B$31)+Base!U59+F$4*Base!U60+Base!U62+Base!U63 -> 0 | U42: =$A$9*Base!V58*(1-Base!$B$31)+Base!V59+F$4*Base!V60+Base!V62+Base!V63 -> 0 | V42: =$A$9*Base!W58*(1-Base!$B$31)+Base!W59+F$4*Base!W60+Base!W62+Base!W63 -> 0
A43: ="Indtægt "&TEXT($A$9,"0%")&" / investering "&TEXT(G$4,"0%") -> Indtægt 130% / investering 120% | B43: =Base!C65*G$4 -> -7500000 | C43: =$A$9*Base!D58*(1-Base!$B$31)+Base!D59+G$4*Base!D60+Base!D62+Base!D63 -> 780405.4 | D43: =$A$9*Base!E58*(1-Base!$B$31)+Base!E59+G$4*Base!E60+Base!E62+Base!E63 -> 756125.21 | E43: =$A$9*Base!F58*(1-Base!$B$31)+Base!F59+G$4*Base!F60+Base!F62+Base!F63 -> 732162.95 | F43: =$A$9*Base!G58*(1-Base!$B$31)+Base!G59+G$4*Base!G60+Base!G62+Base!G63 -> 708505.68 | G43: =$A$9*Base!H58*(1-Base!$B$31)+Base!H59+G$4*Base!H60+Base!H62+Base!H63 -> 685140.73 | H43: =$A$9*Base!I58*(1-Base!$B$31)+Base!I59+G$4*Base!I60+Base!I62+Base!I63 -> 662055.68 | I43: =$A$9*Base!J58*(1-Base!$B$31)+Base!J59+G$4*Base!J60+Base!J62+Base!J63 -> 639238.4 | J43: =$A$9*Base!K58*(1-Base!$B$31)+Base!K59+G$4*Base!K60+Base!K62+Base!K63 -> 616677 | K43: =$A$9*Base!L58*(1-Base!$B$31)+Base!L59+G$4*Base!L60+Base!L62+Base!L63 -> 594359.82 | L43: =$A$9*Base!M58*(1-Base!$B$31)+Base!M59+G$4*Base!M60+Base!M62+Base!M63 -> 572275.46 | M43: =$A$9*Base!N58*(1-Base!$B$31)+Base!N59+G$4*Base!N60+Base!N62+Base!N63 -> 550412.7 | N43: =$A$9*Base!O58*(1-Base!$B$31)+Base!O59+G$4*Base!O60+Base!O62+Base!O63 -> 528760.57 | O43: =$A$9*Base!P58*(1-Base!$B$31)+Base!P59+G$4*Base!P60+Base!P62+Base!P63 -> 507308.28 | P43: =$A$9*Base!Q58*(1-Base!$B$31)+Base!Q59+G$4*Base!Q60+Base!Q62+Base!Q63 -> 486045.25 | Q43: =$A$9*Base!R58*(1-Base!$B$31)+Base!R59+G$4*Base!R60+Base!R62+Base!R63 -> 464961.09 | R43: =$A$9*Base!S58*(1-Base!$B$31)+Base!S59+G$4*Base!S60+Base!S62+Base!S63 -> 0 | S43: =$A$9*Base!T58*(1-Base!$B$31)+Base!T59+G$4*Base!T60+Base!T62+Base!T63 -> 0 | T43: =$A$9*Base!U58*(1-Base!$B$31)+Base!U59+G$4*Base!U60+Base!U62+Base!U63 -> 0 | U43: =$A$9*Base!V58*(1-Base!$B$31)+Base!V59+G$4*Base!V60+Base!V62+Base!V63 -> 0 | V43: =$A$9*Base!W58*(1-Base!$B$31)+Base!W59+G$4*Base!W60+Base!W62+Base!W63 -> 0
A44: ="Indtægt "&TEXT($A$10,"0%")&" / investering "&TEXT(B$4,"0%") -> Indtægt 150% / investering 60% | B44: =Base!C65*B$4 -> -3750000 | C44: =$A$10*Base!D58*(1-Base!$B$31)+Base!D59+B$4*Base!D60+Base!D62+Base!D63 -> 1036564.4 | D44: =$A$10*Base!E58*(1-Base!$B$31)+Base!E59+B$4*Base!E60+Base!E62+Base!E63 -> 1010719.3 | E44: =$A$10*Base!F58*(1-Base!$B$31)+Base!F59+B$4*Base!F60+Base!F62+Base!F63 -> 985284.66 | F44: =$A$10*Base!G58*(1-Base!$B$31)+Base!G59+B$4*Base!G60+Base!G62+Base!G63 -> 960246.45 | G44: =$A$10*Base!H58*(1-Base!$B$31)+Base!H59+B$4*Base!H60+Base!H62+Base!H63 -> 935590.92 | H44: =$A$10*Base!I58*(1-Base!$B$31)+Base!I59+B$4*Base!I60+Base!I62+Base!I63 -> 911304.66 | I44: =$A$10*Base!J58*(1-Base!$B$31)+Base!J59+B$4*Base!J60+Base!J62+Base!J63 -> 887374.59 | J44: =$A$10*Base!K58*(1-Base!$B$31)+Base!K59+B$4*Base!K60+Base!K62+Base!K63 -> 863787.94 | K44: =$A$10*Base!L58*(1-Base!$B$31)+Base!L59+B$4*Base!L60+Base!L62+Base!L63 -> 840532.22 | L44: =$A$10*Base!M58*(1-Base!$B$31)+Base!M59+B$4*Base!M60+Base!M62+Base!M63 -> 817595.24 | M44: =$A$10*Base!N58*(1-Base!$B$31)+Base!N59+B$4*Base!N60+Base!N62+Base!N63 -> 794965.09 | N44: =$A$10*Base!O58*(1-Base!$B$31)+Base!O59+B$4*Base!O60+Base!O62+Base!O63 -> 772630.11 | O44: =$A$10*Base!P58*(1-Base!$B$31)+Base!P59+B$4*Base!P60+Base!P62+Base!P63 -> 750578.9 | P44: =$A$10*Base!Q58*(1-Base!$B$31)+Base!Q59+B$4*Base!Q60+Base!Q62+Base!Q63 -> 728800.31 | Q44: =$A$10*Base!R58*(1-Base!$B$31)+Base!R59+B$4*Base!R60+Base!R62+Base!R63 -> 707283.44 | R44: =$A$10*Base!S58*(1-Base!$B$31)+Base!S59+B$4*Base!S60+Base!S62+Base!S63 -> 0 | S44: =$A$10*Base!T58*(1-Base!$B$31)+Base!T59+B$4*Base!T60+Base!T62+Base!T63 -> 0 | T44: =$A$10*Base!U58*(1-Base!$B$31)+Base!U59+B$4*Base!U60+Base!U62+Base!U63 -> 0 | U44: =$A$10*Base!V58*(1-Base!$B$31)+Base!V59+B$4*Base!V60+Base!V62+Base!V63 -> 0 | V44: =$A$10*Base!W58*(1-Base!$B$31)+Base!W59+B$4*Base!W60+Base!W62+Base!W63 -> 0
A45: ="Indtægt "&TEXT($A$10,"0%")&" / investering "&TEXT(C$4,"0%") -> Indtægt 150% / investering 80% | B45: =Base!C65*C$4 -> -5000000 | C45: =$A$10*Base!D58*(1-Base!$B$31)+Base!D59+C$4*Base!D60+Base!D62+Base!D63 -> 1012843.3 | D45: =$A$10*Base!E58*(1-Base!$B$31)+Base!E59+C$4*Base!E60+Base!E62+Base!E63 -> 986523.74 | E45: =$A$10*Base!F58*(1-Base!$B$31)+Base!F59+C$4*Base!F60+Base!F62+Base!F63 -> 960605.21 | F45: =$A$10*Base!G58*(1-Base!$B$31)+Base!G59+C$4*Base!G60+Base!G62+Base!G63 -> 935073.41 | G45: =$A$10*Base!H58*(1-Base!$B$31)+Base!H59+C$4*Base!H60+Base!H62+Base!H63 -> 909914.42 | H45: =$A$10*Base!I58*(1-Base!$B$31)+Base!I59+C$4*Base!I60+Base!I62+Base!I63 -> 885114.63 | I45: =$A$10*Base!J58*(1-Base!$B$31)+Base!J59+C$4*Base!J60+Base!J62+Base!J63 -> 860660.76 | J45: =$A$10*Base!K58*(1-Base!$B$31)+Base!K59+C$4*Base!K60+Base!K62+Base!K63 -> 836539.83 | K45: =$A$10*Base!L58*(1-Base!$B$31)+Base!L59+C$4*Base!L60+Base!L62+Base!L63 -> 812739.15 | L45: =$A$10*Base!M58*(1-Base!$B$31)+Base!M59+C$4*Base!M60+Base!M62+Base!M63 -> 789246.31 | M45: =$A$10*Base!N58*(1-Base!$B$31)+Base!N59+C$4*Base!N60+Base!N62+Base!N63 -> 766049.18 | N45: =$A$10*Base!O58*(1-Base!$B$31)+Base!O59+C$4*Base!O60+Base!O62+Base!O63 -> 743135.88 | O45: =$A$10*Base!P58*(1-Base!$B$31)+Base!P59+C$4*Base!P60+Base!P62+Base!P63 -> 720494.78 | P45: =$A$10*Base!Q58*(1-Base!$B$31)+Base!Q59+C$4*Base!Q60+Base!Q62+Base!Q63 -> 698114.51 | Q45: =$A$10*Base!R58*(1-Base!$B$31)+Base!R59+C$4*Base!R60+Base!R62+Base!R63 -> 675983.93 | R45: =$A$10*Base!S58*(1-Base!$B$31)+Base!S59+C$4*Base!S60+Base!S62+Base!S63 -> 0 | S45: =$A$10*Base!T58*(1-Base!$B$31)+Base!T59+C$4*Base!T60+Base!T62+Base!T63 -> 0 | T45: =$A$10*Base!U58*(1-Base!$B$31)+Base!U59+C$4*Base!U60+Base!U62+Base!U63 -> 0 | U45: =$A$10*Base!V58*(1-Base!$B$31)+Base!V59+C$4*Base!V60+Base!V62+Base!V63 -> 0 | V45: =$A$10*Base!W58*(1-Base!$B$31)+Base!W59+C$4*Base!W60+Base!W62+Base!W63 -> 0
A46: ="Indtægt "&TEXT($A$10,"0%")&" / investering "&TEXT(D$4,"0%") -> Indtægt 150% / investering 90% | B46: =Base!C65*D$4 -> -5625000 | C46: =$A$10*Base!D58*(1-Base!$B$31)+Base!D59+D$4*Base!D60+Base!D62+Base!D63 -> 1000982.7 | D46: =$A$10*Base!E58*(1-Base!$B$31)+Base!E59+D$4*Base!E60+Base!E62+Base!E63 -> 974425.96 | E46: =$A$10*Base!F58*(1-Base!$B$31)+Base!F59+D$4*Base!F60+Base!F62+Base!F63 -> 948265.48 | F46: =$A$10*Base!G58*(1-Base!$B$31)+Base!G59+D$4*Base!G60+Base!G62+Base!G63 -> 922486.89 | G46: =$A$10*Base!H58*(1-Base!$B$31)+Base!H59+D$4*Base!H60+Base!H62+Base!H63 -> 897076.16 | H46: =$A$10*Base!I58*(1-Base!$B$31)+Base!I59+D$4*Base!I60+Base!I62+Base!I63 -> 872019.61 | I46: =$A$10*Base!J58*(1-Base!$B$31)+Base!J59+D$4*Base!J60+Base!J62+Base!J63 -> 847303.84 | J46: =$A$10*Base!K58*(1-Base!$B$31)+Base!K59+D$4*Base!K60+Base!K62+Base!K63 -> 822915.77 | K46: =$A$10*Base!L58*(1-Base!$B$31)+Base!L59+D$4*Base!L60+Base!L62+Base!L63 -> 798842.61 | L46: =$A$10*Base!M58*(1-Base!$B$31)+Base!M59+D$4*Base!M60+Base!M62+Base!M63 -> 775071.84 | M46: =$A$10*Base!N58*(1-Base!$B$31)+Base!N59+D$4*Base!N60+Base!N62+Base!N63 -> 751591.22 | N46: =$A$10*Base!O58*(1-Base!$B$31)+Base!O59+D$4*Base!O60+Base!O62+Base!O63 -> 728388.76 | O46: =$A$10*Base!P58*(1-Base!$B$31)+Base!P59+D$4*Base!P60+Base!P62+Base!P63 -> 705452.72 | P46: =$A$10*Base!Q58*(1-Base!$B$31)+Base!Q59+D$4*Base!Q60+Base!Q62+Base!Q63 -> 682771.62 | Q46: =$A$10*Base!R58*(1-Base!$B$31)+Base!R59+D$4*Base!R60+Base!R62+Base!R63 -> 660334.17 | R46: =$A$10*Base!S58*(1-Base!$B$31)+Base!S59+D$4*Base!S60+Base!S62+Base!S63 -> 0 | S46: =$A$10*Base!T58*(1-Base!$B$31)+Base!T59+D$4*Base!T60+Base!T62+Base!T63 -> 0 | T46: =$A$10*Base!U58*(1-Base!$B$31)+Base!U59+D$4*Base!U60+Base!U62+Base!U63 -> 0 | U46: =$A$10*Base!V58*(1-Base!$B$31)+Base!V59+D$4*Base!V60+Base!V62+Base!V63 -> 0 | V46: =$A$10*Base!W58*(1-Base!$B$31)+Base!W59+D$4*Base!W60+Base!W62+Base!W63 -> 0
A47: ="Indtægt "&TEXT($A$10,"0%")&" / investering "&TEXT(E$4,"0%") -> Indtægt 150% / investering 100% | B47: =Base!C65*E$4 -> -6250000 | C47: =$A$10*Base!D58*(1-Base!$B$31)+Base!D59+E$4*Base!D60+Base!D62+Base!D63 -> 989122.14 | D47: =$A$10*Base!E58*(1-Base!$B$31)+Base!E59+E$4*Base!E60+Base!E62+Base!E63 -> 962328.19 | E47: =$A$10*Base!F58*(1-Base!$B$31)+Base!F59+E$4*Base!F60+Base!F62+Base!F63 -> 935925.75 | F47: =$A$10*Base!G58*(1-Base!$B$31)+Base!G59+E$4*Base!G60+Base!G62+Base!G63 -> 909900.37 | G47: =$A$10*Base!H58*(1-Base!$B$31)+Base!H59+E$4*Base!H60+Base!H62+Base!H63 -> 884237.91 | H47: =$A$10*Base!I58*(1-Base!$B$31)+Base!I59+E$4*Base!I60+Base!I62+Base!I63 -> 858924.59 | I47: =$A$10*Base!J58*(1-Base!$B$31)+Base!J59+E$4*Base!J60+Base!J62+Base!J63 -> 833946.93 | J47: =$A$10*Base!K58*(1-Base!$B$31)+Base!K59+E$4*Base!K60+Base!K62+Base!K63 -> 809291.72 | K47: =$A$10*Base!L58*(1-Base!$B$31)+Base!L59+E$4*Base!L60+Base!L62+Base!L63 -> 784946.08 | L47: =$A$10*Base!M58*(1-Base!$B$31)+Base!M59+E$4*Base!M60+Base!M62+Base!M63 -> 760897.38 | M47: =$A$10*Base!N58*(1-Base!$B$31)+Base!N59+E$4*Base!N60+Base!N62+Base!N63 -> 737133.26 | N47: =$A$10*Base!O58*(1-Base!$B$31)+Base!O59+E$4*Base!O60+Base!O62+Base!O63 -> 713641.64 | O47: =$A$10*Base!P58*(1-Base!$B$31)+Base!P59+E$4*Base!P60+Base!P62+Base!P63 -> 690410.67 | P47: =$A$10*Base!Q58*(1-Base!$B$31)+Base!Q59+E$4*Base!Q60+Base!Q62+Base!Q63 -> 667428.72 | Q47: =$A$10*Base!R58*(1-Base!$B$31)+Base!R59+E$4*Base!R60+Base!R62+Base!R63 -> 644684.41 | R47: =$A$10*Base!S58*(1-Base!$B$31)+Base!S59+E$4*Base!S60+Base!S62+Base!S63 -> 0 | S47: =$A$10*Base!T58*(1-Base!$B$31)+Base!T59+E$4*Base!T60+Base!T62+Base!T63 -> 0 | T47: =$A$10*Base!U58*(1-Base!$B$31)+Base!U59+E$4*Base!U60+Base!U62+Base!U63 -> 0 | U47: =$A$10*Base!V58*(1-Base!$B$31)+Base!V59+E$4*Base!V60+Base!V62+Base!V63 -> 0 | V47: =$A$10*Base!W58*(1-Base!$B$31)+Base!W59+E$4*Base!W60+Base!W62+Base!W63 -> 0
A48: ="Indtægt "&TEXT($A$10,"0%")&" / investering "&TEXT(F$4,"0%") -> Indtægt 150% / investering 110% | B48: =Base!C65*F$4 -> -6875000 | C48: =$A$10*Base!D58*(1-Base!$B$31)+Base!D59+F$4*Base!D60+Base!D62+Base!D63 -> 977261.58 | D48: =$A$10*Base!E58*(1-Base!$B$31)+Base!E59+F$4*Base!E60+Base!E62+Base!E63 -> 950230.42 | E48: =$A$10*Base!F58*(1-Base!$B$31)+Base!F59+F$4*Base!F60+Base!F62+Base!F63 -> 923586.03 | F48: =$A$10*Base!G58*(1-Base!$B$31)+Base!G59+F$4*Base!G60+Base!G62+Base!G63 -> 897313.85 | G48: =$A$10*Base!H58*(1-Base!$B$31)+Base!H59+F$4*Base!H60+Base!H62+Base!H63 -> 871399.66 | H48: =$A$10*Base!I58*(1-Base!$B$31)+Base!I59+F$4*Base!I60+Base!I62+Base!I63 -> 845829.58 | I48: =$A$10*Base!J58*(1-Base!$B$31)+Base!J59+F$4*Base!J60+Base!J62+Base!J63 -> 820590.01 | J48: =$A$10*Base!K58*(1-Base!$B$31)+Base!K59+F$4*Base!K60+Base!K62+Base!K63 -> 795667.66 | K48: =$A$10*Base!L58*(1-Base!$B$31)+Base!L59+F$4*Base!L60+Base!L62+Base!L63 -> 771049.54 | L48: =$A$10*Base!M58*(1-Base!$B$31)+Base!M59+F$4*Base!M60+Base!M62+Base!M63 -> 746722.91 | M48: =$A$10*Base!N58*(1-Base!$B$31)+Base!N59+F$4*Base!N60+Base!N62+Base!N63 -> 722675.31 | N48: =$A$10*Base!O58*(1-Base!$B$31)+Base!O59+F$4*Base!O60+Base!O62+Base!O63 -> 698894.53 | O48: =$A$10*Base!P58*(1-Base!$B$31)+Base!P59+F$4*Base!P60+Base!P62+Base!P63 -> 675368.61 | P48: =$A$10*Base!Q58*(1-Base!$B$31)+Base!Q59+F$4*Base!Q60+Base!Q62+Base!Q63 -> 652085.82 | Q48: =$A$10*Base!R58*(1-Base!$B$31)+Base!R59+F$4*Base!R60+Base!R62+Base!R63 -> 629034.66 | R48: =$A$10*Base!S58*(1-Base!$B$31)+Base!S59+F$4*Base!S60+Base!S62+Base!S63 -> 0 | S48: =$A$10*Base!T58*(1-Base!$B$31)+Base!T59+F$4*Base!T60+Base!T62+Base!T63 -> 0 | T48: =$A$10*Base!U58*(1-Base!$B$31)+Base!U59+F$4*Base!U60+Base!U62+Base!U63 -> 0 | U48: =$A$10*Base!V58*(1-Base!$B$31)+Base!V59+F$4*Base!V60+Base!V62+Base!V63 -> 0 | V48: =$A$10*Base!W58*(1-Base!$B$31)+Base!W59+F$4*Base!W60+Base!W62+Base!W63 -> 0
A49: ="Indtægt "&TEXT($A$10,"0%")&" / investering "&TEXT(G$4,"0%") -> Indtægt 150% / investering 120% | B49: =Base!C65*G$4 -> -7500000 | C49: =$A$10*Base!D58*(1-Base!$B$31)+Base!D59+G$4*Base!D60+Base!D62+Base!D63 -> 965401.02 | D49: =$A$10*Base!E58*(1-Base!$B$31)+Base!E59+G$4*Base!E60+Base!E62+Base!E63 -> 938132.65 | E49: =$A$10*Base!F58*(1-Base!$B$31)+Base!F59+G$4*Base!F60+Base!F62+Base!F63 -> 911246.3 | F49: =$A$10*Base!G58*(1-Base!$B$31)+Base!G59+G$4*Base!G60+Base!G62+Base!G63 -> 884727.33 | G49: =$A$10*Base!H58*(1-Base!$B$31)+Base!H59+G$4*Base!H60+Base!H62+Base!H63 -> 858561.41 | H49: =$A$10*Base!I58*(1-Base!$B$31)+Base!I59+G$4*Base!I60+Base!I62+Base!I63 -> 832734.56 | I49: =$A$10*Base!J58*(1-Base!$B$31)+Base!J59+G$4*Base!J60+Base!J62+Base!J63 -> 807233.09 | J49: =$A$10*Base!K58*(1-Base!$B$31)+Base!K59+G$4*Base!K60+Base!K62+Base!K63 -> 782043.61 | K49: =$A$10*Base!L58*(1-Base!$B$31)+Base!L59+G$4*Base!L60+Base!L62+Base!L63 -> 757153 | L49: =$A$10*Base!M58*(1-Base!$B$31)+Base!M59+G$4*Base!M60+Base!M62+Base!M63 -> 732548.44 | M49: =$A$10*Base!N58*(1-Base!$B$31)+Base!N59+G$4*Base!N60+Base!N62+Base!N63 -> 708217.35 | N49: =$A$10*Base!O58*(1-Base!$B$31)+Base!O59+G$4*Base!O60+Base!O62+Base!O63 -> 684147.41 | O49: =$A$10*Base!P58*(1-Base!$B$31)+Base!P59+G$4*Base!P60+Base!P62+Base!P63 -> 660326.55 | P49: =$A$10*Base!Q58*(1-Base!$B$31)+Base!Q59+G$4*Base!Q60+Base!Q62+Base!Q63 -> 636742.92 | Q49: =$A$10*Base!R58*(1-Base!$B$31)+Base!R59+G$4*Base!R60+Base!R62+Base!R63 -> 613384.9 | R49: =$A$10*Base!S58*(1-Base!$B$31)+Base!S59+G$4*Base!S60+Base!S62+Base!S63 -> 0 | S49: =$A$10*Base!T58*(1-Base!$B$31)+Base!T59+G$4*Base!T60+Base!T62+Base!T63 -> 0 | T49: =$A$10*Base!U58*(1-Base!$B$31)+Base!U59+G$4*Base!U60+Base!U62+Base!U63 -> 0 | U49: =$A$10*Base!V58*(1-Base!$B$31)+Base!V59+G$4*Base!V60+Base!V62+Base!V63 -> 0 | V49: =$A$10*Base!W58*(1-Base!$B$31)+Base!W59+G$4*Base!W60+Base!W62+Base!W63 -> 0

Sheet Kilder
A1: Kilde | B1: Dato | C1: Bruges til | D1: Link
A2: Energinet, Energi Data Service: Elspotprices, DayAheadPrices, AfrrReservesNordic, FcrDK1, mFRRCapacityMarket (DK1) | B2: hentet 13.10.2026 | C2: Backtest af indtjening og prisudvikling | D2: https://www.energidataservice.dk
A3: Energinet: Energinet sænker elforbrugernes tariffer yderligere (Via Ritzau) | B3: 04.09.2026 | C3: Energinets forbrugs-, indfødnings- og balancetarif 2027 og tarifloft | D3: https://via.ritzau.dk/pressemeddelelse/15138077/energinet-saenker-elforbrugernes-tariffer-yderligere
A4: Elnet.dk (Green Power Denmark): Tarifering af batterier og ellager | B4: ikke dateret | C4: Batterier betaler forbrugs- og indfødningstarif; intet tilslutningsbidrag ved brug af eksisterende kapacitet | D4: https://elnet.dk/nettariffer-priser-gebyrer/tarifering-batterier-ellager
A5: Lov nr. 1775 af 29.12.2025 om nedsættelse af elafgiften i 2026 og 2027 | B5: 29.12.2025 | C5: Elafgift 0,8 øre/kWh 2026-27, 60,9 øre fra 2028 | D5: https://www.retsinformation.dk/eli/lta/2025/1775/pdf
A6: Skattestyrelsen: Midlertidig nedsættelse af elafgiften i 2026 og 2027 | B6: 2025 | C6: Godtgørelse ned til 0,4 øre/kWh for momsreg. virksomheder | D6: https://skat.dk/erhverv/afgifter-paa-varer-og-ydelser-punktafgifter/nyhedsbrev-afgifter/midlertidig-nedsaettelse-af-elafgiften-i-2026-og-2027
A7: Modo Energy: German BESS investment outlook Q2 2026, executive summary | B7: 16.03.2026 | C7: Capex-reference 2h/4h og IRR-reference (Tyskland, ikke DK1) | D7: https://modoenergy.com/research/en/germany-battery-investment-outlook-q2-2026-executive-summary
A8: Energy-Storage.news om BNEF Energy Storage Systems Cost Survey 2025 | B8: dec. 2025 | C8: Turnkey-pris Europa 177 USD/kWh ekskl. EPC og nettilslutning | D8: https://www.energy-storage.news/?p=92133
A9: Dansk Fjernvarme: Ringkøbing vinker farvel til gas | B9: 30.07.2025 | C9: RFV's anlæg: elkedel og gasmotorer på elmarkedet, 500 MWh akkutanke, fase 1 og 2 | D9: https://danskfjernvarme.dk/aktuelt/nyheder/2025/ringkoebing-vinker-farvel-til-gas
A10: Radius Elnet: Tilslutning af batterier | B10: ikke dateret | C10: Proces og krav ved batteritilslutning (Radius' område, kun som indikation) | D10: https://radiuselnet.dk/ny-tilslutning/tilslutning/tilslutning-af-batterier/
A11: Energistyrelsen: Energifællesskab Rødkærsbro Fjernvarmeværk og Nordic Energy Storage | B11: 12.02.2025 | C11: Præcedens: batteri på fjernvarmeværk | D11: https://ens.dk/media/7751/download
